Workbook
Name referenciaTD: #REF!
Name referenciaTD: #REF!
Name referenciaTD: #REF!
Name referenciaTD: #REF!
Name referenciaTD: #REF!
Name referenciaTD: #REF!
Name referenciaTD: #REF!
Name referenciaTD: #REF!
Name referenciaTD: #REF!
Name referenciaTD: #REF!
Name referenciaTD: #REF!
Name referenciaTD: #REF!
Name referenciaTD: #REF!
Name referenciaTD: #REF!
Name referenciaTD: #REF!
Name referenciaTD: #REF!
Name SegmentaciónDeDatos_centroCosto: #N/A
Name SegmentaciónDeDatos_Comprobante: #N/A
Name SegmentaciónDeDatos_Comprobante1: #N/A
Name SegmentaciónDeDatos_DateHierarchy: #N/A
Name SegmentaciónDeDatos_fecha__año: #N/A
Name SegmentaciónDeDatos_Mes__mmm: #N/A
Name SegmentaciónDeDatos_Mes__mmm1: #N/A
Name SegmentaciónDeDatos_Unidad: #N/A

Sheet Selectores
I2: Mes del reporte | N2: Que no esté seleccionado :
F3: Cuando esté el 3000 seleccionar | N3: 01 ING TI IDIEM FACT
N4: 05 PROV ING TI IDIEM FACT
N5: 06 REV PROV ING TI IDIEM FACT
N6: 04 TRAS RECLASIFICA TI
N8: Ojo si hay reclasificaciones, también hay que sacarlo, pero ojalá no saque otras reclasificaciones que no hay que sacar
A28: Meses año actual para el Salesforce

Sheet Indicaciones SGC
A1: Indicaciones
A3: 0. Actualizar
A4: 1. Actualizar hoja "Selectores"
A5: 2. Al cambiar año actualizar la fecha en hoja "Año_reporte", debe ser el último día del año.
A6: 3. Seguir pasos de hoja "Indicaciones GCO"

Sheet Indicaciones GCO
A1: Indicaciones
A3: 0. Solo limitarse a seguir estos pasos.
A4: 1. Actualizar hoja "Reporte Salesforce". Esta hoja se encuentra vinculada una consulta de Salesforce y se actualiza cada 4 horas partiendo a las 7:20.
A5: 2. En hoja "Cuadratura" verificar que todas las celdas marcadas en amarillo sean 0.
A6: 3. En hoja "BBDD Gráficos" verificar que todas las celdas marcadas en amarillo sean 0.

Sheet Reporte Salesforce
A1: Rut Empresa | B1: Nombre de la cuenta | C1: Nombre de la oportunidad | D1: Etapa | E1: Monto | F1: Contador de cuotas | G1: Fecha de cierre del Negocio | H1: Unidad | I1: División | J1: Sección | K1: Presupuesto sincronizado | L1: Fecha de Pago | M1: Traspaso interno
A2: 760779946 | B2: Sociedad LEM Laboratorios & Asistencia Técnica Limitada | C2: PR.DHI.SHI.2026-0777 | D2: Cerrada ganada | E2: 2018731 | F2: 1 | G2: 46213 | H2: 1815 UFMA- Laboratorio de Áridos | I2: DHI | J2: SHI - Sección Hormigones Ingeniería | K2: Análisis físico-mecánicos y químicos en muestra(s) de árido(s). | L2: 46213 | M2: FALSO
A3: 761097792 | B3: MELÓN S.A. | C3: PR.DHI.SHI.2026-0905 | D3: Cerrada ganada | E3: 3935811 | F3: 1 | G3: 46211 | H3: 1815 UFMA- Laboratorio de Áridos | I3: DHI | J3: SHI - Sección Hormigones Ingeniería | K3: Caracterización de áridos planta Osorno M-4055231 | L3: 46211 | M3: FALSO
A4: 969369109 | B4: INDUSTRIA DE TUBOS Y PREFABRICADOS DE HORMIGON BUDNIK S A | C4: PR.DHI.SHI.2026-0564 | D4: Cerrada ganada | E4: 304723 | F4: 1 | G4: 46209 | H4: 1815 UFMA- Laboratorio de Áridos | I4: DHI | J4: SHI - Sección Hormigones Ingeniería | K4: Análisis físico-mecánico a muestra(s) de árido(s) | L4: 46209 | M4: FALSO
A5: 761097792 | B5: MELÓN S.A. | C5: PR.DHI.SHI.2026-0876 | D5: Cerrada ganada | E5: 3826399 | F5: 1 | G5: 46205 | H5: 1815 UFMA- Laboratorio de Áridos | I5: DHI | J5: SHI - Sección Hormigones Ingeniería | K5: Caracterización de áridos planta Villarrica M-4055191 | L5: 46205 | M5: FALSO
A6: 761097792 | B6: MELÓN S.A. | C6: PR.DHI.SHI.2026-0875 | D6: Cerrada ganada | E6: 5056711 | F6: 1 | G6: 46205 | H6: 1815 UFMA- Laboratorio de Áridos | I6: DHI | J6: SHI - Sección Hormigones Ingeniería | K6: Caracterización de áridos planta Temuco M-4055190 | L6: 46205 | M6: FALSO
A7: 760779946 | B7: Sociedad LEM Laboratorios & Asistencia Técnica Limitada | C7: PR.DHI.SHI.2026-0519 | D7: Cerrada ganada | E7: 1217226 | F7: 1 | G7: 46198 | H7: 1815 UFMA- Laboratorio de Áridos | I7: DHI | J7: SHI - Sección Hormigones Ingeniería | K7: Análisis físico-mecánicos y químicos en muestra(s) de árido(s). | L7: 46198 | M7: FALSO
A8: 760779946 | B8: Sociedad LEM Laboratorios & Asistencia Técnica Limitada | C8: PR.DHI.SHI.2026-0520 | D8: Cerrada ganada | E8: 1216826 | F8: 1 | G8: 46198 | H8: 1815 UFMA- Laboratorio de Áridos | I8: DHI | J8: SHI - Sección Hormigones Ingeniería | K8: Análisis físico-mecánicos y químicos en muestra(s) de árido(s). | L8: 46198 | M8: FALSO
A9: 761097792 | B9: MELÓN S.A. | C9: PR.DHI.SHI.2026-0850 | D9: Cerrada ganada | E9: 1309996 | F9: 1 | G9: 46197 | H9: 1815 UFMA- Laboratorio de Áridos | I9: DHI | J9: SHI - Sección Hormigones Ingeniería | K9: Caracterización de árido planta Osorno - Vicat Pozo Cachillahue M-28579 | L9: 46197 | M9: FALSO
A10: 761097792 | B10: MELÓN S.A. | C10: PR.DHI.SHI.2026-0826 | D10: Cerrada ganada | E10: 4055745 | F10: 1 | G10: 46191 | H10: 1815 UFMA- Laboratorio de Áridos | I10: DHI | J10: SHI - Sección Hormigones Ingeniería | K10: Caracterización de áridos planta Castro M-4055393 | L10: 46191 | M10: FALSO
A11: 761097792 | B11: MELÓN S.A. | C11: PR.DHI.SHI.2026-0827 | D11: Cerrada ganada | E11: 4065449 | F11: 1 | G11: 46191 | H11: 1815 UFMA- Laboratorio de Áridos | I11: DHI | J11: SHI - Sección Hormigones Ingeniería | K11: Caracterización de áridos planta Chadmo M-4055320 | L11: 46191 | M11: FALSO
A12: 78465110K | B12: MELÓN ÁRIDOS LIMITADA | C12: PR.DHI.SHI.2026-0823 | D12: Cerrada ganada | E12: 906344 | F12: 1 | G12: 46191 | H12: 1815 UFMA- Laboratorio de Áridos | I12: DHI | J12: SHI - Sección Hormigones Ingeniería | K12: Control de áridos mensual planta PSB Junio M-4068150 | L12: 46191 | M12: FALSO
A13: 78465110K | B13: MELÓN ÁRIDOS LIMITADA | C13: PR.DHI.SHI.2026-0825 | D13: Cerrada ganada | E13: 842099 | F13: 1 | G13: 46191 | H13: 1815 UFMA- Laboratorio de Áridos | I13: DHI | J13: SHI - Sección Hormigones Ingeniería | K13: Control de áridos mensual planta Las Garzas Junio M-4067893 | L13: 46191 | M13: FALSO
... A387: 763034704 | B387: SANTA LAURA HORMIGONES SPA | C387: PR.DHI.SHI.2026-0013 | D387: Cerrada ganada | E387: 868549 | F387: 1 | G387: 46100 | H387: 2318 UHI - Unidad Hormigones Ingeniería | I387: DHI | J387: SHI - Sección Hormigones Ingeniería | K387: Curva de madurez para muestreo en obra | L387: 46100 | M387: FALSO
B388: CODELCO DIVISION EL TENIENTE | C388: PR.DHI.SHI.2024-0243 | D388: Cerrada ganada | E388: 0 | F388: 1 | G388: 46098 | H388: 2318 UHI - Unidad Hormigones Ingeniería | I388: DHI | J388: SHI - Sección Hormigones Ingeniería | K388: Determinación del porcentaje máximo de reemplazo de relave de cobre como arena en 3 tipos de hormigones | L388: 46098 | M388: FALSO
A389: 769103600 | B389: CONSTRUCTORA SANTOLAYA LTDA | C389: PR.DHI.SHI.2026-0192 Lechada en obra | D389: Cerrada ganada | E389: 1035885 | F389: 1 | G389: 46098 | H389: 2935 LM - Laboratorio Mortero de Prueba | I389: DHI | J389: SHI - Sección Hormigones Ingeniería | K389: Ensayos físicos realizados en terreno | L389: 46098 | M389: FALSO
A390: 898536009 | B390: CONSTRUCTORA INGEVEC S.A. | C390: PR.DHI.SHI.2026-0086 | D390: Cerrada ganada | E390: 5969086 | F390: 1 | G390: 46097 | H390: 2318 UHI - Unidad Hormigones Ingeniería | I390: DHI | J390: SHI - Sección Hormigones Ingeniería | K390: Exploración del hormigón y armadura de elementos pertenecientes al edificio El Aromo | L390: 46097 | M390: FALSO
A391: 781028649 | B391: CONSORCIO BAHIA FILDES SPA | C391: PR.DHI.SHI.2025-0207 | D391: Cerrada ganada | E391: 3252678 | F391: 1 | G391: 46097 | H391: 2935 LM - Laboratorio Mortero de Prueba | I391: DHI | J391: SHI - Sección Hormigones Ingeniería | K391: Ensayo de permeabilidad al agua en probetas moldeadas | L391: 46097 | M391: FALSO
A392: 590593400 | B392: OBRASCÓN HUARTE LAIN S A AGENCIA EN CHILE | C392: PR.DHI.SHI.2026-0034-A | D392: Cerrada ganada | E392: 0 | F392: 1 | G392: 46097 | H392: 2318 UHI - Unidad Hormigones Ingeniería | I392: DHI | J392: SHI - Sección Hormigones Ingeniería | K392: Evaluación Mediante Ultrasonido Del Hormigón De De La Losa Superior De Un Sector Del Túnel Lo Ruiz | L392: 46097 | M392: FALSO
A393: 868567007 | B393: CONSTRUCTORA NOVATEC S.A. | C393: PR.DHI.SHI.2025-1013 | D393: Cerrada ganada | E393: 4661481 | F393: 1 | G393: 46094 | H393: 2935 LM - Laboratorio Mortero de Prueba | I393: DHI | J393: SHI - Sección Hormigones Ingeniería | K393: Ensayos de adherencia efectuados en terreno | L393: 46094 | M393: FALSO
A394: 765252903 | B394: EBCO S.A. | C394: PR.DHI.SHI.2025-1380 | D394: Cerrada ganada | E394: 617547 | F394: 1 | G394: 46091 | H394: 2935 LM - Laboratorio Mortero de Prueba | I394: DHI | J394: SHI - Sección Hormigones Ingeniería | K394: Ensayos físicos realizados en terreno | L394: 46091 | M394: FALSO
A395: 592334100 | B395: China First Highway Engineering Co. Ltd. Agencia En Chile | C395: PR.DHI.SHI.2026-0100-A | D395: Cerrada ganada | E395: 4900110 | F395: 1 | G395: 46086 | H395: 2318 UHI - Unidad Hormigones Ingeniería | I395: DHI | J395: SHI - Sección Hormigones Ingeniería | K395: Evaluación mediante testigos y ultrasonido de las fisuras en el hormigón de una losa en la Central Hidroeléctrica Rucalhue. | L395: 46086 | M395: FALSO
A396: 72307267 | B396: Luis Horacio Olave Polanco | C396: PR.DHI.SHI.2025-1430 | D396: Cerrada ganada | E396: 1504944 | F396: 1 | G396: 46085 | H396: 2318 UHI - Unidad Hormigones Ingeniería | I396: DHI | J396: SHI - Sección Hormigones Ingeniería | K396: Dosificación de hormigones | L396: 46085 | M396: FALSO
A397: 763508714 | B397: AISLANTES NACIONALES SPA | C397: PR.DHI.SHI.2026-0015 | D397: Cerrada ganada | E397: 2582044 | F397: 1 | G397: 46069 | H397: 2935 LM - Laboratorio Mortero de Prueba | I397: DHI | J397: SHI - Sección Hormigones Ingeniería | K397: Ensayos Físicos a Morteros | L397: 46080 | M397: FALSO
A398: 766592007 | B398: CONSTRUCTORA PAZ SPA | C398: PR.DHI.SHI.2026-0037 | D398: Cerrada ganada | E398: 1212058 | F398: 1 | G398: 46064 | H398: 2935 LM - Laboratorio Mortero de Prueba | I398: DHI | J398: SHI - Sección Hormigones Ingeniería | K398: Ensayo de Adherencia en terrreno | L398: 46080 | M398: FALSO
A399: 968897802 | B399: CONSTRUCTORA JORGE CARRASCO FARIAS SPA | C399: PR.DHI.SHI.2026-0182 | D399: Cerrada ganada | E399: 615964 | F399: 1 | G399: 46065 | H399: 2935 LM - Laboratorio Mortero de Prueba | I399: DHI | J399: SHI - Sección Hormigones Ingeniería | K399: Ensayo de Adherencia en Terreno | L399: 46080 | M399: FALSO
A400: 765252903 | B400: EBCO S.A. | C400: PR.DHI.SHI.2025-1541 | D400: Cerrada ganada | E400: 1231524 | F400: 1 | G400: 46064 | H400: 2935 LM - Laboratorio Mortero de Prueba | I400: DHI | J400: SHI - Sección Hormigones Ingeniería | K400: Ensayo de Adherencia en Terreno | L400: 46080 | M400: FALSO
... A832: 760934542 | B832: SAN JOSE CONSTRUCTORA CHILE S.A. | C832: PR.DES.2021-183 | D832: Cerrada ganada | E832: 2203046 | F832: 1 | G832: 44616 | H832: 2124 UIE - Unidad Inspección Especialista | I832: DES | J832: SEP - Sección Especialidades | K832: MEDICIÓN DE RESISTENCIA ELÉCTRICA DE PISOS DE PABELLONES DE HOSPITAL DE HUASCO | L832: 46382 | M832: FALSO
B833: CODELCO VICEPRESIDENCIA DE PROYECTOS | C833: PR.DGI.2022-015_I Otros Tranques (Descontable Orden de Cambio 15) | D833: Cerrada ganada | E833: 34341656 | F833: 1 | G833: 44864 | H833: 1785 USJ - Unidad Sondajes | I833: DGI | J833: SPG - Sección Prospecciones Geotécnicas | K833: Orden de Cambio 15 | L833: 46363 | M833: FALSO
A834: 898536009 | B834: CONSTRUCTORA INGEVEC S.A. | C834: PR.DTC.2026.0115 - Estudio Ventanas El Aromo La Florida | D834: Cerrada ganada | E834: 1 | F834: 1 | G834: 46058 | H834: 3149 RMP - RENAM Privado | I834: DTC | J834: SET - Sección Estudios | K834: PR.DTC.2026.0115 | L834: 46356 | M834: FALSO
A835: 898536009 | B835: CONSTRUCTORA INGEVEC S.A. | C835: PR.DTC.2026.0099 - Estudio Ventanas Franklin Sinergia | D835: Cerrada ganada | E835: 1 | F835: 1 | G835: 45988 | H835: 3149 RMP - RENAM Privado | I835: DTC | J835: SET - Sección Estudios | K835: PR.DTC.2026.0099 | L835: 46356 | M835: FALSO
A836: 898536009 | B836: CONSTRUCTORA INGEVEC S.A. | C836: PR.DTC.2026.0100 - Estudio Ventanas Las Quemas II | D836: Cerrada ganada | E836: 1 | F836: 1 | G836: 45988 | H836: 3149 RMP - RENAM Privado | I836: DTC | J836: SET - Sección Estudios | K836: PR.DTC.2026.0100 | L836: 46356 | M836: FALSO
A837: 898536009 | B837: CONSTRUCTORA INGEVEC S.A. | C837: PR.DTC.2026.0102 - Estudio Ventanas Nueva Esmeralda | D837: Cerrada ganada | E837: 1 | F837: 1 | G837: 46014 | H837: 3149 RMP - RENAM Privado | I837: DTC | J837: SET - Sección Estudios | K837: PR.DTC.2026.0102 | L837: 46356 | M837: FALSO
A838: 898536009 | B838: CONSTRUCTORA INGEVEC S.A. | C838: PR.DTC.2026.0116 - Estudio Ventanas Briones Luco Patagon | D838: Cerrada ganada | E838: 1 | F838: 1 | G838: 46058 | H838: 3149 RMP - RENAM Privado | I838: DTC | J838: SET - Sección Estudios | K838: PR.DTC.2026.0116 | L838: 46356 | M838: FALSO
A839: 898536009 | B839: CONSTRUCTORA INGEVEC S.A. | C839: PR.DTC.2026.0101 - Estudio Ventanas Miraflores Ayacucho | D839: Cerrada ganada | E839: 1 | F839: 1 | G839: 46037 | H839: 3149 RMP - RENAM Privado | I839: DTC | J839: SET - Sección Estudios | K839: PR.DTC.2026.0101 | L839: 46356 | M839: FALSO
A840: 898536009 | B840: CONSTRUCTORA INGEVEC S.A. | C840: PR.DTC.2026.0382 - Estudio Ventanas Diagonal Paraguay | D840: Cerrada ganada | E840: 1 | F840: 1 | G840: 46133 | H840: 3149 RMP - RENAM Privado | I840: DTC | J840: SET - Sección Estudios | K840: PR.DTC.2026.0382 | L840: 46356 | M840: FALSO
A841: 781329479 | B841: Inmobiliaria Actual Lira SpA | C841: PR.DES.2026-90 | D841: Cerrada ganada | E841: 6123863 | F841: 1 | G841: 46205 | H841: 2124 UIE - Unidad Inspección Especialista | I841: DES | J841: SEP - Sección Especialidades | K841: Edificio Lira | L841: 46325 | M841: FALSO
A842: 2366 | B842: DIVISIÓN INSPECCIÓN DE OBRAS | C842: PR.DES.2020-166 | D842: Cerrada ganada | E842: 2292802 | F842: 1 | G842: 44053 | H842: 2124 UIE - Unidad Inspección Especialista | I842: DES | J842: SEP - Sección Especialidades | K842: Sevilla Norte | L842: 46295 | M842: FALSO
A843: 898536009 | B843: CONSTRUCTORA INGEVEC S.A. | C843: PR.DES.2025-89 | D843: Cerrada ganada | E843: 6277712 | F843: 1 | G843: 45826 | H843: 2124 UIE - Unidad Inspección Especialista | I843: DES | J843: SEP - Sección Especialidades | K843: Edificios Domeyko y San Ignacio | L843: 46289 | M843: FALSO
A844: 609100001 | B844: UNIVERSIDAD DE CHILE | C844: PR.DES.2026-108 | D844: Cerrada ganada | E844: 7348635 | F844: 1 | G844: 46205 | H844: 2124 UIE - Unidad Inspección Especialista | I844: DES | J844: SEP - Sección Especialidades | K844: Diagnostico Ascensores Torre 15 | L844: 46289 | M844: FALSO
A845: 609100001 | B845: UNIVERSIDAD DE CHILE | C845: PR.DTC.2025.0795 - Análisis ingeniería | D845: Cerrada ganada | E845: 3915875 | F845: 1 | G845: 45876 | H845: 2118 ICI - Ingenieria contra Incendios | I845: DTC | J845: SET - Sección Estudios | K845: PR.DTC.2025.0795 | L845: 46265 | M845: FALSO
... A848: 76048251K | B848: CONSTRUCTORA INMOBILIARIA E INVERSIONES OVAL LIMITADA | C848: PR.DES.2026-103 | D848: Cerrada ganada | E848: 3062747 | F848: 1 | G848: 46209 | H848: 2124 UIE - Unidad Inspección Especialista | I848: DES | J848: SEP - Sección Especialidades | K848: Condominio Vista Parque | L848: 46262 | M848: FALSO
B849: MINISTERIO DE VIVIENDA Y URBANISMO | C849: PR.DTC.2026.0304 - REV PROYECTO EL OLIVAR - INCENDIOS | D849: Cerrada ganada | E849: 8168414 | F849: 1 | G849: 46112 | H849: 2118 ICI - Ingenieria contra Incendios | I849: DTC | J849: SET - Sección Estudios | K849: PR.DTC.2026.0304 | L849: 46234 | M849: FALSO
A850: 861603008 | B850: BHP CHILE INC | C850: PR.DGI.2026-019 Servicio de Geofísica Proyecto Spence Chalcopyrite Leaching Ripios Disposal (SCPY-RD) | D850: Cerrada ganada | E850: 81983581 | F850: 1 | G850: 46070 | H850: 1787 UIG - Unidad Ingeniería Geotécnica | I850: DGI | J850: SIG - Sección Ingeniería Geotécnica | K850: Servicio de Geofísica Proyecto Spence Chalcopyrite Leaching Ripios Disposal (SCPY-RD) | L850: 46234 | M850: FALSO
A851: 788937709 | B851: RGM MALLAS DE ALAMBRE LIMITADA | C851: PR.DEP.2026.0160 Ensayos a sistemas de fortificación de túnel | D851: Cerrada ganada | E851: 2450524.2 | F851: 1 | G851: 46211 | H851: 2121 UES - Unidad Ensayos Estructurales | I851: DEP | J851: Sin sección DEP | K851: PR.DEP.2026-0160 | L851: 46234 | M851: FALSO
A852: 612190003 | B852: EMPRESA DE TRANSPORTE DE PASAJEROS METRO S A | C852: PR.DES.2026-82 | D852: Cerrada ganada | E852: 2286394 | F852: 1 | G852: 46206 | H852: 2124 UIE - Unidad Inspección Especialista | I852: DES | J852: SEP - Sección Especialidades | K852: ENSAYOS ELÉCTRICOS POR FALLA DE DISYUNTOR EN ESTACION VIVACETA DE METRO DE SANTIAGO. | L852: 46234 | M852: FALSO
A853: 798532804 | B853: Besalco Desarrollos Inmobiliarios S.A. | C853: PR.DEP.2026.0139 Ensayos carga transversal a panel | D853: Cerrada ganada | E853: 3880255 | F853: 1 | G853: 46216 | H853: 2121 UES - Unidad Ensayos Estructurales | I853: DEP | J853: Sin sección DEP | K853: PR.DEP.2026-0139 | L853: 46234 | M853: FALSO
A854: 783463903 | B854: MC LARENS TOPLIS CHILE LTDA. | C854: PR.DTC.2026.0525 - Peritaje causa-origen | D854: Cerrada ganada | E854: 8919475 | F854: 1 | G854: 46169 | H854: 2118 ICI - Ingenieria contra Incendios | I854: DTC | J854: SET - Sección Estudios | K854: PR.DTC.2026.0525 | L854: 46234 | M854: FALSO
A855: 764303482 | B855: Inversiones Y Comercio RGP SpA | C855: PR.DEP.2026.0168 Ensayos de tracción a barras autoperforantes | D855: Cerrada ganada | E855: 612101 | F855: 1 | G855: 46198 | H855: 2121 UES - Unidad Ensayos Estructurales | I855: DEP | J855: Sin sección DEP | K855: PR.DEP.2026-0168 | L855: 46234 | M855: FALSO
A856: 96594270K | B856: VIOLLIER Y ASOCIADOS LIQUIDADORES DE SEGUROS LIMITADA | C856: PR.DTC.2026.0535 - Peritaje Causa-Origen | D856: Cerrada ganada | E856: 9730337 | F856: 1 | G856: 46170 | H856: 2118 ICI - Ingenieria contra Incendios | I856: DTC | J856: SET - Sección Estudios | K856: PR.DTC.2026.0535 | L856: 46234 | M856: FALSO
A857: 769210261 | B857: CONSTRUCTORA DE INFRAESTRUCTURA DE CHILE SPA | C857: PR.DIC.2026-027 | D857: Cerrada ganada | E857: 9791657 | F857: 1 | G857: 46196 | H857: 2343 UEP - Unidad Estudios y Peritajes | I857: DIC | J857: Sin sección DIC | K857: INFORME TÉCNICO DE CÁLCULO DE DAÑOS ASOCIADOS A LOS PERJUICIOS SUFRIDOS POR CICH EN EL PROYECTO HOSPITAL DEL SALVADOR E INSTITUTO NACIONAL DE GERIATRIA (PROYECTO HDS) – MINUTA COMPLEMENTO | L857: 46234 | M857: FALSO
A858: 3333 | B858: DES - Cuenta Comercial Salesforce | C858: PR.DTC.2026.0496 AIF ESTADIO- SAN ANTONIO | D858: Cerrada ganada | E858: 10784482 | F858: 1 | G858: 46167 | H858: 2118 ICI - Ingenieria contra Incendios | I858: DTC | J858: SET - Sección Estudios | K858: PR.DTC.2026.0496 | L858: 46234 | M858: FALSO
A859: 781555401 | B859: PROTERM S.A. | C859: PR.DTC.2026.0468 - Solución constructiva vertical | D859: Cerrada ganada | E859: 684938 | F859: 1 | G859: 46199 | H859: 1827 RNM - Estudios Acústicos | I859: DTC | J859: SET - Sección Estudios | K859: PR.DTC.2026.0468 | L859: 46234 | M859: FALSO
A860: 811050008 | B860: VILLALBA S A | C860: PR.DTC.2026.0704-Asimilación RF | D860: Cerrada ganada | E860: 1633574 | F860: 1 | G860: 46213 | H860: 2118 ICI - Ingenieria contra Incendios | I860: DTC | J860: SET - Sección Estudios | K860: PR.DTC.2026.0704 | L860: 46233 | M860: FALSO
B861: MINISTERIO DE VIVIENDA Y URBANISMO | C861: PR.DTC.2026.0304 - REV PROYECTO EL OLIVAR - ACU | D861: Cerrada ganada | E861: 5577841 | F861: 1 | G861: 46112 | H861: 1827 RNM - Estudios Acústicos | I861: DTC | J861: SET - Sección Estudios | K861: PR.DTC.2026.0304 | L861: 46233 | M861: FALSO
A862: 861603008 | B862: BHP CHILE INC | C862: PR.DTC.2025.1336 - Estudio de vulnerabilidades BHP | D862: Cerrada ganada | E862: 18841626 | F862: 1 | G862: 46042 | H862: 2118 ICI - Ingenieria contra Incendios | I862: DTC | J862: SET - Sección Estudios | K862: PR.DTC.2025.1336 | L862: 46233 | M862: FALSO
A863: 2345 | B863: DIVISIÓN GEOTECNIA LABORATORIO | C863: PR.DES.2026-30 | D863: Cerrada ganada | E863: 11940594 | F863: 1 | G863: 46077 | H863: 2124 UIE - Unidad Inspección Especialista | I863: DES | J863: SEP - Sección Especialidades | K863: Medición de resistividad de suelo Minera Caserones | L863: 46233 | M863: FALSO
A864: 765678749 | B864: CONSTRUCTORA LA RIOJA SPA | C864: PR.DTC.2026.0720-Estudio de asimilación RF | D864: Cerrada ganada | E864: 3430962 | F864: 1 | G864: 46213 | H864: 2118 ICI - Ingenieria contra Incendios | I864: DTC | J864: SET - Sección Estudios | K864: PR.DTC.2026.0720 | L864: 46233 | M864: FALSO
A865: 618010007 | B865: Subsecretaria del Ministerio de la Vivienda y Urbanismo | C865: PR.DTC.2026.0305 - Asimilación RF | D865: Cerrada ganada | E865: 7968344 | F865: 1 | G865: 46114 | H865: 2118 ICI - Ingenieria contra Incendios | I865: DTC | J865: SET - Sección Estudios | K865: PR.DTC.2026.0305 | L865: 46233 | M865: FALSO
A866: 898536009 | B866: CONSTRUCTORA INGEVEC S.A. | C866: PR.DES.2024-185 | D866: Cerrada ganada | E866: 3984386 | F866: 1 | G866: 45624 | H866: 2124 UIE - Unidad Inspección Especialista | I866: DES | J866: SEP - Sección Especialidades | K866: Puesta en marcha, edificio Serrano | L866: 46226 | M866: FALSO
A867: 995875209 | B867: UNACEM CHILE S.A. | C867: PR.DHI.SHI.2026-0922 | D867: Cerrada ganada | E867: 4901048 | F867: 1 | G867: 46216 | H867: 1820 UCC - Unidad de Control de Cemento | I867: DHI | J867: SCM - Sección Control Cemento | K867: Control mensual de cemento -JULIO 2026 / Resistencia mecánica | L867: 46216 | M867: FALSO
A868: 913370007 | B868: CEMENTOS POLPAICO S.A. | C868: PR.DHI.SHI.2026-0924 | D868: Cerrada ganada | E868: 7082487 | F868: 1 | G868: 46216 | H868: 1820 UCC - Unidad de Control de Cemento | I868: DHI | J868: SCM - Sección Control Cemento | K868: Ensayos especiales | L868: 46216 | M868: FALSO
A869: 995875209 | B869: UNACEM CHILE S.A. | C869: PR.DHI.SHI.2026-0923 | D869: Cerrada ganada | E869: 4084479 | F869: 1 | G869: 46216 | H869: 1820 UCC - Unidad de Control de Cemento | I869: DHI | J869: SCM - Sección Control Cemento | K869: Control mensual de cemento -JULIO 2026 / Resistencia mecánica | L869: 46216 | M869: FALSO
A870: 767341962 | B870: CONSTRUCTORA COLBUN SPA | C870: PR.DHC.2321.2026.036 V2 Paseo Hacienda II Indepencia-Colbun | D870: Cerrada ganada | E870: 360 | F870: 1 | G870: 46178 | H870: 2321 UHTE - Unidad Hormigones Temuco | I870: DHC | J870: SHS - Sección Hormigones Sur | K870: Servicios de laboratorio | L870: 46215 | M870: FALSO
A871: 995875209 | B871: UNACEM CHILE S.A. | C871: PR.DHI.SHI.2026-0654 | D871: Cerrada ganada | E871: 2134140 | F871: 1 | G871: 46213 | H871: 1820 UCC - Unidad de Control de Cemento | I871: DHI | J871: SCM - Sección Control Cemento | K871: Análisis a muestras de Cemento AR | L871: 46213 | M871: FALSO
A872: 995875209 | B872: UNACEM CHILE S.A. | C872: PR.DHI.SHI.2026-0475 | D872: Cerrada ganada | E872: 2134140 | F872: 1 | G872: 46213 | H872: 1820 UCC - Unidad de Control de Cemento | I872: DHI | J872: SCM - Sección Control Cemento | K872: Análisis a muestras de Cemento AR | L872: 46213 | M872: FALSO
A873: 995298805 | B873: PCR TRADING S.A. | C873: PR.DHI.SHI.2026-0921 | D873: Cerrada ganada | E873: 16174537 | F873: 1 | G873: 46213 | H873: 1820 UCC - Unidad de Control de Cemento | I873: DHI | J873: SCM - Sección Control Cemento | K873: Certificación Período de MAYO 2026 Regiones de Magallanes - Aysén | L873: 46213 | M873: FALSO
... A892: 965219404 | B892: INMOBILIARIA RIO COLORADO S.A. | C892: PR.DIO.2025-5 (Extensión Junio 2026) | D892: Cerrada ganada | E892: 3139089 | F892: 1 | G892: 46203 | H892: 2123 ITO1 - ITO1 | I892: DIO | J892: Sin sección DIO | K892: Hijuela 4 - Fundo el Peral | L892: 46203 | M892: FALSO
B893: MINISTERIO DE VIVIENDA Y URBANISMO | C893: PR.DEP.2026.0076 Revisión proyecto de cálculo estructural de 3 tipologías de viviendas El Olivar, Quilpué – Valparaíso | D893: Cerrada ganada | E893: 27490787 | F893: 1 | G893: 46119 | H893: 2304 PE1 - Proyecto Estructura 1 | I893: DEP | J893: Sin sección DEP | K893: PR.DEP.2026.0076 | L893: 46203 | M893: FALSO
A894: 609100001 | B894: UNIVERSIDAD DE CHILE | C894: PR.DIO.2024-56 (Complemento Junio 2026) | D894: Cerrada ganada | E894: 4000390 | F894: 1 | G894: 46203 | H894: 2123 ITO1 - ITO1 | I894: DIO | J894: Sin sección DIO | K894: Reposición Techumbre Casa Central de la Universidad de Chile | L894: 46203 | M894: FALSO
A895: 609100001 | B895: UNIVERSIDAD DE CHILE | C895: PR.DGI.2026-079 Escaneo Láser Juan Gómez Millas | D895: Cerrada ganada | E895: 3264320 | F895: 1 | G895: 46199 | H895: 2314 UGM - Unidad Geomensura | I895: DGI | J895: SIG - Sección Ingeniería Geotécnica | K895: Escaneo Láser Juan Gómez Millas | L895: 46203 | M895: FALSO
A896: 7777 | B896: DIC - Cuenta Comercial Salesforce | C896: PR.DTC.2026.0362 - Visita a terreno | D896: Cerrada ganada | E896: 803736 | F896: 1 | G896: 46147 | H896: 2118 ICI - Ingenieria contra Incendios | I896: DTC | J896: SET - Sección Estudios | K896: PR.DTC.2026.0362 | L896: 46203 | M896: FALSO
A897: 898536009 | B897: CONSTRUCTORA INGEVEC S.A. | C897: PR.DTC.2026.0098 - Estudio Ventanas Parque Zenteno II | D897: Cerrada ganada | E897: 1 | F897: 1 | G897: 45953 | H897: 3149 RMP - RENAM Privado | I897: DTC | J897: SET - Sección Estudios | K897: PR.DTC.2026.0098 | L897: 46203 | M897: FALSO
A898: 898536009 | B898: CONSTRUCTORA INGEVEC S.A. | C898: PR.DTC.2026.0585 - REVISION VENTANAS INGEVEC -BOLSA 2 | D898: Cerrada ganada | E898: 1877234 | F898: 1 | G898: 46203 | H898: 3149 RMP - RENAM Privado | I898: DTC | J898: SET - Sección Estudios | K898: PR.DTC.2026.0585 | L898: 46203 | M898: FALSO
A899: 761623885 | B899: INMOBILIARIA ACM S.A. | C899: PR.DIO.2024-48 (Extensión Junio 2026) | D899: Cerrada ganada | E899: 3877929 | F899: 1 | G899: 46203 | H899: 2123 ITO1 - ITO1 | I899: DIO | J899: Sin sección DIO | K899: Quillayes 1A7 - Etapa 6 | L899: 46203 | M899: FALSO
A900: 967639508 | B900: INMOBILIARIA LOMAS DE ASIS LIMITADA | C900: PR.DIO.2024-49 (Extensión Junio 2026) | D900: Cerrada ganada | E900: 3877929 | F900: 1 | G900: 46203 | H900: 2123 ITO1 - ITO1 | I900: DIO | J900: Sin sección DIO | K900: Reserva San Francisco Casas | L900: 46203 | M900: FALSO
A901: 965681809 | B901: EMPRESA NACIONAL DE CONSTRUCCION LAS VERTIENTES S A | C901: PR.DHC.2380.2026.227_ENACO-Reserva San Francisco Etapa 43, Lote O. | D901: Cerrada ganada | E901: 77321 | F901: 1 | G901: 46184 | H901: 2380 UHT - Unidad Hormigones Terreno | I901: DHC | J901: SHM - Sección Hormigones Metropolitana | K901: Reserva San Francisco Etapa 43, Lote O. | L901: 46203 | M901: FALSO
A902: 774545875 | B902: SANCHEZ HERMANOS SPA | C902: PR.DTC.2026.0447 - Calculo valor U Panel Metalico | D902: Cerrada ganada | E902: 1420190 | F902: 1 | G902: 46150 | H902: 3149 RMP - RENAM Privado | I902: DTC | J902: SET - Sección Estudios | K902: PR.DTC.2026.0447 | L902: 46202 | M902: FALSO
A903: 992256230001 | B903: FERREMUNDO S.A.S. | C903: PR.DTC.2026.0492 - Cálculo térmico de solución constructiva | D903: Cerrada ganada | E903: 1009783 | F903: 1 | G903: 46160 | H903: 3149 RMP - RENAM Privado | I903: DTC | J903: SET - Sección Estudios | K903: PR.DTC.2026.0492 | L903: 46202 | M903: FALSO
A904: 764624408 | B904: ZOPONE CHILE ING. LTDA. | C904: PR.DHC.2380.2026.092_ZOPONE-Obra Quintay | D904: Cerrada ganada | E904: 59882 | F904: 1 | G904: 46199 | H904: 2380 UHT - Unidad Hormigones Terreno | I904: DHC | J904: SHM - Sección Hormigones Metropolitana | K904: Obra Quintay | L904: 46199 | M904: FALSO
A905: 764496213 | B905: CONSTRUCTORA LO AGUIRRE SPA | C905: PR.DHC.2380.2026.151_CONSTRUCTORA LO AGUIRRE_Ballica | D905: Cerrada ganada | E905: 81151 | F905: 1 | G905: 46199 | H905: 2380 UHT - Unidad Hormigones Terreno | I905: DHC | J905: SHM - Sección Hormigones Metropolitana | K905: Ballica | L905: 46199 | M905: FALSO
... A945: 761623885 | B945: INMOBILIARIA ACM S.A. | C945: PR.DIO.2024-48 (Extensión Mayo 2026) | D945: Cerrada ganada | E945: 3858016 | F945: 1 | G945: 46169 | H945: 2123 ITO1 - ITO1 | I945: DIO | J945: Sin sección DIO | K945: Quillayes 1A7 - Etapa 6 | L945: 46173 | M945: FALSO
B946: CODELCO VICEPRESIDENCIA DE PROYECTOS | C946: PR.DGI.2022-015_J ODS10 Pampa Austral - Adicional Marzo 2026 | D946: Cerrada ganada | E946: 83394 | F946: 1 | G946: 44864 | H946: 3819 DRPA - Depósito de Relaves Pampa Austral | I946: DGI | J946: SPG - Sección Prospecciones Geotécnicas | K946: ODS10 Pampa Austral - Acicional Marzo 2026 | L946: 46173 | M946: FALSO
A947: 727547002 | B947: FUND INSTITUTO PROFESIONAL DUOC UC | C947: PR.DEP.2026.0116 Ensayo de la conexión, flexión y compresión excéntrica de columna CLT | D947: Cerrada ganada | E947: 7653633 | F947: 1 | G947: 46162 | H947: 2121 UES - Unidad Ensayos Estructurales | I947: DEP | J947: Sin sección DEP | K947: PR.DEP.2026-0116 | L947: 46173 | M947: FALSO
A948: 1011 | B948: DCO - Cuenta Comercial Salesforce | C948: PR.DGI.2026-039 Ensayos geofísicos en Minera Zaldívar | D948: Cerrada ganada | E948: 16947871 | F948: 1 | G948: 46119 | H948: 1787 UIG - Unidad Ingeniería Geotécnica | I948: DGI | J948: SIG - Sección Ingeniería Geotécnica | K948: Ensayos geofísicos en Minera Zaldívar | L948: 46173 | M948: FALSO
A949: 3333 | B949: DES - Cuenta Comercial Salesforce | C949: PR.DGI.2026-048 ESTUDIO DE MECÁNICA DE SUELO ESTADIO PIERINO PERAZZO GAGLIARDO | D949: Cerrada ganada | E949: 17445494 | F949: 1 | G949: 46155 | H949: 1787 UIG - Unidad Ingeniería Geotécnica | I949: DGI | J949: SIG - Sección Ingeniería Geotécnica | K949: ESTUDIO DE MECÁNICA DE SUELO ESTADIO PIERINO PERAZZO GAGLIARDO | L949: 46173 | M949: FALSO
A950: 894689005 | B950: CIA. MINERA DONA INES DE COLLAHUASI SCM | C950: PR.DGI.2025-021 Orden de Cambio 1 - Sondajes Geotécnicos para Proyecto Integrado de Crecimiento IGP Collahuasi Adicional | D950: Cerrada ganada | E950: 230007986 | F950: 1 | G950: 46053 | H950: 3874 CMC - Sondajes Geotécnicos para Proyecto Integrado de Crecimiento IGP Collahuasi | I950: DGI | J950: SPG - Sección Prospecciones Geotécnicas | K950: OPR.DGI.2025-0187 Collahuasi | L950: 46173 | M950: FALSO
A951: 945100001 | B951: RENTA NACIONAL CIA DE SEGUROS GENERALES S A | C951: PR.DTC.2026.0200 - Peritaje causa-origen | D951: Cerrada ganada | E951: 8765178 | F951: 1 | G951: 46098 | H951: 2118 ICI - Ingenieria contra Incendios | I951: DTC | J951: SET - Sección Estudios | K951: PR.DTC.2026.0200 | L951: 46173 | M951: FALSO
A952: 592753006 | B952: CHINA RAILWAY TUNNEL GROUP CO., LTD SUCURSAL CHILE | C952: PR.DEP.2026.0089 Ensayos de tracción a barras autoperforantes | D952: Cerrada ganada | E952: 1691495 | F952: 1 | G952: 46153 | H952: 2121 UES - Unidad Ensayos Estructurales | I952: DEP | J952: Sin sección DEP | K952: PR.DEP.2026-0089 | L952: 46173 | M952: FALSO
A953: 773033706 | B953: Inmobiliaria y Constr. la Pata | C953: PR.DEP.2026.0110 Ensayos de carga transversal a prototipo de ventana | D953: Cerrada ganada | E953: 2418435.6 | F953: 1 | G953: 46155 | H953: 2121 UES - Unidad Ensayos Estructurales | I953: DEP | J953: Sin sección DEP | K953: PR.DEP.2026-0110 | L953: 46173 | M953: FALSO
A954: 609100001 | B954: UNIVERSIDAD DE CHILE | C954: PR.DIO.2024-56 (Complemento Mayo 2026) | D954: Cerrada ganada | E954: 1523225 | F954: 1 | G954: 46169 | H954: 2123 ITO1 - ITO1 | I954: DIO | J954: Sin sección DIO | K954: Reposición Techumbre Casa Central de la Universidad de Chile | L954: 46173 | M954: FALSO
A955: 966608900 | B955: Vector Ltda | C955: PR.DEP.2026.0063 Ensayos de tracción y de contenido de zinc a alambre de malla de fortificación de túnel | D955: Cerrada ganada | E955: 1212244.5 | F955: 1 | G955: 46161 | H955: 2121 UES - Unidad Ensayos Estructurales | I955: DEP | J955: Sin sección DEP | K955: PR.DEP.2026.0063 | L955: 46173 | M955: FALSO
A956: 898536009 | B956: CONSTRUCTORA INGEVEC S.A. | C956: PR.DEP.2026.0113 Ensayos carga transversal a barandas | D956: Cerrada ganada | E956: 3221895.2 | F956: 1 | G956: 46153 | H956: 2121 UES - Unidad Ensayos Estructurales | I956: DEP | J956: Sin sección DEP | K956: PR.DEP.2026-0113 | L956: 46173 | M956: FALSO
A957: 76007019K | B957: INMOBILIARIA LAMPA ORIENTE S.A. | C957: PR.DIO.2025-8 (Extensión Mayo 2026) | D957: Cerrada ganada | E957: 5482443 | F957: 1 | G957: 46169 | H957: 2123 ITO1 - ITO1 | I957: DIO | J957: Sin sección DIO | K957: Parque Chicauma Etapa 9.1 | L957: 46173 | M957: FALSO
A958: 130772862 | B958: DDA - Cuenta Comercial Salesforce | C958: PR.DGI.2026-002 Levantamiento Topográfico para Proyecto de Abastecimiento de Agua - Región de la Araucania | D958: Cerrada ganada | E958: 11316960 | F958: 1 | G958: 46052 | H958: 2314 UGM - Unidad Geomensura | I958: DGI | J958: SIG - Sección Ingeniería Geotécnica | K958: Levantamiento Topográfico para Proyecto de Abastecimiento de Agua - Región de la Araucanía | L958: 46173 | M958: FALSO
... A1040: 965294805 | B1040: V S L SISTEMAS ESPECIALES DE CONSTRUCCION S A | C1040: PR.DHC.2380.2025.224_V2_VSL-PREFABRICADOS CANAL DE ADUCCION COLBUN | D1040: Cerrada ganada | E1040: 951420 | F1040: 1 | G1040: 46118 | H1040: 2380 UHT - Unidad Hormigones Terreno | I1040: DHC | J1040: SHM - Sección Hormigones Metropolitana | K1040: PREFABRICADOS CANAL DE ADUCCION COLBUN | L1040: 46142 | M1040: FALSO
B1041: CODELCO VICEPRESIDENCIA DE PROYECTOS | C1041: PR.DGI.2022-015_K OdS 11 Tove 3868 - Adicional Marzo 2026 | D1041: Cerrada ganada | E1041: 10168548 | F1041: 1 | G1041: 44864 | H1041: 3868 TOA - Tranque Ovejería | I1041: DGI | J1041: SPG - Sección Prospecciones Geotécnicas | K1041: OdS 11 Tove 3868 - Adicional Marzo 2026 | L1041: 46142 | M1041: FALSO
A1042: 811050008 | B1042: VILLALBA S A | C1042: PR.DTC.2026.0396 - Estudio de asimilación RF | D1042: Cerrada ganada | E1042: 1683931 | F1042: 1 | G1042: 46140 | H1042: 2118 ICI - Ingenieria contra Incendios | I1042: DTC | J1042: SET - Sección Estudios | K1042: PR.DTC.2026.0396 | L1042: 46142 | M1042: FALSO
A1043: 764303482 | B1043: Inversiones Y Comercio RGP SpA | C1043: PR.DEP.2026.0108 Ensayos de tracción a barras autoperforantes | D1043: Cerrada ganada | E1043: 1800624.6 | F1043: 1 | G1043: 46134 | H1043: 2121 UES - Unidad Ensayos Estructurales | I1043: DEP | J1043: Sin sección DEP | K1043: PR.DEP.2026-0108 | L1043: 46142 | M1043: FALSO
A1044: 764303482 | B1044: Inversiones Y Comercio RGP SpA | C1044: PR.DEP.2026.0054A Ensayos de tracción a barras autoperforantes | D1044: Cerrada ganada | E1044: 3595282.2 | F1044: 1 | G1044: 46129 | H1044: 2121 UES - Unidad Ensayos Estructurales | I1044: DEP | J1044: Sin sección DEP | K1044: PR.DEP.2026-0054A | L1044: 46142 | M1044: FALSO
...

Sheet Año_reporte
A1: Fecha | B1: Comentario
A2: 46387 | B2: Esta fecha cambiarla cada año que se hace el reporte, dejar el último día del año

Sheet Cuadratura
A1: Revisar acumulado EERR vs Div | D1: =SUM(D3:D19) -> 0 | F1: Revisar acumulado SalesForce vs Div | I1: =SUM(I3:I19) -> 0 | K1: Revisar acumulado Diferencia vs Div | N1: =SUM(N3:N19) -> -4.529953e-06 | P1: Revisar Detalle acumulado EERR vs Div | S1: =SUM(S3:S19) -> 0 | U1: Revisar Detalle acumulado SalesForce vs Div | X1: =SUM(X3:X19) -> 0 | Z1: Reporte Facturación
B2: Ingreso EERR | C2: Ingreso DIV | D2: Diferencia | G2: Ingreso EERR | H2: Ingreso DIV | I2: Diferencia | L2: Ingreso EERR | M2: Ingreso DIV | N2: Diferencia | Q2: Ingreso EERR | R2: Ingreso DIV | S2: Diferencia | V2: Ingreso Div Detalle | W2: Ingreso DIV | X2: Diferencia | AA2: =GETPIVOTDATA("[Measures].[Ingreso]",IDIEM!$I$1) -> 22940610337 | AB2: =GETPIVOTDATA("[Measures].[Ingreso]",'Reporte Facturación sin TI'!$A$3) -> 22940610337 | AC2: =AB2-AA2 -> 0
A3: DAC | B3: =GETPIVOTDATA("[Measures].[Ingreso]",IDIEM!$I$1,"[Resultado].[Div]","[Resultado].[Div].&[DAC]") -> 854485347 | C3: =GETPIVOTDATA("[Measures].[Ingreso]",DAC!$I$1,"[Resultado].[Div]","[Resultado].[Div].&[DAC]") -> 854485347 | D3: =C3-B3 -> 0 | F3: DAC | G3: =GETPIVOTDATA("[Measures].[Ingreso_Salesforce]",IDIEM!$I$25,"[TBD_Reporte_Salesforce].[División]","[TBD_Reporte_Salesforce].[División].&[DAC]") -> 1.2797689e+09 | H3: =DAC!V63 -> 1.2797689e+09 | I3: =H3-G3 -> 0 | K3: DAC | L3: =B3-G3 -> -4.2528352e+08 | M3: =DAC!V84 -> -4.2528352e+08 | N3: =L3-M3 -> 0 | P3: DAC | Q3: =GETPIVOTDATA("[Measures].[Ingreso]",DAC!$I$88) -> 854485347 | R3: =GETPIVOTDATA("[Measures].[Ingreso]",DAC!$I$1,"[Resultado].[Div]","[Resultado].[Div].&[DAC]") -> 854485347 | S3: =R3-Q3 -> 0 | U3: DAC | V3: =GETPIVOTDATA("[Measures].[Ingreso_Salesforce]",DAC!$Z$88) -> 1.2797689e+09 | W3: =DAC!V63 -> 1.2797689e+09 | X3: =W3-V3 -> 0
A4: DCO | B4: =GETPIVOTDATA("[Measures].[Ingreso]",IDIEM!$I$1,"[Resultado].[Div]","[Resultado].[Div].&[DCO]") -> 2375406406 | C4: =GETPIVOTDATA("[Measures].[Ingreso]",DCO!$I$1,"[Resultado].[Div]","[Resultado].[Div].&[DCO]") -> 2375406406 | D4: =C4-B4 -> 0 | F4: DCO | G4: =GETPIVOTDATA("[Measures].[Ingreso_Salesforce]",IDIEM!$I$25,"[TBD_Reporte_Salesforce].[División]","[TBD_Reporte_Salesforce].[División].&[DCO]") -> 3.5954668e+09 | H4: =DCO!V63 -> 3.5954668e+09 | I4: =H4-G4 -> 0 | K4: DCO | L4: =B4-G4 -> -1.2200604e+09 | M4: =DCO!V84 -> -1.2200604e+09 | N4: =L4-M4 -> 0 | P4: DCO | Q4: =GETPIVOTDATA("[Measures].[Ingreso]",DCO!$I$88) -> 2375406406 | R4: =GETPIVOTDATA("[Measures].[Ingreso]",DCO!$I$1,"[Resultado].[Div]","[Resultado].[Div].&[DCO]") -> 2375406406 | S4: =R4-Q4 -> 0 | U4: DCO | V4: =GETPIVOTDATA("[Measures].[Ingreso_Salesforce]",DCO!$Z$88) -> 3.5954668e+09 | W4: =DCO!V63 -> 3.5954668e+09 | X4: =W4-V4 -> 0
A5: DDA | B5: =GETPIVOTDATA("[Measures].[Ingreso]",IDIEM!$I$1,"[Resultado].[Div]","[Resultado].[Div].&[DDA]") -> 1611234147 | C5: =GETPIVOTDATA("[Measures].[Ingreso]",DDA!$I$1) -> 1611234147 | D5: =C5-B5 -> 0 | F5: DDA | G5: =GETPIVOTDATA("[Measures].[Ingreso_Salesforce]",IDIEM!$I$25,"[TBD_Reporte_Salesforce].[División]","[TBD_Reporte_Salesforce].[División].&[DDA]") -> 772668938 | H5: =DDA!V63 -> 772668938 | I5: =H5-G5 -> 0 | K5: DDA | L5: =B5-G5 -> 838565209 | M5: =DDA!V84 -> 838565209 | N5: =L5-M5 -> 0 | P5: DDA | Q5: =GETPIVOTDATA("[Measures].[Ingreso]",DDA!$I$88) -> 1611234147 | R5: =GETPIVOTDATA("[Measures].[Ingreso]",DDA!$I$1) -> 1611234147 | S5: =R5-Q5 -> 0 | U5: DDA | V5: =GETPIVOTDATA("[Measures].[Ingreso_Salesforce]",DDA!$Z$88) -> 772668938 | W5: =DDA!V63 -> 772668938 | X5: =W5-V5 -> 0
A6: DEP | B6: =GETPIVOTDATA("[Measures].[Ingreso]",IDIEM!$I$1,"[Resultado].[Div]","[Resultado].[Div].&[DEP]") -> 777676470 | C6: =GETPIVOTDATA("[Measures].[Ingreso]",DEP!$I$1,"[Resultado].[Div]","[Resultado].[Div].&[DEP]") -> 777676470 | D6: =C6-B6 -> 0 | F6: DEP | G6: =GETPIVOTDATA("[Measures].[Ingreso_Salesforce]",IDIEM!$I$25,"[TBD_Reporte_Salesforce].[División]","[TBD_Reporte_Salesforce].[División].&[DEP]") -> 7.1343642e+08 | H6: =DEP!V63 -> 7.1343642e+08 | I6: =H6-G6 -> 0 | K6: DEP | L6: =B6-G6 -> 64240048 | M6: =DEP!V84 -> 64240048 | N6: =L6-M6 -> 5.9604645e-08 | P6: DEP | Q6: =GETPIVOTDATA("[Measures].[Ingreso]",DEP!$I$88) -> 777676470 | R6: =GETPIVOTDATA("[Measures].[Ingreso]",DEP!$I$1,"[Resultado].[Div]","[Resultado].[Div].&[DEP]") -> 777676470 | S6: =R6-Q6 -> 0 | U6: DEP | V6: =GETPIVOTDATA("[Measures].[Ingreso_Salesforce]",DEP!$Z$88) -> 7.1343642e+08 | W6: =DEP!V63 -> 7.1343642e+08 | X6: =W6-V6 -> 0
A7: DES | B7: =GETPIVOTDATA("[Measures].[Ingreso]",IDIEM!$I$1,"[Resultado].[Div]","[Resultado].[Div].&[DES]") -> 1544101259 | C7: =GETPIVOTDATA("[Measures].[Ingreso]",DES!$I$1) -> 1544101259 | D7: =C7-B7 -> 0 | F7: DES | G7: =GETPIVOTDATA("[Measures].[Ingreso_Salesforce]",IDIEM!$I$25,"[TBD_Reporte_Salesforce].[División]","[TBD_Reporte_Salesforce].[División].&[DES]") -> 1.5521385e+09 | H7: =DES!V63 -> 1.5521385e+09 | I7: =H7-G7 -> 0 | K7: DES | L7: =B7-G7 -> -8037197.2 | M7: =DES!V84 -> -8037197.2 | N7: =L7-M7 -> 1.1920929e-07 | P7: DES | Q7: =GETPIVOTDATA("[Measures].[Ingreso]",DES!$I$88) -> 1544101259 | R7: =GETPIVOTDATA("[Measures].[Ingreso]",DES!$I$1) -> 1544101259 | S7: =R7-Q7 -> 0 | U7: DES | V7: =GETPIVOTDATA("[Measures].[Ingreso_Salesforce]",DES!$Z$88) -> 1.5521385e+09 | W7: =DES!V63 -> 1.5521385e+09 | X7: =W7-V7 -> 0
A8: DGI | B8: =GETPIVOTDATA("[Measures].[Ingreso]",IDIEM!$I$1,"[Resultado].[Div]","[Resultado].[Div].&[DGI]") -> 7773506377 | C8: =GETPIVOTDATA("[Measures].[Ingreso]",DGI!$I$1) -> 7773506377 | D8: =C8-B8 -> 0 | F8: DGI | G8: =GETPIVOTDATA("[Measures].[Ingreso_Salesforce]",IDIEM!$I$25,"[TBD_Reporte_Salesforce].[División]","[TBD_Reporte_Salesforce].[División].&[DGI]") -> 8526059472 | H8: =DGI!V63 -> 8526059472 | I8: =H8-G8 -> 0 | K8: DGI | L8: =B8-G8 -> -752553095 | M8: =DGI!V84 -> -752553095 | N8: =L8-M8 -> 0 | P8: DGI | Q8: =GETPIVOTDATA("[Measures].[Ingreso]",DGI!$I$88) -> 7773506377 | R8: =GETPIVOTDATA("[Measures].[Ingreso]",DGI!$I$1) -> 7773506377 | S8: =R8-Q8 -> 0 | U8: DGI | V8: =GETPIVOTDATA("[Measures].[Ingreso_Salesforce]",DGI!$Z$88) -> 8526059472 | W8: =DGI!V63 -> 8526059472 | X8: =W8-V8 -> 0
A9: DGL | B9: =GETPIVOTDATA("[Measures].[Ingreso]",IDIEM!$I$1,"[Resultado].[Div]","[Resultado].[Div].&[DGL]") -> 1996413912 | C9: =GETPIVOTDATA("[Measures].[Ingreso]",DGL!$I$1) -> 1996413912 | D9: =C9-B9 -> 0 | F9: DGL | G9: =GETPIVOTDATA("[Measures].[Ingreso_Salesforce]",IDIEM!$I$25,"[TBD_Reporte_Salesforce].[División]","[TBD_Reporte_Salesforce].[División].&[DGL]") -> 2084836477 | H9: =DGL!V63 -> 2084836477 | I9: =H9-G9 -> 0 | K9: DGL | L9: =B9-G9 -> -88422565 | M9: =DGL!V84 -> -88422565 | N9: =L9-M9 -> 0 | P9: DGL | Q9: =GETPIVOTDATA("[Measures].[Ingreso]",DGL!$I$88) -> 1996413912 | R9: =GETPIVOTDATA("[Measures].[Ingreso]",DGL!$I$1) -> 1996413912 | S9: =R9-Q9 -> 0 | U9: DGL | V9: =GETPIVOTDATA("[Measures].[Ingreso_Salesforce]",DGL!$Z$88) -> 2084836477 | W9: =DGL!V63 -> 2084836477 | X9: =W9-V9 -> 0
A10: DHC | B10: =GETPIVOTDATA("[Measures].[Ingreso]",IDIEM!$I$1,"[Resultado].[Div]","[Resultado].[Div].&[DHC]") -> 1647253291 | C10: =GETPIVOTDATA("[Measures].[Ingreso]",DHC!$I$1) -> 1647253291 | D10: =C10-B10 -> 0 | F10: DHC | G10: =GETPIVOTDATA("[Measures].[Ingreso_Salesforce]",IDIEM!$I$25,"[TBD_Reporte_Salesforce].[División]","[TBD_Reporte_Salesforce].[División].&[DHC]") -> 542858276 | H10: =DHC!V63 -> 542858276 | I10: =H10-G10 -> 0 | K10: DHC | L10: =B10-G10 -> 1104395015 | M10: =DHC!V84 -> 1104395015 | N10: =L10-M10 -> 0 | P10: DHC | Q10: =GETPIVOTDATA("[Measures].[Ingreso]",DHC!$I$88) -> 1647253291 | R10: =GETPIVOTDATA("[Measures].[Ingreso]",DHC!$I$1) -> 1647253291 | S10: =R10-Q10 -> 0 | U10: DHC | V10: =GETPIVOTDATA("[Measures].[Ingreso_Salesforce]",DHC!$Z$88) -> 542858276 | W10: =DHC!V63 -> 542858276 | X10: =W10-V10 -> 0
A11: DHI | B11: =GETPIVOTDATA("[Measures].[Ingreso]",IDIEM!$I$1,"[Resultado].[Div]","[Resultado].[Div].&[DHI]") -> 1467179760 | C11: =GETPIVOTDATA("[Measures].[Ingreso]",DHI!$I$1) -> 1467179760 | D11: =C11-B11 -> 0 | F11: DHI | G11: =GETPIVOTDATA("[Measures].[Ingreso_Salesforce]",IDIEM!$I$25,"[TBD_Reporte_Salesforce].[División]","[TBD_Reporte_Salesforce].[División].&[DHI]") -> 1076834468 | H11: =DHI!V63 -> 1076834468 | I11: =H11-G11 -> 0 | K11: DHI | L11: =B11-G11 -> 390345292 | M11: =DHI!V84 -> 390345292 | N11: =L11-M11 -> 0 | P11: DHI | Q11: =GETPIVOTDATA("[Measures].[Ingreso]",DHI!$I$88) -> 1467179760 | R11: =GETPIVOTDATA("[Measures].[Ingreso]",DHI!$I$1) -> 1467179760 | S11: =R11-Q11 -> 0 | U11: DHI | V11: =GETPIVOTDATA("[Measures].[Ingreso_Salesforce]",DHI!$Z$88) -> 1076834468 | W11: =DHI!V63 -> 1076834468 | X11: =W11-V11 -> 0
A12: DIC | B12: =GETPIVOTDATA("[Measures].[Ingreso]",IDIEM!$I$1,"[Resultado].[Div]","[Resultado].[Div].&[DIC]") -> 312889501 | C12: =GETPIVOTDATA("[Measures].[Ingreso]",DIC!$I$1) -> 312889501 | D12: =C12-B12 -> 0 | F12: DIC | G12: =GETPIVOTDATA("[Measures].[Ingreso_Salesforce]",IDIEM!$I$25,"[TBD_Reporte_Salesforce].[División]","[TBD_Reporte_Salesforce].[División].&[DIC]") -> 312889501 | H12: =DIC!V63 -> 312889501 | I12: =H12-G12 -> 0 | K12: DIC | L12: =B12-G12 -> 0 | M12: =DIC!V84 -> 0 | N12: =L12-M12 -> 0 | P12: DIC | Q12: =GETPIVOTDATA("[Measures].[Ingreso]",DIC!$I$88) -> 312889501 | R12: =GETPIVOTDATA("[Measures].[Ingreso]",DIC!$I$1) -> 312889501 | S12: =R12-Q12 -> 0 | U12: DIC | V12: =GETPIVOTDATA("[Measures].[Ingreso_Salesforce]",DIC!$Z$88) -> 312889501 | W12: =DIC!V63 -> 312889501 | X12: =W12-V12 -> 0
A13: DIO | B13: =GETPIVOTDATA("[Measures].[Ingreso]",IDIEM!$I$1,"[Resultado].[Div]","[Resultado].[Div].&[DIO]") -> 211266786 | C13: =GETPIVOTDATA("[Measures].[Ingreso]",DIO!$I$1) -> 211266786 | D13: =C13-B13 -> 0 | F13: DIO | G13: =GETPIVOTDATA("[Measures].[Ingreso_Salesforce]",IDIEM!$I$25,"[TBD_Reporte_Salesforce].[División]","[TBD_Reporte_Salesforce].[División].&[DIO]") -> 324140668 | H13: =DIO!V63 -> 324140668 | I13: =H13-G13 -> 0 | K13: DIO | L13: =B13-G13 -> -112873882 | M13: =DIO!V84 -> -112873882 | N13: =L13-M13 -> 0 | P13: DIO | Q13: =GETPIVOTDATA("[Measures].[Ingreso]",DIO!$I$88) -> 211266786 | R13: =GETPIVOTDATA("[Measures].[Ingreso]",DIO!$I$1) -> 211266786 | S13: =R13-Q13 -> 0 | U13: DIO | V13: =GETPIVOTDATA("[Measures].[Ingreso_Salesforce]",DIO!$Z$88) -> 324140668 | W13: =DIO!V63 -> 324140668 | X13: =W13-V13 -> 0
A14: DPR | B14: =GETPIVOTDATA("[Measures].[Ingreso]",IDIEM!$I$1,"[Resultado].[Div]","[Resultado].[Div].&[DPR]") -> 1614959968 | C14: =GETPIVOTDATA("[Measures].[Ingreso]",DPR!$I$1) -> 1614959968 | D14: =C14-B14 -> 0 | F14: DPR | G14: =GETPIVOTDATA("[Measures].[Ingreso_Salesforce]",IDIEM!$I$25,"[TBD_Reporte_Salesforce].[División]","[TBD_Reporte_Salesforce].[División].&[DPR]") -> 2980799873 | H14: =DPR!V63 -> 2980799873 | I14: =H14-G14 -> 0 | K14: DPR | L14: =B14-G14 -> -1365839905 | M14: =DPR!V84 -> -1365839905 | N14: =L14-M14 -> 0 | P14: DPR | Q14: =GETPIVOTDATA("[Measures].[Ingreso]",DPR!$I$88) -> 1614959968 | R14: =GETPIVOTDATA("[Measures].[Ingreso]",DPR!$I$1) -> 1614959968 | S14: =R14-Q14 -> 0 | U14: DPR | V14: =GETPIVOTDATA("[Measures].[Ingreso_Salesforce]",DPR!$Z$88) -> 2980799873 | W14: =DPR!V63 -> 2980799873 | X14: =W14-V14 -> 0
A15: DTC | B15: =GETPIVOTDATA("[Measures].[Ingreso]",IDIEM!$I$1,"[Resultado].[Div]","[Resultado].[Div].&[DTC]") -> 1004760047 | C15: =GETPIVOTDATA("[Measures].[Ingreso]",DTC!$I$1) -> 1004760047 | D15: =C15-B15 -> 0 | F15: DTC | G15: =GETPIVOTDATA("[Measures].[Ingreso_Salesforce]",IDIEM!$I$25,"[TBD_Reporte_Salesforce].[División]","[TBD_Reporte_Salesforce].[División].&[DTC]") -> 1.1088036e+09 | H15: =DTC!V63 -> 1.1088036e+09 | I15: =H15-G15 -> 0 | K15: DTC | L15: =B15-G15 -> -1.0404359e+08 | M15: =DTC!V84 -> -1.0404359e+08 | N15: =L15-M15 -> -1.7881393e-07 | P15: DTC | Q15: =GETPIVOTDATA("[Measures].[Ingreso]",DTC!$I$88) -> 1004760047 | R15: =GETPIVOTDATA("[Measures].[Ingreso]",DTC!$I$1) -> 1004760047 | S15: =R15-Q15 -> 0 | U15: DTC | V15: =GETPIVOTDATA("[Measures].[Ingreso_Salesforce]",DTC!$Z$88) -> 1.1088036e+09 | W15: =DTC!V63 -> 1.1088036e+09 | X15: =W15-V15 -> 0
A16: EQM | B16: =GETPIVOTDATA("[Measures].[Ingreso]",IDIEM!$I$1,"[Resultado].[Div]","[Resultado].[Div].&[EQM]") -> -288986146 | C16: =GETPIVOTDATA("[Measures].[Suma de Monto 2]",EQM!$I$1) -> -288986146 | D16: =C16-B16 -> 0 | F16: EQM | G16: =IFERROR(GETPIVOTDATA("[Measures].[Ingreso_Salesforce]",IDIEM!$I$25,"[TBD_Reporte_Salesforce].[División]","[TBD_Reporte_Salesforce].[División].&[EQM]"),0) -> 0 | H16: =EQM!V63 -> 0 | I16: =H16-G16 -> 0 | K16: EQM | L16: =B16-G16 -> -288986146 | M16: =EQM!V84 -> -288986146 | N16: =L16-M16 -> 0 | P16: EQM | Q16: =GETPIVOTDATA("[Measures].[Suma de Monto 2]",EQM!$I$88) -> -288986146 | R16: =GETPIVOTDATA("[Measures].[Suma de Monto 2]",EQM!$I$1) -> -288986146 | S16: =R16-Q16 -> 0 | U16: EQM | V16: 0 | W16: =EQM!V63 -> 0
A17: MDQ | B17: =GETPIVOTDATA("[Measures].[Ingreso]",IDIEM!$I$1,"[Resultado].[Div]","[Resultado].[Div].&[MDQ]") -> 0 | C17: =GETPIVOTDATA("[Measures].[Suma de Monto 2]",MDQ!$I$1) -> 0 | D17: =C17-B17 -> 0 | F17: MDQ | G17: =IFERROR(GETPIVOTDATA("[Measures].[Ingreso_Salesforce]",IDIEM!$I$25,"[TBD_Reporte_Salesforce].[División]","[TBD_Reporte_Salesforce].[División].&[MDQ]"),0) -> 0 | H17: =MDQ!V63 -> 0 | I17: =H17-G17 -> 0 | K17: MDQ | L17: =B17-G17 -> 0 | M17: =MDQ!V84 -> 0 | N17: =L17-M17 -> 0 | P17: MDQ | Q17: =GETPIVOTDATA("[Measures].[Suma de Monto 2]",MDQ!$I$88) -> 0 | R17: =GETPIVOTDATA("[Measures].[Suma de Monto 2]",MDQ!$I$1) -> 0 | S17: =R17-Q17 -> 0 | U17: MDQ | V17: 0 | W17: =MDQ!V63 -> 0 | X17: =W17-V17 -> 0
A18: SDO | B18: =GETPIVOTDATA("[Measures].[Ingreso]",IDIEM!$I$1,"[Resultado].[Div]","[Resultado].[Div].&[SDO]") -> 38463212 | C18: =B18 -> 38463212 | D18: =C18-B18 -> 0 | F18: SDO | K18: SDO | L18: =B18-G18 -> 38463212 | M18: =L18 -> 38463212 | N18: =L18-M18 -> 0
A19: IDIEM | B19: =GETPIVOTDATA("[Measures].[Ingreso]",IDIEM!$I$1) -> 22940610337 | C19: =SUM(C3:C18) -> 22940610337 | D19: =C19-B19 -> 0 | F19: Total general | G19: =GETPIVOTDATA("[Measures].[Ingreso_Salesforce]",IDIEM!$I$25)-GETPIVOTDATA("[Measures].[Ingreso_Salesforce]",IDIEM!$I$25,"[TBD_Reporte_Salesforce].[División]","[TBD_Reporte_Salesforce].[División].&[SDO]") -> 2.4870702e+10 | H19: =SUM(H3:H17) -> 2.4870702e+10 | I19: =H19-G19 -> 0 | K19: IDIEM | L19: =B19-G19 -> -1.9300916e+09 | M19: =SUM(M3:M18) -> -1.9300916e+09 | N19: =L19-M19 -> -4.529953e-06 | P19: IDIEM | Q19: =SUM(Q3:Q17) -> 22902147125 | R19: =SUM(R3:R17) -> 22902147125 | S19: =R19-Q19 -> 0 | U19: IDIEM | V19: =SUM(V3:V17) -> 2.4870702e+10 | W19: =SUM(W3:W17) -> 2.4870702e+10 | X19: =W19-V19 -> 0
V21: EQM y MDQ no tiene nada por Salesforce pero si por EERR, por eso le puse 0

Sheet BBDD Gráficos
A1: Mes Actual
B2: Backlog | C2: (Salesforce) | E2: Facturación | F2: (EERR) | H2: Traspasos | I2: (EERR) | K2: Ingresos (EERR)
B3: Etiquetas de fila | C3: Ingreso_Salesforce | E3: Etiquetas de fila | F3: EERR | H3: Etiquetas de fila | I3: EERR | K3: Etiquetas de fila | L3: EERR
B4: DAC | C4: 3.6332564e+08 | E4: DAC | F4: 501144778 | H4: DAC | I4: 1844000 | K4: DAC | L4: 502988778
B5: DCO | C5: 486320169 | E5: DCO | F5: 202280197 | H5: DCO | I5: -32848612 | K5: DCO | L5: 169431585
B6: DDA | C6: 130045454 | E6: DDA | F6: 268536935 | H6: DEP | I6: 9419648 | K6: DDA | L6: 268536935
B7: DEP | C7: 79488858 | E7: DEP | F7: 151372459 | H7: DES | I7: -71496509 | K7: DEP | L7: 160792107
B8: DES | C8: 3.2742769e+08 | E8: DES | F8: 319390498 | H8: DGI | I8: 38839886 | K8: DES | L8: 247893989
B9: DGI | C9: 1229933471 | E9: DGI | F9: 1585394898 | H9: DGL | I9: 40212085 | K9: DGI | L9: 1624234784
B10: DGL | C10: 436919745 | E10: DGL | F10: 337161507 | H10: DHC | I10: -3120929 | K10: DGL | L10: 377373592
B11: DHC | C11: 146170041 | E11: DHC | F11: 339732550 | H11: DHI | I11: 53055793 | K11: DHC | L11: 336611621
B12: DHI | C12: 125279423 | E12: DHI | F12: 243547684 | H12: DIC | I12: -1608004 | K12: DHI | L12: 296603477
B13: DIC | C13: 41091978 | E13: DIC | F13: 41091978 | H13: DPR | I13: -51606392 | K13: DIC | L13: 39483974
B14: DIO | C14: 47567549 | E14: DIO | F14: 44774892 | H14: DTC | I14: 17309034 | K14: DIO | L14: 44774892
B15: DPR | C15: 492863760 | E15: DPR | F15: 442422045 | H15: Total general | I15: 0 | K15: DPR | L15: 390815653
B16: DTC | C16: 2.1220769e+08 | E16: DTC | F16: 159210040 | K16: DTC | L16: 176519074
B17: SDG | C17: 444000 | E17: EQM | F17: -206156436 | K17: EQM | L17: -206156436
B18: SDO | C18: 4465971 | E18: SDO | F18: 7007326 | K18: SDO | L18: 7007326
B19: Total general | C19: 4.1235514e+09 | E19: Total general | F19: 4436911351 | K19: Total general | L19: 4436911351
A22: Datos para gráficos
B23: Backlog | C23: Facturación | D23: Traspasos | E23: Ingresos (EERR) | F23: Diferencia
A24: DAC | B24: =IFERROR(VLOOKUP($A24,$B$4:$C$19,2,0),0) -> 3.6332564e+08 | C24: =IFERROR(VLOOKUP($A24,$E$4:$F$19,2,0),0) -> 501144778 | D24: =IFERROR(VLOOKUP($A24,$H$4:$I$19,2,0),0) -> 1844000 | E24: =IFERROR(VLOOKUP($A24,$K$4:$L$19,2,0),0) -> 502988778 | F24: =B24-C24 -> -1.3781914e+08
A25: DCO | B25: =IFERROR(VLOOKUP($A25,$B$4:$C$19,2,0),0) -> 486320169 | C25: =IFERROR(VLOOKUP($A25,$E$4:$F$19,2,0),0) -> 202280197 | D25: =IFERROR(VLOOKUP($A25,$H$4:$I$19,2,0),0) -> -32848612 | E25: =IFERROR(VLOOKUP($A25,$K$4:$L$19,2,0),0) -> 169431585 | F25: =B25-C25 -> 284039972
A26: DEP | B26: =IFERROR(VLOOKUP($A26,$B$4:$C$19,2,0),0) -> 79488858 | C26: =IFERROR(VLOOKUP($A26,$E$4:$F$19,2,0),0) -> 151372459 | D26: =IFERROR(VLOOKUP($A26,$H$4:$I$19,2,0),0) -> 9419648 | E26: =IFERROR(VLOOKUP($A26,$K$4:$L$19,2,0),0) -> 160792107 | F26: =B26-C26 -> -71883601
A27: DES | B27: =IFERROR(VLOOKUP($A27,$B$4:$C$19,2,0),0) -> 3.2742769e+08 | C27: =IFERROR(VLOOKUP($A27,$E$4:$F$19,2,0),0) -> 319390498 | D27: =IFERROR(VLOOKUP($A27,$H$4:$I$19,2,0),0) -> -71496509 | E27: =IFERROR(VLOOKUP($A27,$K$4:$L$19,2,0),0) -> 247893989 | F27: =B27-C27 -> 8037196.8
A28: DGI | B28: =IFERROR(VLOOKUP($A28,$B$4:$C$19,2,0),0) -> 1229933471 | C28: =IFERROR(VLOOKUP($A28,$E$4:$F$19,2,0),0) -> 1585394898 | D28: =IFERROR(VLOOKUP($A28,$H$4:$I$19,2,0),0) -> 38839886 | E28: =IFERROR(VLOOKUP($A28,$K$4:$L$19,2,0),0) -> 1624234784 | F28: =B28-C28 -> -355461427
A29: DGL | B29: =IFERROR(VLOOKUP($A29,$B$4:$C$19,2,0),0) -> 436919745 | C29: =IFERROR(VLOOKUP($A29,$E$4:$F$19,2,0),0) -> 337161507 | D29: =IFERROR(VLOOKUP($A29,$H$4:$I$19,2,0),0) -> 40212085 | E29: =IFERROR(VLOOKUP($A29,$K$4:$L$19,2,0),0) -> 377373592 | F29: =B29-C29 -> 99758238
A30: DHC | B30: =IFERROR(VLOOKUP($A30,$B$4:$C$19,2,0),0) -> 146170041 | C30: =IFERROR(VLOOKUP($A30,$E$4:$F$19,2,0),0) -> 339732550 | D30: =IFERROR(VLOOKUP($A30,$H$4:$I$19,2,0),0) -> -3120929 | E30: =IFERROR(VLOOKUP($A30,$K$4:$L$19,2,0),0) -> 336611621 | F30: =B30-C30 -> -193562509
A31: DHI | B31: =IFERROR(VLOOKUP($A31,$B$4:$C$19,2,0),0) -> 125279423 | C31: =IFERROR(VLOOKUP($A31,$E$4:$F$19,2,0),0) -> 243547684 | D31: =IFERROR(VLOOKUP($A31,$H$4:$I$19,2,0),0) -> 53055793 | E31: =IFERROR(VLOOKUP($A31,$K$4:$L$19,2,0),0) -> 296603477 | F31: =B31-C31 -> -118268261
A32: DIC | B32: =IFERROR(VLOOKUP($A32,$B$4:$C$19,2,0),0) -> 41091978 | C32: =IFERROR(VLOOKUP($A32,$E$4:$F$19,2,0),0) -> 41091978 | D32: =IFERROR(VLOOKUP($A32,$H$4:$I$19,2,0),0) -> -1608004 | E32: =IFERROR(VLOOKUP($A32,$K$4:$L$19,2,0),0) -> 39483974 | F32: =B32-C32 -> 0
A33: DIO | B33: =IFERROR(VLOOKUP($A33,$B$4:$C$19,2,0),0) -> 47567549 | C33: =IFERROR(VLOOKUP($A33,$E$4:$F$19,2,0),0) -> 44774892 | D33: =IFERROR(VLOOKUP($A33,$H$4:$I$19,2,0),0) -> 0 | E33: =IFERROR(VLOOKUP($A33,$K$4:$L$19,2,0),0) -> 44774892 | F33: =B33-C33 -> 2792657
A34: DDA | B34: =IFERROR(VLOOKUP($A34,$B$4:$C$19,2,0),0) -> 130045454 | C34: =IFERROR(VLOOKUP($A34,$E$4:$F$19,2,0),0) -> 268536935 | D34: =IFERROR(VLOOKUP($A34,$H$4:$I$19,2,0),0) -> 0 | E34: =IFERROR(VLOOKUP($A34,$K$4:$L$19,2,0),0) -> 268536935 | F34: =B34-C34 -> -138491481
A35: DPR | B35: =IFERROR(VLOOKUP($A35,$B$4:$C$19,2,0),0) -> 492863760 | C35: =IFERROR(VLOOKUP($A35,$E$4:$F$19,2,0),0) -> 442422045 | D35: =IFERROR(VLOOKUP($A35,$H$4:$I$19,2,0),0) -> -51606392 | E35: =IFERROR(VLOOKUP($A35,$K$4:$L$19,2,0),0) -> 390815653 | F35: =B35-C35 -> 50441715
... A39: EQM | B39: =IFERROR(VLOOKUP($A39,$B$4:$C$19,2,0),0) -> 0 | C39: =IFERROR(VLOOKUP($A39,$E$4:$F$19,2,0),0) -> -206156436 | D39: =IFERROR(VLOOKUP($A39,$H$4:$I$19,2,0),0) -> 0 | E39: =IFERROR(VLOOKUP($A39,$K$4:$L$19,2,0),0) -> -206156436 | F39: =B39-C39 -> 206156436
A40: IDIEM | B40: =SUM(B24:B39) -> 4.1231074e+09 | C40: =SUM(C24:C39) -> 4436911351 | D40: =SUM(D24:D39) -> 0 | E40: =SUM(E24:E39) -> 4436911351 | F40: =B40-C40 -> -3.1380391e+08
B41: =B40-C18 -> 4.1186415e+09 | C41: =C40-GETPIVOTDATA("[Measures].[Ingreso]",$E$3) -> 0 | D41: =D40-GETPIVOTDATA("[Measures].[Ingreso]",$H$3) -> 0 | E41: =E40-GETPIVOTDATA("[Measures].[Ingreso]",$K$3) -> 0 | F41: =B41-C41 -> 4.1186415e+09

Sheet IDIEM
I1: EERR s/TI Fact | J1: Etiquetas de columna
I2: Etiquetas de fila | J2: ene | K2: feb | L2: mar | M2: abr | N2: may | O2: jun | P2: jul | Q2: ago | R2: sep | S2: oct | T2: nov | U2: dic | V2: Total general
I3: DAC | J3: -171901206 | K3: 229661282 | L3: 169799213 | M3: 202455970 | N3: -76674690 | O3: 501144778 | V3: 854485347
I4: DCO | J4: 206690743 | K4: 512465962 | L4: 555906372 | M4: 323393211 | N4: 574669921 | O4: 202280197 | V4: 2375406406
I5: DDA | J5: 253505267 | K5: 260928783 | L5: 243506035 | M5: 317466070 | N5: 267291057 | O5: 268536935 | V5: 1611234147
I6: DEP | J6: 100713842 | K6: 103734301 | L6: 148678005 | M6: 137835819 | N6: 135342044 | O6: 151372459 | V6: 777676470
I7: DES | J7: 289140060 | K7: 257502742 | L7: 270815880 | M7: 267801174 | N7: 139450905 | O7: 319390498 | V7: 1544101259
I8: DGI | J8: 1271029488 | K8: 1406463891 | L8: 1338014616 | M8: -14883670 | N8: 2187487154 | O8: 1585394898 | V8: 7773506377
I9: DGL | J9: 286168992 | K9: 338984671 | L9: 241489944 | M9: 451087812 | N9: 341520986 | O9: 337161507 | V9: 1996413912
I10: DHC | J10: 243964570 | K10: 254759929 | L10: 270545544 | M10: 278000887 | N10: 260249811 | O10: 339732550 | V10: 1647253291
I11: DHI | J11: 247050882 | K11: 233153774 | L11: 266744910 | M11: 257612262 | N11: 219070248 | O11: 243547684 | V11: 1467179760
I12: DIC | J12: 16026670 | K12: 57914174 | L12: 25901536 | M12: 90119211 | N12: 81835932 | O12: 41091978 | V12: 312889501
I13: DIO | J13: 55747322 | K13: 55969812 | L13: 55377307 | M13: 48320406 | N13: -48922953 | O13: 44774892 | V13: 211266786
I14: DPR | J14: -78263649 | K14: 344738594 | L14: 360099288 | M14: 185834816 | N14: 360128874 | O14: 442422045 | V14: 1614959968
... I16: EQM | J16: -288986146 | K16: 288986146 | L16: 0 | M16: 0 | N16: -82829710 | O16: -206156436 | V16: -288986146
I17: MDQ | J17: 45730726 | K17: 0 | L17: 0 | M17: 0 | N17: -45730726 | V17: 0
A18: Facturación: Incluye Facturación externa y Traspasos de Servicios Internos | I18: SDO | J18: 4150871 | K18: 2970636 | L18: 10337952 | M18: 7262276 | N18: 6734151 | O18: 7007326 | V18: 38463212
A19: Traspasos: Corresponde solo a Traspasos de Facturación | I19: Total general | J19: 2573481448 | K19: 4525070140 | L19: 4144195780 | M19: 2761451807 | N19: 4499499811 | O19: 4436911351 | V19: 22940610337
A20: Valor en círculo: Representa diferncia entre Backlog y Facturación
I24: Se descarga de SalesForce a traves de una planilla de google sheets
I25: Ingreso_Salesforce | J25: Etiquetas de columna
I26: Etiquetas de fila | J26: ene | K26: feb | L26: mar | M26: abr | N26: may | O26: jun | P26: Total general
I27: DAC | J27: -169531556 | K27: 229661282 | L27: 132474079 | M27: 254268998 | N27: 4.6957042e+08 | O27: 3.6332564e+08 | P27: 1.2797689e+09
I28: DCO | J28: 842635563 | K28: 592333115 | L28: 354793861 | M28: 4.2707473e+08 | N28: 892309408 | O28: 486320169 | P28: 3.5954668e+09
I29: DDA | J29: 181228409 | K29: 129936364 | L29: 134027273 | M29: 157001893 | N29: 40429545 | O29: 130045454 | P29: 772668938
I30: DEP | J30: 27617921 | K30: 1.7119322e+08 | L30: 2.5230381e+08 | M30: 1.2067604e+08 | N30: 62156575 | O30: 79488858 | P30: 7.1343642e+08
I31: DES | J31: 289140060 | K31: 2.5750274e+08 | L31: 270815880 | M31: 267801174 | N31: 1.3945091e+08 | O31: 3.2742769e+08 | P31: 1.5521385e+09
I32: DGI | J32: 1271029488 | K32: 1406463891 | L32: 1321970041 | M32: -137844577 | N32: 3434507158 | O32: 1229933471 | P32: 8526059472
I33: DGL | J33: 286168992 | K33: 338984671 | L33: 230154271 | M33: 451087812 | N33: 341520986 | O33: 436919745 | P33: 2084836477
I34: DHC | J34: 73086361 | K34: 73231017 | L34: 80734296 | M34: 85650722 | N34: 83985839 | O34: 146170041 | P34: 542858276
I35: DHI | J35: 218731800 | K35: 172601844 | L35: 161539048 | M35: 196879192 | N35: 201803161 | O35: 125279423 | P35: 1076834468
I36: DIC | J36: 16026670 | K36: 57914174 | L36: 25901536 | M36: 90119211 | N36: 81835932 | O36: 41091978 | P36: 312889501
I37: DIO | J37: 50982594 | K37: 54985753 | L37: 42216285 | M37: 80987512 | N37: 47400975 | O37: 47567549 | P37: 324140668
I38: DPR | J38: 522514884 | K38: 478946114 | L38: 4.0956632e+08 | M38: 5.4676366e+08 | N38: 530145136 | O38: 492863760 | P38: 2980799873
... I41: Total general | J41: 3.7150929e+09 | K41: 4.1173616e+09 | L41: 3.6396797e+09 | M41: 2.7135035e+09 | N41: 6.583573e+09 | O41: 4.1231074e+09 | P41: 2.4892318e+10
I47: Salesforce | J47: Ene | K47: Feb | L47: Mar | M47: Abr | N47: May | O47: Jun | P47: Jul | Q47: Ago | R47: Sep | S47: Oct | T47: Nov | U47: Dic | V47: Total
I48: DAC | J48: =IFERROR(VLOOKUP($I48,$I$26:$V$42,MATCH(J$47,$I$26:$V$26,0),0),0) -> -169531556 | K48: =IFERROR(VLOOKUP($I48,$I$26:$V$42,MATCH(K$47,$I$26:$V$26,0),0),0) -> 229661282 | L48: =IFERROR(VLOOKUP($I48,$I$26:$V$42,MATCH(L$47,$I$26:$V$26,0),0),0) -> 132474079 | M48: =IFERROR(VLOOKUP($I48,$I$26:$V$42,MATCH(M$47,$I$26:$V$26,0),0),0) -> 254268998 | N48: =IFERROR(VLOOKUP($I48,$I$26:$V$42,MATCH(N$47,$I$26:$V$26,0),0),0) -> 4.6957042e+08 | O48: =IFERROR(VLOOKUP($I48,$I$26:$V$42,MATCH(O$47,$I$26:$V$26,0),0),0) -> 3.6332564e+08 | P48: =IFERROR(VLOOKUP($I48,$I$26:$V$42,MATCH(P$47,$I$26:$V$26,0),0),0) -> 0 | Q48: =IFERROR(VLOOKUP($I48,$I$26:$V$42,MATCH(Q$47,$I$26:$V$26,0),0),0) -> 0 | ... U48: =IFERROR(VLOOKUP($I48,$I$26:$V$42,MATCH(U$47,$I$26:$V$26,0),0),0) -> 0 | V48: =SUM(J48:U48) -> 1.2797689e+09
I49: DCO | J49: =IFERROR(VLOOKUP($I49,$I$26:$V$42,MATCH(J$47,$I$26:$V$26,0),0),0) -> 842635563 | K49: =IFERROR(VLOOKUP($I49,$I$26:$V$42,MATCH(K$47,$I$26:$V$26,0),0),0) -> 592333115 | L49: =IFERROR(VLOOKUP($I49,$I$26:$V$42,MATCH(L$47,$I$26:$V$26,0),0),0) -> 354793861 | M49: =IFERROR(VLOOKUP($I49,$I$26:$V$42,MATCH(M$47,$I$26:$V$26,0),0),0) -> 4.2707473e+08 | N49: =IFERROR(VLOOKUP($I49,$I$26:$V$42,MATCH(N$47,$I$26:$V$26,0),0),0) -> 892309408 | O49: =IFERROR(VLOOKUP($I49,$I$26:$V$42,MATCH(O$47,$I$26:$V$26,0),0),0) -> 486320169 | P49: =IFERROR(VLOOKUP($I49,$I$26:$V$42,MATCH(P$47,$I$26:$V$26,0),0),0) -> 0 | Q49: =IFERROR(VLOOKUP($I49,$I$26:$V$42,MATCH(Q$47,$I$26:$V$26,0),0),0) -> 0 | ... U49: =IFERROR(VLOOKUP($I49,$I$26:$V$42,MATCH(U$47,$I$26:$V$26,0),0),0) -> 0 | V49: =SUM(J49:U49) -> 3.5954668e+09
I50: DEP | J50: =IFERROR(VLOOKUP($I50,$I$26:$V$42,MATCH(J$47,$I$26:$V$26,0),0),0) -> 27617921 | K50: =IFERROR(VLOOKUP($I50,$I$26:$V$42,MATCH(K$47,$I$26:$V$26,0),0),0) -> 1.7119322e+08 | L50: =IFERROR(VLOOKUP($I50,$I$26:$V$42,MATCH(L$47,$I$26:$V$26,0),0),0) -> 2.5230381e+08 | M50: =IFERROR(VLOOKUP($I50,$I$26:$V$42,MATCH(M$47,$I$26:$V$26,0),0),0) -> 1.2067604e+08 | N50: =IFERROR(VLOOKUP($I50,$I$26:$V$42,MATCH(N$47,$I$26:$V$26,0),0),0) -> 62156575 | O50: =IFERROR(VLOOKUP($I50,$I$26:$V$42,MATCH(O$47,$I$26:$V$26,0),0),0) -> 79488858 | P50: =IFERROR(VLOOKUP($I50,$I$26:$V$42,MATCH(P$47,$I$26:$V$26,0),0),0) -> 0 | Q50: =IFERROR(VLOOKUP($I50,$I$26:$V$42,MATCH(Q$47,$I$26:$V$26,0),0),0) -> 0 | ... U50: =IFERROR(VLOOKUP($I50,$I$26:$V$42,MATCH(U$47,$I$26:$V$26,0),0),0) -> 0 | V50: =SUM(J50:U50) -> 7.1343642e+08
I51: DES | J51: =IFERROR(VLOOKUP($I51,$I$26:$V$42,MATCH(J$47,$I$26:$V$26,0),0),0) -> 289140060 | K51: =IFERROR(VLOOKUP($I51,$I$26:$V$42,MATCH(K$47,$I$26:$V$26,0),0),0) -> 2.5750274e+08 | L51: =IFERROR(VLOOKUP($I51,$I$26:$V$42,MATCH(L$47,$I$26:$V$26,0),0),0) -> 270815880 | M51: =IFERROR(VLOOKUP($I51,$I$26:$V$42,MATCH(M$47,$I$26:$V$26,0),0),0) -> 267801174 | N51: =IFERROR(VLOOKUP($I51,$I$26:$V$42,MATCH(N$47,$I$26:$V$26,0),0),0) -> 1.3945091e+08 | O51: =IFERROR(VLOOKUP($I51,$I$26:$V$42,MATCH(O$47,$I$26:$V$26,0),0),0) -> 3.2742769e+08 | P51: =IFERROR(VLOOKUP($I51,$I$26:$V$42,MATCH(P$47,$I$26:$V$26,0),0),0) -> 0 | Q51: =IFERROR(VLOOKUP($I51,$I$26:$V$42,MATCH(Q$47,$I$26:$V$26,0),0),0) -> 0 | ... U51: =IFERROR(VLOOKUP($I51,$I$26:$V$42,MATCH(U$47,$I$26:$V$26,0),0),0) -> 0 | V51: =SUM(J51:U51) -> 1.5521385e+09
I52: DGI | J52: =IFERROR(VLOOKUP($I52,$I$26:$V$42,MATCH(J$47,$I$26:$V$26,0),0),0) -> 1271029488 | K52: =IFERROR(VLOOKUP($I52,$I$26:$V$42,MATCH(K$47,$I$26:$V$26,0),0),0) -> 1406463891 | L52: =IFERROR(VLOOKUP($I52,$I$26:$V$42,MATCH(L$47,$I$26:$V$26,0),0),0) -> 1321970041 | M52: =IFERROR(VLOOKUP($I52,$I$26:$V$42,MATCH(M$47,$I$26:$V$26,0),0),0) -> -137844577 | N52: =IFERROR(VLOOKUP($I52,$I$26:$V$42,MATCH(N$47,$I$26:$V$26,0),0),0) -> 3434507158 | O52: =IFERROR(VLOOKUP($I52,$I$26:$V$42,MATCH(O$47,$I$26:$V$26,0),0),0) -> 1229933471 | P52: =IFERROR(VLOOKUP($I52,$I$26:$V$42,MATCH(P$47,$I$26:$V$26,0),0),0) -> 0 | Q52: =IFERROR(VLOOKUP($I52,$I$26:$V$42,MATCH(Q$47,$I$26:$V$26,0),0),0) -> 0 | ... U52: =IFERROR(VLOOKUP($I52,$I$26:$V$42,MATCH(U$47,$I$26:$V$26,0),0),0) -> 0 | V52: =SUM(J52:U52) -> 8526059472
I53: DGL | J53: =IFERROR(VLOOKUP($I53,$I$26:$V$42,MATCH(J$47,$I$26:$V$26,0),0),0) -> 286168992 | K53: =IFERROR(VLOOKUP($I53,$I$26:$V$42,MATCH(K$47,$I$26:$V$26,0),0),0) -> 338984671 | L53: =IFERROR(VLOOKUP($I53,$I$26:$V$42,MATCH(L$47,$I$26:$V$26,0),0),0) -> 230154271 | M53: =IFERROR(VLOOKUP($I53,$I$26:$V$42,MATCH(M$47,$I$26:$V$26,0),0),0) -> 451087812 | N53: =IFERROR(VLOOKUP($I53,$I$26:$V$42,MATCH(N$47,$I$26:$V$26,0),0),0) -> 341520986 | O53: =IFERROR(VLOOKUP($I53,$I$26:$V$42,MATCH(O$47,$I$26:$V$26,0),0),0) -> 436919745 | P53: =IFERROR(VLOOKUP($I53,$I$26:$V$42,MATCH(P$47,$I$26:$V$26,0),0),0) -> 0 | Q53: =IFERROR(VLOOKUP($I53,$I$26:$V$42,MATCH(Q$47,$I$26:$V$26,0),0),0) -> 0 | ... U53: =IFERROR(VLOOKUP($I53,$I$26:$V$42,MATCH(U$47,$I$26:$V$26,0),0),0) -> 0 | V53: =SUM(J53:U53) -> 2084836477
I54: DHC | J54: =IFERROR(VLOOKUP($I54,$I$26:$V$42,MATCH(J$47,$I$26:$V$26,0),0),0) -> 73086361 | K54: =IFERROR(VLOOKUP($I54,$I$26:$V$42,MATCH(K$47,$I$26:$V$26,0),0),0) -> 73231017 | L54: =IFERROR(VLOOKUP($I54,$I$26:$V$42,MATCH(L$47,$I$26:$V$26,0),0),0) -> 80734296 | M54: =IFERROR(VLOOKUP($I54,$I$26:$V$42,MATCH(M$47,$I$26:$V$26,0),0),0) -> 85650722 | N54: =IFERROR(VLOOKUP($I54,$I$26:$V$42,MATCH(N$47,$I$26:$V$26,0),0),0) -> 83985839 | O54: =IFERROR(VLOOKUP($I54,$I$26:$V$42,MATCH(O$47,$I$26:$V$26,0),0),0) -> 146170041 | P54: =IFERROR(VLOOKUP($I54,$I$26:$V$42,MATCH(P$47,$I$26:$V$26,0),0),0) -> 0 | Q54: =IFERROR(VLOOKUP($I54,$I$26:$V$42,MATCH(Q$47,$I$26:$V$26,0),0),0) -> 0 | ... U54: =IFERROR(VLOOKUP($I54,$I$26:$V$42,MATCH(U$47,$I$26:$V$26,0),0),0) -> 0 | V54: =SUM(J54:U54) -> 542858276
I55: DHI | J55: =IFERROR(VLOOKUP($I55,$I$26:$V$42,MATCH(J$47,$I$26:$V$26,0),0),0) -> 218731800 | K55: =IFERROR(VLOOKUP($I55,$I$26:$V$42,MATCH(K$47,$I$26:$V$26,0),0),0) -> 172601844 | L55: =IFERROR(VLOOKUP($I55,$I$26:$V$42,MATCH(L$47,$I$26:$V$26,0),0),0) -> 161539048 | M55: =IFERROR(VLOOKUP($I55,$I$26:$V$42,MATCH(M$47,$I$26:$V$26,0),0),0) -> 196879192 | N55: =IFERROR(VLOOKUP($I55,$I$26:$V$42,MATCH(N$47,$I$26:$V$26,0),0),0) -> 201803161 | O55: =IFERROR(VLOOKUP($I55,$I$26:$V$42,MATCH(O$47,$I$26:$V$26,0),0),0) -> 125279423 | P55: =IFERROR(VLOOKUP($I55,$I$26:$V$42,MATCH(P$47,$I$26:$V$26,0),0),0) -> 0 | Q55: =IFERROR(VLOOKUP($I55,$I$26:$V$42,MATCH(Q$47,$I$26:$V$26,0),0),0) -> 0 | ... U55: =IFERROR(VLOOKUP($I55,$I$26:$V$42,MATCH(U$47,$I$26:$V$26,0),0),0) -> 0 | V55: =SUM(J55:U55) -> 1076834468
I56: DIC | J56: =IFERROR(VLOOKUP($I56,$I$26:$V$42,MATCH(J$47,$I$26:$V$26,0),0),0) -> 16026670 | K56: =IFERROR(VLOOKUP($I56,$I$26:$V$42,MATCH(K$47,$I$26:$V$26,0),0),0) -> 57914174 | L56: =IFERROR(VLOOKUP($I56,$I$26:$V$42,MATCH(L$47,$I$26:$V$26,0),0),0) -> 25901536 | M56: =IFERROR(VLOOKUP($I56,$I$26:$V$42,MATCH(M$47,$I$26:$V$26,0),0),0) -> 90119211 | N56: =IFERROR(VLOOKUP($I56,$I$26:$V$42,MATCH(N$47,$I$26:$V$26,0),0),0) -> 81835932 | O56: =IFERROR(VLOOKUP($I56,$I$26:$V$42,MATCH(O$47,$I$26:$V$26,0),0),0) -> 41091978 | P56: =IFERROR(VLOOKUP($I56,$I$26:$V$42,MATCH(P$47,$I$26:$V$26,0),0),0) -> 0 | Q56: =IFERROR(VLOOKUP($I56,$I$26:$V$42,MATCH(Q$47,$I$26:$V$26,0),0),0) -> 0 | ... U56: =IFERROR(VLOOKUP($I56,$I$26:$V$42,MATCH(U$47,$I$26:$V$26,0),0),0) -> 0 | V56: =SUM(J56:U56) -> 312889501
I57: DIO | J57: =IFERROR(VLOOKUP($I57,$I$26:$V$42,MATCH(J$47,$I$26:$V$26,0),0),0) -> 50982594 | K57: =IFERROR(VLOOKUP($I57,$I$26:$V$42,MATCH(K$47,$I$26:$V$26,0),0),0) -> 54985753 | L57: =IFERROR(VLOOKUP($I57,$I$26:$V$42,MATCH(L$47,$I$26:$V$26,0),0),0) -> 42216285 | M57: =IFERROR(VLOOKUP($I57,$I$26:$V$42,MATCH(M$47,$I$26:$V$26,0),0),0) -> 80987512 | N57: =IFERROR(VLOOKUP($I57,$I$26:$V$42,MATCH(N$47,$I$26:$V$26,0),0),0) -> 47400975 | O57: =IFERROR(VLOOKUP($I57,$I$26:$V$42,MATCH(O$47,$I$26:$V$26,0),0),0) -> 47567549 | P57: =IFERROR(VLOOKUP($I57,$I$26:$V$42,MATCH(P$47,$I$26:$V$26,0),0),0) -> 0 | Q57: =IFERROR(VLOOKUP($I57,$I$26:$V$42,MATCH(Q$47,$I$26:$V$26,0),0),0) -> 0 | ... U57: =IFERROR(VLOOKUP($I57,$I$26:$V$42,MATCH(U$47,$I$26:$V$26,0),0),0) -> 0 | V57: =SUM(J57:U57) -> 324140668
I58: DDA | J58: =IFERROR(VLOOKUP($I58,$I$26:$V$42,MATCH(J$47,$I$26:$V$26,0),0),0)+IFERROR(VLOOKUP("DOH",$I$26:$V$42,MATCH(J$47,$I$26:$V$26,0),0),0) -> 181228409 | K58: =IFERROR(VLOOKUP($I58,$I$26:$V$42,MATCH(K$47,$I$26:$V$26,0),0),0)+IFERROR(VLOOKUP("DOH",$I$26:$V$42,MATCH(K$47,$I$26:$V$26,0),0),0) -> 129936364 | L58: =IFERROR(VLOOKUP($I58,$I$26:$V$42,MATCH(L$47,$I$26:$V$26,0),0),0)+IFERROR(VLOOKUP("DOH",$I$26:$V$42,MATCH(L$47,$I$26:$V$26,0),0),0) -> 134027273 | M58: =IFERROR(VLOOKUP($I58,$I$26:$V$42,MATCH(M$47,$I$26:$V$26,0),0),0)+IFERROR(VLOOKUP("DOH",$I$26:$V$42,MATCH(M$47,$I$26:$V$26,0),0),0) -> 157001893 | N58: =IFERROR(VLOOKUP($I58,$I$26:$V$42,MATCH(N$47,$I$26:$V$26,0),0),0)+IFERROR(VLOOKUP("DOH",$I$26:$V$42,MATCH(N$47,$I$26:$V$26,0),0),0) -> 40429545 | O58: =IFERROR(VLOOKUP($I58,$I$26:$V$42,MATCH(O$47,$I$26:$V$26,0),0),0)+IFERROR(VLOOKUP("DOH",$I$26:$V$42,MATCH(O$47,$I$26:$V$26,0),0),0) -> 130045454 | P58: =IFERROR(VLOOKUP($I58,$I$26:$V$42,MATCH(P$47,$I$26:$V$26,0),0),0)+IFERROR(VLOOKUP("DOH",$I$26:$V$42,MATCH(P$47,$I$26:$V$26,0),0),0) -> 0 | Q58: =IFERROR(VLOOKUP($I58,$I$26:$V$42,MATCH(Q$47,$I$26:$V$26,0),0),0)+IFERROR(VLOOKUP("DOH",$I$26:$V$42,MATCH(Q$47,$I$26:$V$26,0),0),0) -> 0 | ... U58: =IFERROR(VLOOKUP($I58,$I$26:$V$42,MATCH(U$47,$I$26:$V$26,0),0),0)+IFERROR(VLOOKUP("DOH",$I$26:$V$42,MATCH(U$47,$I$26:$V$26,0),0),0) -> 0 | V58: =SUM(J58:U58) -> 772668938
I59: DPR | J59: =IFERROR(VLOOKUP($I59,$I$26:$V$42,MATCH(J$47,$I$26:$V$26,0),0),0) -> 522514884 | K59: =IFERROR(VLOOKUP($I59,$I$26:$V$42,MATCH(K$47,$I$26:$V$26,0),0),0) -> 478946114 | L59: =IFERROR(VLOOKUP($I59,$I$26:$V$42,MATCH(L$47,$I$26:$V$26,0),0),0) -> 4.0956632e+08 | M59: =IFERROR(VLOOKUP($I59,$I$26:$V$42,MATCH(M$47,$I$26:$V$26,0),0),0) -> 5.4676366e+08 | N59: =IFERROR(VLOOKUP($I59,$I$26:$V$42,MATCH(N$47,$I$26:$V$26,0),0),0) -> 530145136 | O59: =IFERROR(VLOOKUP($I59,$I$26:$V$42,MATCH(O$47,$I$26:$V$26,0),0),0) -> 492863760 | P59: =IFERROR(VLOOKUP($I59,$I$26:$V$42,MATCH(P$47,$I$26:$V$26,0),0),0) -> 0 | Q59: =IFERROR(VLOOKUP($I59,$I$26:$V$42,MATCH(Q$47,$I$26:$V$26,0),0),0) -> 0 | ... U59: =IFERROR(VLOOKUP($I59,$I$26:$V$42,MATCH(U$47,$I$26:$V$26,0),0),0) -> 0 | V59: =SUM(J59:U59) -> 2980799873
I60: DTC | J60: =IFERROR(VLOOKUP($I60,$I$26:$V$42,MATCH(J$47,$I$26:$V$26,0),0),0) -> 1.0186675e+08 | K60: =IFERROR(VLOOKUP($I60,$I$26:$V$42,MATCH(K$47,$I$26:$V$26,0),0),0) -> 1.5340891e+08 | L60: =IFERROR(VLOOKUP($I60,$I$26:$V$42,MATCH(L$47,$I$26:$V$26,0),0),0) -> 2.1757082e+08 | M60: =IFERROR(VLOOKUP($I60,$I$26:$V$42,MATCH(M$47,$I$26:$V$26,0),0),0) -> 1.6916078e+08 | N60: =IFERROR(VLOOKUP($I60,$I$26:$V$42,MATCH(N$47,$I$26:$V$26,0),0),0) -> 2.5458868e+08 | O60: =IFERROR(VLOOKUP($I60,$I$26:$V$42,MATCH(O$47,$I$26:$V$26,0),0),0) -> 2.1220769e+08 | P60: =IFERROR(VLOOKUP($I60,$I$26:$V$42,MATCH(P$47,$I$26:$V$26,0),0),0) -> 0 | Q60: =IFERROR(VLOOKUP($I60,$I$26:$V$42,MATCH(Q$47,$I$26:$V$26,0),0),0) -> 0 | ... U60: =IFERROR(VLOOKUP($I60,$I$26:$V$42,MATCH(U$47,$I$26:$V$26,0),0),0) -> 0 | V60: =SUM(J60:U60) -> 1.1088036e+09
I61: EQM | J61: =IFERROR(VLOOKUP($I61,$I$26:$V$42,MATCH(J$47,$I$26:$V$26,0),0),0) -> 0 | K61: =IFERROR(VLOOKUP($I61,$I$26:$V$42,MATCH(K$47,$I$26:$V$26,0),0),0) -> 0 | L61: =IFERROR(VLOOKUP($I61,$I$26:$V$42,MATCH(L$47,$I$26:$V$26,0),0),0) -> 0 | M61: =IFERROR(VLOOKUP($I61,$I$26:$V$42,MATCH(M$47,$I$26:$V$26,0),0),0) -> 0 | N61: =IFERROR(VLOOKUP($I61,$I$26:$V$42,MATCH(N$47,$I$26:$V$26,0),0),0) -> 0 | O61: =IFERROR(VLOOKUP($I61,$I$26:$V$42,MATCH(O$47,$I$26:$V$26,0),0),0) -> 0 | P61: =IFERROR(VLOOKUP($I61,$I$26:$V$42,MATCH(P$47,$I$26:$V$26,0),0),0) -> 0 | Q61: =IFERROR(VLOOKUP($I61,$I$26:$V$42,MATCH(Q$47,$I$26:$V$26,0),0),0) -> 0 | ... U61: =IFERROR(VLOOKUP($I61,$I$26:$V$42,MATCH(U$47,$I$26:$V$26,0),0),0) -> 0 | V61: =SUM(J61:U61) -> 0
I62: MDQ | J62: =IFERROR(VLOOKUP($I62,$I$26:$V$42,MATCH(J$47,$I$26:$V$26,0),0),0) -> 0 | K62: =IFERROR(VLOOKUP($I62,$I$26:$V$42,MATCH(K$47,$I$26:$V$26,0),0),0) -> 0 | L62: =IFERROR(VLOOKUP($I62,$I$26:$V$42,MATCH(L$47,$I$26:$V$26,0),0),0) -> 0 | M62: =IFERROR(VLOOKUP($I62,$I$26:$V$42,MATCH(M$47,$I$26:$V$26,0),0),0) -> 0 | N62: =IFERROR(VLOOKUP($I62,$I$26:$V$42,MATCH(N$47,$I$26:$V$26,0),0),0) -> 0 | O62: =IFERROR(VLOOKUP($I62,$I$26:$V$42,MATCH(O$47,$I$26:$V$26,0),0),0) -> 0 | P62: =IFERROR(VLOOKUP($I62,$I$26:$V$42,MATCH(P$47,$I$26:$V$26,0),0),0) -> 0 | Q62: =IFERROR(VLOOKUP($I62,$I$26:$V$42,MATCH(Q$47,$I$26:$V$26,0),0),0) -> 0 | ... U62: =IFERROR(VLOOKUP($I62,$I$26:$V$42,MATCH(U$47,$I$26:$V$26,0),0),0) -> 0 | V62: =SUM(J62:U62) -> 0
I63: SDO | J63: =IFERROR(VLOOKUP($I63,$I$26:$V$42,MATCH(J$47,$I$26:$V$26,0),0),0) -> 3594914 | K63: =IFERROR(VLOOKUP($I63,$I$26:$V$42,MATCH(K$47,$I$26:$V$26,0),0),0) -> 198466 | L63: =IFERROR(VLOOKUP($I63,$I$26:$V$42,MATCH(L$47,$I$26:$V$26,0),0),0) -> 5612144 | M63: =IFERROR(VLOOKUP($I63,$I$26:$V$42,MATCH(M$47,$I$26:$V$26,0),0),0) -> 3876374 | N63: =IFERROR(VLOOKUP($I63,$I$26:$V$42,MATCH(N$47,$I$26:$V$26,0),0),0) -> 3868251 | O63: =IFERROR(VLOOKUP($I63,$I$26:$V$42,MATCH(O$47,$I$26:$V$26,0),0),0) -> 4465971 | P63: =IFERROR(VLOOKUP($I63,$I$26:$V$42,MATCH(P$47,$I$26:$V$26,0),0),0) -> 0 | Q63: =IFERROR(VLOOKUP($I63,$I$26:$V$42,MATCH(Q$47,$I$26:$V$26,0),0),0) -> 0 | ... U63: =IFERROR(VLOOKUP($I63,$I$26:$V$42,MATCH(U$47,$I$26:$V$26,0),0),0) -> 0 | V63: =SUM(J63:U63) -> 21616120
I64: Total | J64: =SUM(J48:J63) -> 3.7150929e+09 | K64: =SUM(K48:K63) -> 4.1173616e+09 | L64: =SUM(L48:L63) -> 3.6396797e+09 | M64: =SUM(M48:M63) -> 2.7135035e+09 | N64: =SUM(N48:N63) -> 6.583573e+09 | O64: =SUM(O48:O63) -> 4.1231074e+09 | P64: =SUM(P48:P63) -> 0 | Q64: =SUM(Q48:Q63) -> 0 | ... U64: =SUM(U48:U63) -> 0 | V64: =SUM(J64:U64) -> 2.4892318e+10
I68: Diferencia | J68: Ene | K68: Feb | L68: Mar | M68: Abr | N68: May | O68: Jun | P68: Jul | Q68: Ago | R68: Sep | S68: Oct | T68: Nov | U68: Dic | V68: Total
I69: DAC | J69: =-IFERROR(VLOOKUP($I69,$I$47:$U$67,MATCH(J$68,$I$47:$U$47,0),0),0)+IFERROR(VLOOKUP($I69,$I$2:$U$23,MATCH(J$68,$I$2:$U$2,0),0),0) -> -2369650 | K69: =-IFERROR(VLOOKUP($I69,$I$47:$U$67,MATCH(K$68,$I$47:$U$47,0),0),0)+IFERROR(VLOOKUP($I69,$I$2:$U$23,MATCH(K$68,$I$2:$U$2,0),0),0) -> 0 | L69: =-IFERROR(VLOOKUP($I69,$I$47:$U$67,MATCH(L$68,$I$47:$U$47,0),0),0)+IFERROR(VLOOKUP($I69,$I$2:$U$23,MATCH(L$68,$I$2:$U$2,0),0),0) -> 37325134 | M69: =-IFERROR(VLOOKUP($I69,$I$47:$U$67,MATCH(M$68,$I$47:$U$47,0),0),0)+IFERROR(VLOOKUP($I69,$I$2:$U$23,MATCH(M$68,$I$2:$U$2,0),0),0) -> -51813028 | N69: =-IFERROR(VLOOKUP($I69,$I$47:$U$67,MATCH(N$68,$I$47:$U$47,0),0),0)+IFERROR(VLOOKUP($I69,$I$2:$U$23,MATCH(N$68,$I$2:$U$2,0),0),0) -> -5.4624511e+08 | O69: =-IFERROR(VLOOKUP($I69,$I$47:$U$67,MATCH(O$68,$I$47:$U$47,0),0),0)+IFERROR(VLOOKUP($I69,$I$2:$U$23,MATCH(O$68,$I$2:$U$2,0),0),0) -> 1.3781914e+08 | P69: =-IFERROR(VLOOKUP($I69,$I$47:$U$67,MATCH(P$68,$I$47:$U$47,0),0),0)+IFERROR(VLOOKUP($I69,$I$2:$U$23,MATCH(P$68,$I$2:$U$2,0),0),0) -> 0 | Q69: =-IFERROR(VLOOKUP($I69,$I$47:$U$67,MATCH(Q$68,$I$47:$U$47,0),0),0)+IFERROR(VLOOKUP($I69,$I$2:$U$23,MATCH(Q$68,$I$2:$U$2,0),0),0) -> 0 | ... U69: =-IFERROR(VLOOKUP($I69,$I$47:$U$67,MATCH(U$68,$I$47:$U$47,0),0),0)+IFERROR(VLOOKUP($I69,$I$2:$U$23,MATCH(U$68,$I$2:$U$2,0),0),0) -> 0 | V69: =SUM(J69:U69) -> -4.2528352e+08
I70: DCO | J70: =-IFERROR(VLOOKUP($I70,$I$47:$U$67,MATCH(J$68,$I$47:$U$47,0),0),0)+IFERROR(VLOOKUP($I70,$I$2:$U$23,MATCH(J$68,$I$2:$U$2,0),0),0) -> -635944820 | K70: =-IFERROR(VLOOKUP($I70,$I$47:$U$67,MATCH(K$68,$I$47:$U$47,0),0),0)+IFERROR(VLOOKUP($I70,$I$2:$U$23,MATCH(K$68,$I$2:$U$2,0),0),0) -> -79867153 | L70: =-IFERROR(VLOOKUP($I70,$I$47:$U$67,MATCH(L$68,$I$47:$U$47,0),0),0)+IFERROR(VLOOKUP($I70,$I$2:$U$23,MATCH(L$68,$I$2:$U$2,0),0),0) -> 201112511 | M70: =-IFERROR(VLOOKUP($I70,$I$47:$U$67,MATCH(M$68,$I$47:$U$47,0),0),0)+IFERROR(VLOOKUP($I70,$I$2:$U$23,MATCH(M$68,$I$2:$U$2,0),0),0) -> -1.0368152e+08 | N70: =-IFERROR(VLOOKUP($I70,$I$47:$U$67,MATCH(N$68,$I$47:$U$47,0),0),0)+IFERROR(VLOOKUP($I70,$I$2:$U$23,MATCH(N$68,$I$2:$U$2,0),0),0) -> -317639487 | O70: =-IFERROR(VLOOKUP($I70,$I$47:$U$67,MATCH(O$68,$I$47:$U$47,0),0),0)+IFERROR(VLOOKUP($I70,$I$2:$U$23,MATCH(O$68,$I$2:$U$2,0),0),0) -> -284039972 | P70: =-IFERROR(VLOOKUP($I70,$I$47:$U$67,MATCH(P$68,$I$47:$U$47,0),0),0)+IFERROR(VLOOKUP($I70,$I$2:$U$23,MATCH(P$68,$I$2:$U$2,0),0),0) -> 0 | Q70: =-IFERROR(VLOOKUP($I70,$I$47:$U$67,MATCH(Q$68,$I$47:$U$47,0),0),0)+IFERROR(VLOOKUP($I70,$I$2:$U$23,MATCH(Q$68,$I$2:$U$2,0),0),0) -> 0 | ... U70: =-IFERROR(VLOOKUP($I70,$I$47:$U$67,MATCH(U$68,$I$47:$U$47,0),0),0)+IFERROR(VLOOKUP($I70,$I$2:$U$23,MATCH(U$68,$I$2:$U$2,0),0),0) -> 0 | V70: =SUM(J70:U70) -> -1.2200604e+09
I71: DEP | J71: =-IFERROR(VLOOKUP($I71,$I$47:$U$67,MATCH(J$68,$I$47:$U$47,0),0),0)+IFERROR(VLOOKUP($I71,$I$2:$U$23,MATCH(J$68,$I$2:$U$2,0),0),0) -> 73095921 | K71: =-IFERROR(VLOOKUP($I71,$I$47:$U$67,MATCH(K$68,$I$47:$U$47,0),0),0)+IFERROR(VLOOKUP($I71,$I$2:$U$23,MATCH(K$68,$I$2:$U$2,0),0),0) -> -67458916 | L71: =-IFERROR(VLOOKUP($I71,$I$47:$U$67,MATCH(L$68,$I$47:$U$47,0),0),0)+IFERROR(VLOOKUP($I71,$I$2:$U$23,MATCH(L$68,$I$2:$U$2,0),0),0) -> -1.0362581e+08 | M71: =-IFERROR(VLOOKUP($I71,$I$47:$U$67,MATCH(M$68,$I$47:$U$47,0),0),0)+IFERROR(VLOOKUP($I71,$I$2:$U$23,MATCH(M$68,$I$2:$U$2,0),0),0) -> 17159780 | N71: =-IFERROR(VLOOKUP($I71,$I$47:$U$67,MATCH(N$68,$I$47:$U$47,0),0),0)+IFERROR(VLOOKUP($I71,$I$2:$U$23,MATCH(N$68,$I$2:$U$2,0),0),0) -> 73185469 | O71: =-IFERROR(VLOOKUP($I71,$I$47:$U$67,MATCH(O$68,$I$47:$U$47,0),0),0)+IFERROR(VLOOKUP($I71,$I$2:$U$23,MATCH(O$68,$I$2:$U$2,0),0),0) -> 71883601 | P71: =-IFERROR(VLOOKUP($I71,$I$47:$U$67,MATCH(P$68,$I$47:$U$47,0),0),0)+IFERROR(VLOOKUP($I71,$I$2:$U$23,MATCH(P$68,$I$2:$U$2,0),0),0) -> 0 | Q71: =-IFERROR(VLOOKUP($I71,$I$47:$U$67,MATCH(Q$68,$I$47:$U$47,0),0),0)+IFERROR(VLOOKUP($I71,$I$2:$U$23,MATCH(Q$68,$I$2:$U$2,0),0),0) -> 0 | ... U71: =-IFERROR(VLOOKUP($I71,$I$47:$U$67,MATCH(U$68,$I$47:$U$47,0),0),0)+IFERROR(VLOOKUP($I71,$I$2:$U$23,MATCH(U$68,$I$2:$U$2,0),0),0) -> 0 | V71: =SUM(J71:U71) -> 64240048
I72: DES | J72: =-IFERROR(VLOOKUP($I72,$I$47:$U$67,MATCH(J$68,$I$47:$U$47,0),0),0)+IFERROR(VLOOKUP($I72,$I$2:$U$23,MATCH(J$68,$I$2:$U$2,0),0),0) -> 0 | K72: =-IFERROR(VLOOKUP($I72,$I$47:$U$67,MATCH(K$68,$I$47:$U$47,0),0),0)+IFERROR(VLOOKUP($I72,$I$2:$U$23,MATCH(K$68,$I$2:$U$2,0),0),0) -> 0 | L72: =-IFERROR(VLOOKUP($I72,$I$47:$U$67,MATCH(L$68,$I$47:$U$47,0),0),0)+IFERROR(VLOOKUP($I72,$I$2:$U$23,MATCH(L$68,$I$2:$U$2,0),0),0) -> 0 | M72: =-IFERROR(VLOOKUP($I72,$I$47:$U$67,MATCH(M$68,$I$47:$U$47,0),0),0)+IFERROR(VLOOKUP($I72,$I$2:$U$23,MATCH(M$68,$I$2:$U$2,0),0),0) -> 0 | N72: =-IFERROR(VLOOKUP($I72,$I$47:$U$67,MATCH(N$68,$I$47:$U$47,0),0),0)+IFERROR(VLOOKUP($I72,$I$2:$U$23,MATCH(N$68,$I$2:$U$2,0),0),0) -> -0.39999998 | O72: =-IFERROR(VLOOKUP($I72,$I$47:$U$67,MATCH(O$68,$I$47:$U$47,0),0),0)+IFERROR(VLOOKUP($I72,$I$2:$U$23,MATCH(O$68,$I$2:$U$2,0),0),0) -> -8037196.8 | P72: =-IFERROR(VLOOKUP($I72,$I$47:$U$67,MATCH(P$68,$I$47:$U$47,0),0),0)+IFERROR(VLOOKUP($I72,$I$2:$U$23,MATCH(P$68,$I$2:$U$2,0),0),0) -> 0 | Q72: =-IFERROR(VLOOKUP($I72,$I$47:$U$67,MATCH(Q$68,$I$47:$U$47,0),0),0)+IFERROR(VLOOKUP($I72,$I$2:$U$23,MATCH(Q$68,$I$2:$U$2,0),0),0) -> 0 | ... U72: =-IFERROR(VLOOKUP($I72,$I$47:$U$67,MATCH(U$68,$I$47:$U$47,0),0),0)+IFERROR(VLOOKUP($I72,$I$2:$U$23,MATCH(U$68,$I$2:$U$2,0),0),0) -> 0 | V72: =SUM(J72:U72) -> -8037197.2
I73: DGI | J73: =-IFERROR(VLOOKUP($I73,$I$47:$U$67,MATCH(J$68,$I$47:$U$47,0),0),0)+IFERROR(VLOOKUP($I73,$I$2:$U$23,MATCH(J$68,$I$2:$U$2,0),0),0) -> 0 | K73: =-IFERROR(VLOOKUP($I73,$I$47:$U$67,MATCH(K$68,$I$47:$U$47,0),0),0)+IFERROR(VLOOKUP($I73,$I$2:$U$23,MATCH(K$68,$I$2:$U$2,0),0),0) -> 0 | L73: =-IFERROR(VLOOKUP($I73,$I$47:$U$67,MATCH(L$68,$I$47:$U$47,0),0),0)+IFERROR(VLOOKUP($I73,$I$2:$U$23,MATCH(L$68,$I$2:$U$2,0),0),0) -> 16044575 | M73: =-IFERROR(VLOOKUP($I73,$I$47:$U$67,MATCH(M$68,$I$47:$U$47,0),0),0)+IFERROR(VLOOKUP($I73,$I$2:$U$23,MATCH(M$68,$I$2:$U$2,0),0),0) -> 122960907 | N73: =-IFERROR(VLOOKUP($I73,$I$47:$U$67,MATCH(N$68,$I$47:$U$47,0),0),0)+IFERROR(VLOOKUP($I73,$I$2:$U$23,MATCH(N$68,$I$2:$U$2,0),0),0) -> -1247020004 | O73: =-IFERROR(VLOOKUP($I73,$I$47:$U$67,MATCH(O$68,$I$47:$U$47,0),0),0)+IFERROR(VLOOKUP($I73,$I$2:$U$23,MATCH(O$68,$I$2:$U$2,0),0),0) -> 355461427 | P73: =-IFERROR(VLOOKUP($I73,$I$47:$U$67,MATCH(P$68,$I$47:$U$47,0),0),0)+IFERROR(VLOOKUP($I73,$I$2:$U$23,MATCH(P$68,$I$2:$U$2,0),0),0) -> 0 | Q73: =-IFERROR(VLOOKUP($I73,$I$47:$U$67,MATCH(Q$68,$I$47:$U$47,0),0),0)+IFERROR(VLOOKUP($I73,$I$2:$U$23,MATCH(Q$68,$I$2:$U$2,0),0),0) -> 0 | ... U73: =-IFERROR(VLOOKUP($I73,$I$47:$U$67,MATCH(U$68,$I$47:$U$47,0),0),0)+IFERROR(VLOOKUP($I73,$I$2:$U$23,MATCH(U$68,$I$2:$U$2,0),0),0) -> 0 | V73: =SUM(J73:U73) -> -752553095
I74: DGL | J74: =-IFERROR(VLOOKUP($I74,$I$47:$U$67,MATCH(J$68,$I$47:$U$47,0),0),0)+IFERROR(VLOOKUP($I74,$I$2:$U$23,MATCH(J$68,$I$2:$U$2,0),0),0) -> 0 | K74: =-IFERROR(VLOOKUP($I74,$I$47:$U$67,MATCH(K$68,$I$47:$U$47,0),0),0)+IFERROR(VLOOKUP($I74,$I$2:$U$23,MATCH(K$68,$I$2:$U$2,0),0),0) -> 0 | L74: =-IFERROR(VLOOKUP($I74,$I$47:$U$67,MATCH(L$68,$I$47:$U$47,0),0),0)+IFERROR(VLOOKUP($I74,$I$2:$U$23,MATCH(L$68,$I$2:$U$2,0),0),0) -> 11335673 | M74: =-IFERROR(VLOOKUP($I74,$I$47:$U$67,MATCH(M$68,$I$47:$U$47,0),0),0)+IFERROR(VLOOKUP($I74,$I$2:$U$23,MATCH(M$68,$I$2:$U$2,0),0),0) -> 0 | N74: =-IFERROR(VLOOKUP($I74,$I$47:$U$67,MATCH(N$68,$I$47:$U$47,0),0),0)+IFERROR(VLOOKUP($I74,$I$2:$U$23,MATCH(N$68,$I$2:$U$2,0),0),0) -> 0 | O74: =-IFERROR(VLOOKUP($I74,$I$47:$U$67,MATCH(O$68,$I$47:$U$47,0),0),0)+IFERROR(VLOOKUP($I74,$I$2:$U$23,MATCH(O$68,$I$2:$U$2,0),0),0) -> -99758238 | P74: =-IFERROR(VLOOKUP($I74,$I$47:$U$67,MATCH(P$68,$I$47:$U$47,0),0),0)+IFERROR(VLOOKUP($I74,$I$2:$U$23,MATCH(P$68,$I$2:$U$2,0),0),0) -> 0 | Q74: =-IFERROR(VLOOKUP($I74,$I$47:$U$67,MATCH(Q$68,$I$47:$U$47,0),0),0)+IFERROR(VLOOKUP($I74,$I$2:$U$23,MATCH(Q$68,$I$2:$U$2,0),0),0) -> 0 | ... U74: =-IFERROR(VLOOKUP($I74,$I$47:$U$67,MATCH(U$68,$I$47:$U$47,0),0),0)+IFERROR(VLOOKUP($I74,$I$2:$U$23,MATCH(U$68,$I$2:$U$2,0),0),0) -> 0 | V74: =SUM(J74:U74) -> -88422565
I75: DHC | J75: =-IFERROR(VLOOKUP($I75,$I$47:$U$67,MATCH(J$68,$I$47:$U$47,0),0),0)+IFERROR(VLOOKUP($I75,$I$2:$U$23,MATCH(J$68,$I$2:$U$2,0),0),0) -> 170878209 | K75: =-IFERROR(VLOOKUP($I75,$I$47:$U$67,MATCH(K$68,$I$47:$U$47,0),0),0)+IFERROR(VLOOKUP($I75,$I$2:$U$23,MATCH(K$68,$I$2:$U$2,0),0),0) -> 181528912 | L75: =-IFERROR(VLOOKUP($I75,$I$47:$U$67,MATCH(L$68,$I$47:$U$47,0),0),0)+IFERROR(VLOOKUP($I75,$I$2:$U$23,MATCH(L$68,$I$2:$U$2,0),0),0) -> 189811248 | M75: =-IFERROR(VLOOKUP($I75,$I$47:$U$67,MATCH(M$68,$I$47:$U$47,0),0),0)+IFERROR(VLOOKUP($I75,$I$2:$U$23,MATCH(M$68,$I$2:$U$2,0),0),0) -> 192350165 | N75: =-IFERROR(VLOOKUP($I75,$I$47:$U$67,MATCH(N$68,$I$47:$U$47,0),0),0)+IFERROR(VLOOKUP($I75,$I$2:$U$23,MATCH(N$68,$I$2:$U$2,0),0),0) -> 176263972 | O75: =-IFERROR(VLOOKUP($I75,$I$47:$U$67,MATCH(O$68,$I$47:$U$47,0),0),0)+IFERROR(VLOOKUP($I75,$I$2:$U$23,MATCH(O$68,$I$2:$U$2,0),0),0) -> 193562509 | P75: =-IFERROR(VLOOKUP($I75,$I$47:$U$67,MATCH(P$68,$I$47:$U$47,0),0),0)+IFERROR(VLOOKUP($I75,$I$2:$U$23,MATCH(P$68,$I$2:$U$2,0),0),0) -> 0 | Q75: =-IFERROR(VLOOKUP($I75,$I$47:$U$67,MATCH(Q$68,$I$47:$U$47,0),0),0)+IFERROR(VLOOKUP($I75,$I$2:$U$23,MATCH(Q$68,$I$2:$U$2,0),0),0) -> 0 | ... U75: =-IFERROR(VLOOKUP($I75,$I$47:$U$67,MATCH(U$68,$I$47:$U$47,0),0),0)+IFERROR(VLOOKUP($I75,$I$2:$U$23,MATCH(U$68,$I$2:$U$2,0),0),0) -> 0 | V75: =SUM(J75:U75) -> 1104395015
I76: DHI | J76: =-IFERROR(VLOOKUP($I76,$I$47:$U$67,MATCH(J$68,$I$47:$U$47,0),0),0)+IFERROR(VLOOKUP($I76,$I$2:$U$23,MATCH(J$68,$I$2:$U$2,0),0),0) -> 28319082 | K76: =-IFERROR(VLOOKUP($I76,$I$47:$U$67,MATCH(K$68,$I$47:$U$47,0),0),0)+IFERROR(VLOOKUP($I76,$I$2:$U$23,MATCH(K$68,$I$2:$U$2,0),0),0) -> 60551930 | L76: =-IFERROR(VLOOKUP($I76,$I$47:$U$67,MATCH(L$68,$I$47:$U$47,0),0),0)+IFERROR(VLOOKUP($I76,$I$2:$U$23,MATCH(L$68,$I$2:$U$2,0),0),0) -> 105205862 | M76: =-IFERROR(VLOOKUP($I76,$I$47:$U$67,MATCH(M$68,$I$47:$U$47,0),0),0)+IFERROR(VLOOKUP($I76,$I$2:$U$23,MATCH(M$68,$I$2:$U$2,0),0),0) -> 60733070 | N76: =-IFERROR(VLOOKUP($I76,$I$47:$U$67,MATCH(N$68,$I$47:$U$47,0),0),0)+IFERROR(VLOOKUP($I76,$I$2:$U$23,MATCH(N$68,$I$2:$U$2,0),0),0) -> 17267087 | O76: =-IFERROR(VLOOKUP($I76,$I$47:$U$67,MATCH(O$68,$I$47:$U$47,0),0),0)+IFERROR(VLOOKUP($I76,$I$2:$U$23,MATCH(O$68,$I$2:$U$2,0),0),0) -> 118268261 | P76: =-IFERROR(VLOOKUP($I76,$I$47:$U$67,MATCH(P$68,$I$47:$U$47,0),0),0)+IFERROR(VLOOKUP($I76,$I$2:$U$23,MATCH(P$68,$I$2:$U$2,0),0),0) -> 0 | Q76: =-IFERROR(VLOOKUP($I76,$I$47:$U$67,MATCH(Q$68,$I$47:$U$47,0),0),0)+IFERROR(VLOOKUP($I76,$I$2:$U$23,MATCH(Q$68,$I$2:$U$2,0),0),0) -> 0 | ... U76: =-IFERROR(VLOOKUP($I76,$I$47:$U$67,MATCH(U$68,$I$47:$U$47,0),0),0)+IFERROR(VLOOKUP($I76,$I$2:$U$23,MATCH(U$68,$I$2:$U$2,0),0),0) -> 0 | V76: =SUM(J76:U76) -> 390345292
I77: DIC | J77: =-IFERROR(VLOOKUP($I77,$I$47:$U$67,MATCH(J$68,$I$47:$U$47,0),0),0)+IFERROR(VLOOKUP($I77,$I$2:$U$23,MATCH(J$68,$I$2:$U$2,0),0),0) -> 0 | K77: =-IFERROR(VLOOKUP($I77,$I$47:$U$67,MATCH(K$68,$I$47:$U$47,0),0),0)+IFERROR(VLOOKUP($I77,$I$2:$U$23,MATCH(K$68,$I$2:$U$2,0),0),0) -> 0 | L77: =-IFERROR(VLOOKUP($I77,$I$47:$U$67,MATCH(L$68,$I$47:$U$47,0),0),0)+IFERROR(VLOOKUP($I77,$I$2:$U$23,MATCH(L$68,$I$2:$U$2,0),0),0) -> 0 | M77: =-IFERROR(VLOOKUP($I77,$I$47:$U$67,MATCH(M$68,$I$47:$U$47,0),0),0)+IFERROR(VLOOKUP($I77,$I$2:$U$23,MATCH(M$68,$I$2:$U$2,0),0),0) -> 0 | N77: =-IFERROR(VLOOKUP($I77,$I$47:$U$67,MATCH(N$68,$I$47:$U$47,0),0),0)+IFERROR(VLOOKUP($I77,$I$2:$U$23,MATCH(N$68,$I$2:$U$2,0),0),0) -> 0 | O77: =-IFERROR(VLOOKUP($I77,$I$47:$U$67,MATCH(O$68,$I$47:$U$47,0),0),0)+IFERROR(VLOOKUP($I77,$I$2:$U$23,MATCH(O$68,$I$2:$U$2,0),0),0) -> 0 | P77: =-IFERROR(VLOOKUP($I77,$I$47:$U$67,MATCH(P$68,$I$47:$U$47,0),0),0)+IFERROR(VLOOKUP($I77,$I$2:$U$23,MATCH(P$68,$I$2:$U$2,0),0),0) -> 0 | Q77: =-IFERROR(VLOOKUP($I77,$I$47:$U$67,MATCH(Q$68,$I$47:$U$47,0),0),0)+IFERROR(VLOOKUP($I77,$I$2:$U$23,MATCH(Q$68,$I$2:$U$2,0),0),0) -> 0 | ... U77: =-IFERROR(VLOOKUP($I77,$I$47:$U$67,MATCH(U$68,$I$47:$U$47,0),0),0)+IFERROR(VLOOKUP($I77,$I$2:$U$23,MATCH(U$68,$I$2:$U$2,0),0),0) -> 0 | V77: =SUM(J77:U77) -> 0
I78: DIO | J78: =-IFERROR(VLOOKUP($I78,$I$47:$U$67,MATCH(J$68,$I$47:$U$47,0),0),0)+IFERROR(VLOOKUP($I78,$I$2:$U$23,MATCH(J$68,$I$2:$U$2,0),0),0) -> 4764728 | K78: =-IFERROR(VLOOKUP($I78,$I$47:$U$67,MATCH(K$68,$I$47:$U$47,0),0),0)+IFERROR(VLOOKUP($I78,$I$2:$U$23,MATCH(K$68,$I$2:$U$2,0),0),0) -> 984059 | L78: =-IFERROR(VLOOKUP($I78,$I$47:$U$67,MATCH(L$68,$I$47:$U$47,0),0),0)+IFERROR(VLOOKUP($I78,$I$2:$U$23,MATCH(L$68,$I$2:$U$2,0),0),0) -> 13161022 | M78: =-IFERROR(VLOOKUP($I78,$I$47:$U$67,MATCH(M$68,$I$47:$U$47,0),0),0)+IFERROR(VLOOKUP($I78,$I$2:$U$23,MATCH(M$68,$I$2:$U$2,0),0),0) -> -32667106 | N78: =-IFERROR(VLOOKUP($I78,$I$47:$U$67,MATCH(N$68,$I$47:$U$47,0),0),0)+IFERROR(VLOOKUP($I78,$I$2:$U$23,MATCH(N$68,$I$2:$U$2,0),0),0) -> -96323928 | O78: =-IFERROR(VLOOKUP($I78,$I$47:$U$67,MATCH(O$68,$I$47:$U$47,0),0),0)+IFERROR(VLOOKUP($I78,$I$2:$U$23,MATCH(O$68,$I$2:$U$2,0),0),0) -> -2792657 | P78: =-IFERROR(VLOOKUP($I78,$I$47:$U$67,MATCH(P$68,$I$47:$U$47,0),0),0)+IFERROR(VLOOKUP($I78,$I$2:$U$23,MATCH(P$68,$I$2:$U$2,0),0),0) -> 0 | Q78: =-IFERROR(VLOOKUP($I78,$I$47:$U$67,MATCH(Q$68,$I$47:$U$47,0),0),0)+IFERROR(VLOOKUP($I78,$I$2:$U$23,MATCH(Q$68,$I$2:$U$2,0),0),0) -> 0 | ... U78: =-IFERROR(VLOOKUP($I78,$I$47:$U$67,MATCH(U$68,$I$47:$U$47,0),0),0)+IFERROR(VLOOKUP($I78,$I$2:$U$23,MATCH(U$68,$I$2:$U$2,0),0),0) -> 0 | V78: =SUM(J78:U78) -> -112873882
G79: Suma DOH | I79: DDA | J79: =-IFERROR(VLOOKUP($I79,$I$47:$U$67,MATCH(J$68,$I$47:$U$47,0),0),0)+IFERROR(VLOOKUP($I79,$I$2:$U$23,MATCH(J$68,$I$2:$U$2,0),0),0)+IFERROR(VLOOKUP("DOH",$I$2:$U$23,MATCH(J$68,$I$2:$U$2,0),0),0) -> 72276858 | K79: =-IFERROR(VLOOKUP($I79,$I$47:$U$67,MATCH(K$68,$I$47:$U$47,0),0),0)+IFERROR(VLOOKUP($I79,$I$2:$U$23,MATCH(K$68,$I$2:$U$2,0),0),0)+IFERROR(VLOOKUP("DOH",$I$2:$U$23,MATCH(K$68,$I$2:$U$2,0),0),0) -> 130992419 | L79: =-IFERROR(VLOOKUP($I79,$I$47:$U$67,MATCH(L$68,$I$47:$U$47,0),0),0)+IFERROR(VLOOKUP($I79,$I$2:$U$23,MATCH(L$68,$I$2:$U$2,0),0),0)+IFERROR(VLOOKUP("DOH",$I$2:$U$23,MATCH(L$68,$I$2:$U$2,0),0),0) -> 109478762 | M79: =-IFERROR(VLOOKUP($I79,$I$47:$U$67,MATCH(M$68,$I$47:$U$47,0),0),0)+IFERROR(VLOOKUP($I79,$I$2:$U$23,MATCH(M$68,$I$2:$U$2,0),0),0)+IFERROR(VLOOKUP("DOH",$I$2:$U$23,MATCH(M$68,$I$2:$U$2,0),0),0) -> 160464177 | N79: =-IFERROR(VLOOKUP($I79,$I$47:$U$67,MATCH(N$68,$I$47:$U$47,0),0),0)+IFERROR(VLOOKUP($I79,$I$2:$U$23,MATCH(N$68,$I$2:$U$2,0),0),0)+IFERROR(VLOOKUP("DOH",$I$2:$U$23,MATCH(N$68,$I$2:$U$2,0),0),0) -> 226861512 | O79: =-IFERROR(VLOOKUP($I79,$I$47:$U$67,MATCH(O$68,$I$47:$U$47,0),0),0)+IFERROR(VLOOKUP($I79,$I$2:$U$23,MATCH(O$68,$I$2:$U$2,0),0),0)+IFERROR(VLOOKUP("DOH",$I$2:$U$23,MATCH(O$68,$I$2:$U$2,0),0),0) -> 138491481 | P79: =-IFERROR(VLOOKUP($I79,$I$47:$U$67,MATCH(P$68,$I$47:$U$47,0),0),0)+IFERROR(VLOOKUP($I79,$I$2:$U$23,MATCH(P$68,$I$2:$U$2,0),0),0)+IFERROR(VLOOKUP("DOH",$I$2:$U$23,MATCH(P$68,$I$2:$U$2,0),0),0) -> 0 | Q79: =-IFERROR(VLOOKUP($I79,$I$47:$U$67,MATCH(Q$68,$I$47:$U$47,0),0),0)+IFERROR(VLOOKUP($I79,$I$2:$U$23,MATCH(Q$68,$I$2:$U$2,0),0),0)+IFERROR(VLOOKUP("DOH",$I$2:$U$23,MATCH(Q$68,$I$2:$U$2,0),0),0) -> 0 | ... U79: =-IFERROR(VLOOKUP($I79,$I$47:$U$67,MATCH(U$68,$I$47:$U$47,0),0),0)+IFERROR(VLOOKUP($I79,$I$2:$U$23,MATCH(U$68,$I$2:$U$2,0),0),0)+IFERROR(VLOOKUP("DOH",$I$2:$U$23,MATCH(U$68,$I$2:$U$2,0),0),0) -> 0 | V79: =SUM(J79:U79) -> 838565209
I80: DPR | J80: =-IFERROR(VLOOKUP($I80,$I$47:$U$67,MATCH(J$68,$I$47:$U$47,0),0),0)+IFERROR(VLOOKUP($I80,$I$2:$U$23,MATCH(J$68,$I$2:$U$2,0),0),0) -> -600778533 | K80: =-IFERROR(VLOOKUP($I80,$I$47:$U$67,MATCH(K$68,$I$47:$U$47,0),0),0)+IFERROR(VLOOKUP($I80,$I$2:$U$23,MATCH(K$68,$I$2:$U$2,0),0),0) -> -134207520 | L80: =-IFERROR(VLOOKUP($I80,$I$47:$U$67,MATCH(L$68,$I$47:$U$47,0),0),0)+IFERROR(VLOOKUP($I80,$I$2:$U$23,MATCH(L$68,$I$2:$U$2,0),0),0) -> -49467030 | M80: =-IFERROR(VLOOKUP($I80,$I$47:$U$67,MATCH(M$68,$I$47:$U$47,0),0),0)+IFERROR(VLOOKUP($I80,$I$2:$U$23,MATCH(M$68,$I$2:$U$2,0),0),0) -> -3.6092884e+08 | N80: =-IFERROR(VLOOKUP($I80,$I$47:$U$67,MATCH(N$68,$I$47:$U$47,0),0),0)+IFERROR(VLOOKUP($I80,$I$2:$U$23,MATCH(N$68,$I$2:$U$2,0),0),0) -> -170016262 | O80: =-IFERROR(VLOOKUP($I80,$I$47:$U$67,MATCH(O$68,$I$47:$U$47,0),0),0)+IFERROR(VLOOKUP($I80,$I$2:$U$23,MATCH(O$68,$I$2:$U$2,0),0),0) -> -50441715 | P80: =-IFERROR(VLOOKUP($I80,$I$47:$U$67,MATCH(P$68,$I$47:$U$47,0),0),0)+IFERROR(VLOOKUP($I80,$I$2:$U$23,MATCH(P$68,$I$2:$U$2,0),0),0) -> 0 | Q80: =-IFERROR(VLOOKUP($I80,$I$47:$U$67,MATCH(Q$68,$I$47:$U$47,0),0),0)+IFERROR(VLOOKUP($I80,$I$2:$U$23,MATCH(Q$68,$I$2:$U$2,0),0),0) -> 0 | ... U80: =-IFERROR(VLOOKUP($I80,$I$47:$U$67,MATCH(U$68,$I$47:$U$47,0),0),0)+IFERROR(VLOOKUP($I80,$I$2:$U$23,MATCH(U$68,$I$2:$U$2,0),0),0) -> 0 | V80: =SUM(J80:U80) -> -1365839905
I81: DTC | J81: =-IFERROR(VLOOKUP($I81,$I$47:$U$67,MATCH(J$68,$I$47:$U$47,0),0),0)+IFERROR(VLOOKUP($I81,$I$2:$U$23,MATCH(J$68,$I$2:$U$2,0),0),0) -> -9153737.2 | K81: =-IFERROR(VLOOKUP($I81,$I$47:$U$67,MATCH(K$68,$I$47:$U$47,0),0),0)+IFERROR(VLOOKUP($I81,$I$2:$U$23,MATCH(K$68,$I$2:$U$2,0),0),0) -> 23426529 | L81: =-IFERROR(VLOOKUP($I81,$I$47:$U$67,MATCH(L$68,$I$47:$U$47,0),0),0)+IFERROR(VLOOKUP($I81,$I$2:$U$23,MATCH(L$68,$I$2:$U$2,0),0),0) -> -30591644 | M81: =-IFERROR(VLOOKUP($I81,$I$47:$U$67,MATCH(M$68,$I$47:$U$47,0),0),0)+IFERROR(VLOOKUP($I81,$I$2:$U$23,MATCH(M$68,$I$2:$U$2,0),0),0) -> 39984785 | N81: =-IFERROR(VLOOKUP($I81,$I$47:$U$67,MATCH(N$68,$I$47:$U$47,0),0),0)+IFERROR(VLOOKUP($I81,$I$2:$U$23,MATCH(N$68,$I$2:$U$2,0),0),0) -> -74711872 | O81: =-IFERROR(VLOOKUP($I81,$I$47:$U$67,MATCH(O$68,$I$47:$U$47,0),0),0)+IFERROR(VLOOKUP($I81,$I$2:$U$23,MATCH(O$68,$I$2:$U$2,0),0),0) -> -52997647 | P81: =-IFERROR(VLOOKUP($I81,$I$47:$U$67,MATCH(P$68,$I$47:$U$47,0),0),0)+IFERROR(VLOOKUP($I81,$I$2:$U$23,MATCH(P$68,$I$2:$U$2,0),0),0) -> 0 | Q81: =-IFERROR(VLOOKUP($I81,$I$47:$U$67,MATCH(Q$68,$I$47:$U$47,0),0),0)+IFERROR(VLOOKUP($I81,$I$2:$U$23,MATCH(Q$68,$I$2:$U$2,0),0),0) -> 0 | ... U81: =-IFERROR(VLOOKUP($I81,$I$47:$U$67,MATCH(U$68,$I$47:$U$47,0),0),0)+IFERROR(VLOOKUP($I81,$I$2:$U$23,MATCH(U$68,$I$2:$U$2,0),0),0) -> 0 | V81: =SUM(J81:U81) -> -1.0404359e+08
I82: EQM | J82: =-IFERROR(VLOOKUP($I82,$I$47:$U$67,MATCH(J$68,$I$47:$U$47,0),0),0)+IFERROR(VLOOKUP($I82,$I$2:$U$23,MATCH(J$68,$I$2:$U$2,0),0),0) -> -288986146 | K82: =-IFERROR(VLOOKUP($I82,$I$47:$U$67,MATCH(K$68,$I$47:$U$47,0),0),0)+IFERROR(VLOOKUP($I82,$I$2:$U$23,MATCH(K$68,$I$2:$U$2,0),0),0) -> 288986146 | L82: =-IFERROR(VLOOKUP($I82,$I$47:$U$67,MATCH(L$68,$I$47:$U$47,0),0),0)+IFERROR(VLOOKUP($I82,$I$2:$U$23,MATCH(L$68,$I$2:$U$2,0),0),0) -> 0 | M82: =-IFERROR(VLOOKUP($I82,$I$47:$U$67,MATCH(M$68,$I$47:$U$47,0),0),0)+IFERROR(VLOOKUP($I82,$I$2:$U$23,MATCH(M$68,$I$2:$U$2,0),0),0) -> 0 | N82: =-IFERROR(VLOOKUP($I82,$I$47:$U$67,MATCH(N$68,$I$47:$U$47,0),0),0)+IFERROR(VLOOKUP($I82,$I$2:$U$23,MATCH(N$68,$I$2:$U$2,0),0),0) -> -82829710 | O82: =-IFERROR(VLOOKUP($I82,$I$47:$U$67,MATCH(O$68,$I$47:$U$47,0),0),0)+IFERROR(VLOOKUP($I82,$I$2:$U$23,MATCH(O$68,$I$2:$U$2,0),0),0) -> -206156436 | P82: =-IFERROR(VLOOKUP($I82,$I$47:$U$67,MATCH(P$68,$I$47:$U$47,0),0),0)+IFERROR(VLOOKUP($I82,$I$2:$U$23,MATCH(P$68,$I$2:$U$2,0),0),0) -> 0 | Q82: =-IFERROR(VLOOKUP($I82,$I$47:$U$67,MATCH(Q$68,$I$47:$U$47,0),0),0)+IFERROR(VLOOKUP($I82,$I$2:$U$23,MATCH(Q$68,$I$2:$U$2,0),0),0) -> 0 | ... U82: =-IFERROR(VLOOKUP($I82,$I$47:$U$67,MATCH(U$68,$I$47:$U$47,0),0),0)+IFERROR(VLOOKUP($I82,$I$2:$U$23,MATCH(U$68,$I$2:$U$2,0),0),0) -> 0 | V82: =SUM(J82:U82) -> -288986146
I83: MDQ | J83: =-IFERROR(VLOOKUP($I83,$I$47:$U$67,MATCH(J$68,$I$47:$U$47,0),0),0)+IFERROR(VLOOKUP($I83,$I$2:$U$23,MATCH(J$68,$I$2:$U$2,0),0),0) -> 45730726 | K83: =-IFERROR(VLOOKUP($I83,$I$47:$U$67,MATCH(K$68,$I$47:$U$47,0),0),0)+IFERROR(VLOOKUP($I83,$I$2:$U$23,MATCH(K$68,$I$2:$U$2,0),0),0) -> 0 | L83: =-IFERROR(VLOOKUP($I83,$I$47:$U$67,MATCH(L$68,$I$47:$U$47,0),0),0)+IFERROR(VLOOKUP($I83,$I$2:$U$23,MATCH(L$68,$I$2:$U$2,0),0),0) -> 0 | M83: =-IFERROR(VLOOKUP($I83,$I$47:$U$67,MATCH(M$68,$I$47:$U$47,0),0),0)+IFERROR(VLOOKUP($I83,$I$2:$U$23,MATCH(M$68,$I$2:$U$2,0),0),0) -> 0 | N83: =-IFERROR(VLOOKUP($I83,$I$47:$U$67,MATCH(N$68,$I$47:$U$47,0),0),0)+IFERROR(VLOOKUP($I83,$I$2:$U$23,MATCH(N$68,$I$2:$U$2,0),0),0) -> -45730726 | O83: =-IFERROR(VLOOKUP($I83,$I$47:$U$67,MATCH(O$68,$I$47:$U$47,0),0),0)+IFERROR(VLOOKUP($I83,$I$2:$U$23,MATCH(O$68,$I$2:$U$2,0),0),0) -> 0 | P83: =-IFERROR(VLOOKUP($I83,$I$47:$U$67,MATCH(P$68,$I$47:$U$47,0),0),0)+IFERROR(VLOOKUP($I83,$I$2:$U$23,MATCH(P$68,$I$2:$U$2,0),0),0) -> 0 | Q83: =-IFERROR(VLOOKUP($I83,$I$47:$U$67,MATCH(Q$68,$I$47:$U$47,0),0),0)+IFERROR(VLOOKUP($I83,$I$2:$U$23,MATCH(Q$68,$I$2:$U$2,0),0),0) -> 0 | ... U83: =-IFERROR(VLOOKUP($I83,$I$47:$U$67,MATCH(U$68,$I$47:$U$47,0),0),0)+IFERROR(VLOOKUP($I83,$I$2:$U$23,MATCH(U$68,$I$2:$U$2,0),0),0) -> 0 | V83: =SUM(J83:U83) -> 0
I84: SDO | J84: =-IFERROR(VLOOKUP($I84,$I$47:$U$67,MATCH(J$68,$I$47:$U$47,0),0),0)+IFERROR(VLOOKUP($I84,$I$2:$U$23,MATCH(J$68,$I$2:$U$2,0),0),0) -> 555957 | K84: =-IFERROR(VLOOKUP($I84,$I$47:$U$67,MATCH(K$68,$I$47:$U$47,0),0),0)+IFERROR(VLOOKUP($I84,$I$2:$U$23,MATCH(K$68,$I$2:$U$2,0),0),0) -> 2772170 | L84: =-IFERROR(VLOOKUP($I84,$I$47:$U$67,MATCH(L$68,$I$47:$U$47,0),0),0)+IFERROR(VLOOKUP($I84,$I$2:$U$23,MATCH(L$68,$I$2:$U$2,0),0),0) -> 4725808 | M84: =-IFERROR(VLOOKUP($I84,$I$47:$U$67,MATCH(M$68,$I$47:$U$47,0),0),0)+IFERROR(VLOOKUP($I84,$I$2:$U$23,MATCH(M$68,$I$2:$U$2,0),0),0) -> 3385902 | N84: =-IFERROR(VLOOKUP($I84,$I$47:$U$67,MATCH(N$68,$I$47:$U$47,0),0),0)+IFERROR(VLOOKUP($I84,$I$2:$U$23,MATCH(N$68,$I$2:$U$2,0),0),0) -> 2865900 | O84: =-IFERROR(VLOOKUP($I84,$I$47:$U$67,MATCH(O$68,$I$47:$U$47,0),0),0)+IFERROR(VLOOKUP($I84,$I$2:$U$23,MATCH(O$68,$I$2:$U$2,0),0),0) -> 2541355 | P84: =-IFERROR(VLOOKUP($I84,$I$47:$U$67,MATCH(P$68,$I$47:$U$47,0),0),0)+IFERROR(VLOOKUP($I84,$I$2:$U$23,MATCH(P$68,$I$2:$U$2,0),0),0) -> 0 | Q84: =-IFERROR(VLOOKUP($I84,$I$47:$U$67,MATCH(Q$68,$I$47:$U$47,0),0),0)+IFERROR(VLOOKUP($I84,$I$2:$U$23,MATCH(Q$68,$I$2:$U$2,0),0),0) -> 0 | ... U84: =-IFERROR(VLOOKUP($I84,$I$47:$U$67,MATCH(U$68,$I$47:$U$47,0),0),0)+IFERROR(VLOOKUP($I84,$I$2:$U$23,MATCH(U$68,$I$2:$U$2,0),0),0) -> 0 | V84: =SUM(J84:U84) -> 16847092
I85: Total | J85: =SUM(J69:J84) -> -1.1416114e+09 | K85: =SUM(K69:K84) -> 4.0770858e+08 | L85: =SUM(L69:L84) -> 5.0451611e+08 | M85: =SUM(M69:M84) -> 47948286 | N85: =SUM(N69:N84) -> -2.0840732e+09 | O85: =SUM(O69:O84) -> 3.1380391e+08 | P85: =SUM(P69:P84) -> 0 | Q85: =SUM(Q69:Q84) -> 0 | ... U85: =SUM(U69:U84) -> 0 | V85: =SUM(J85:U85) -> -1.9517077e+09

Sheet DAC
I1: EERR s/TI Fact | J1: Etiquetas de columna
I2: Etiquetas de fila | J2: ene | K2: feb | L2: mar | M2: abr | N2: may | O2: jun | P2: jul | Q2: ago | R2: sep | S2: oct | T2: nov | U2: dic | V2: Total general
I3: DAC | J3: -171901206 | K3: 229661282 | L3: 169799213 | M3: 202455970 | N3: -76674690 | O3: 501144778 | V3: 854485347
I4: Total general | J4: -171901206 | K4: 229661282 | L4: 169799213 | M4: 202455970 | N4: -76674690 | O4: 501144778 | V4: 854485347
I25: Ingreso_Salesforce | J25: Etiquetas de columna
I26: Etiquetas de fila | J26: ene | K26: feb | L26: mar | M26: abr | N26: may | O26: jun | P26: Total general
I27: DAC | J27: -169531556 | K27: 229661282 | L27: 132474079 | M27: 254268998 | N27: 4.6957042e+08 | O27: 3.6332564e+08 | P27: 1.2797689e+09
I28: DCO | J28: 842635563 | K28: 592333115 | L28: 354793861 | M28: 4.2707473e+08 | N28: 892309408 | O28: 486320169 | P28: 3.5954668e+09
I29: DDA | J29: 181228409 | K29: 129936364 | L29: 134027273 | M29: 157001893 | N29: 40429545 | O29: 130045454 | P29: 772668938
I30: DEP | J30: 27617921 | K30: 1.7119322e+08 | L30: 2.5230381e+08 | M30: 1.2067604e+08 | N30: 62156575 | O30: 79488858 | P30: 7.1343642e+08
I31: DES | J31: 289140060 | K31: 2.5750274e+08 | L31: 270815880 | M31: 267801174 | N31: 1.3945091e+08 | O31: 3.2742769e+08 | P31: 1.5521385e+09
I32: DGI | J32: 1271029488 | K32: 1406463891 | L32: 1321970041 | M32: -137844577 | N32: 3434507158 | O32: 1229933471 | P32: 8526059472
I33: DGL | J33: 286168992 | K33: 338984671 | L33: 230154271 | M33: 451087812 | N33: 341520986 | O33: 436919745 | P33: 2084836477
I34: DHC | J34: 73086361 | K34: 73231017 | L34: 80734296 | M34: 85650722 | N34: 83985839 | O34: 146170041 | P34: 542858276
I35: DHI | J35: 218731800 | K35: 172601844 | L35: 161539048 | M35: 196879192 | N35: 201803161 | O35: 125279423 | P35: 1076834468
I36: DIC | J36: 16026670 | K36: 57914174 | L36: 25901536 | M36: 90119211 | N36: 81835932 | O36: 41091978 | P36: 312889501
I37: DIO | J37: 50982594 | K37: 54985753 | L37: 42216285 | M37: 80987512 | N37: 47400975 | O37: 47567549 | P37: 324140668
I38: DPR | J38: 522514884 | K38: 478946114 | L38: 4.0956632e+08 | M38: 5.4676366e+08 | N38: 530145136 | O38: 492863760 | P38: 2980799873
I39: DTC | J39: 1.0186675e+08 | K39: 1.5340891e+08 | L39: 2.1757082e+08 | M39: 1.6916078e+08 | N39: 2.5458868e+08 | O39: 2.1220769e+08 | P39: 1.1088036e+09
I40: SDG | O40: 444000 | P40: 444000
I41: SDO | J41: 3594914 | K41: 198466 | L41: 5612144 | M41: 3876374 | N41: 3868251 | O41: 4465971 | P41: 21616120
I42: Total general | J42: 3.7150929e+09 | K42: 4.1173616e+09 | L42: 3.6396797e+09 | M42: 2.7135035e+09 | N42: 6.583573e+09 | O42: 4.1235514e+09 | P42: 2.4892762e+10
I62: Salesforce | J62: Ene | K62: Feb | L62: Mar | M62: Abr | N62: May | O62: Jun | P62: Jul | Q62: Ago | R62: Sep | S62: Oct | T62: Nov | U62: Dic | V62: Total
I63: DAC | J63: =IFERROR(VLOOKUP($I63,$I$26:$V$42,MATCH(J$62,$I$26:$V$26,0),0),0) -> -169531556 | K63: =IFERROR(VLOOKUP($I63,$I$26:$V$42,MATCH(K$62,$I$26:$V$26,0),0),0) -> 229661282 | L63: =IFERROR(VLOOKUP($I63,$I$26:$V$42,MATCH(L$62,$I$26:$V$26,0),0),0) -> 132474079 | M63: =IFERROR(VLOOKUP($I63,$I$26:$V$42,MATCH(M$62,$I$26:$V$26,0),0),0) -> 254268998 | N63: =IFERROR(VLOOKUP($I63,$I$26:$V$42,MATCH(N$62,$I$26:$V$26,0),0),0) -> 4.6957042e+08 | O63: =IFERROR(VLOOKUP($I63,$I$26:$V$42,MATCH(O$62,$I$26:$V$26,0),0),0) -> 3.6332564e+08 | P63: =IFERROR(VLOOKUP($I63,$I$26:$V$42,MATCH(P$62,$I$26:$V$26,0),0),0) -> 0 | Q63: =IFERROR(VLOOKUP($I63,$I$26:$V$42,MATCH(Q$62,$I$26:$V$26,0),0),0) -> 0 | ... U63: =IFERROR(VLOOKUP($I63,$I$26:$V$42,MATCH(U$62,$I$26:$V$26,0),0),0) -> 0 | V63: =SUM(J63:U63) -> 1.2797689e+09
I83: Diferencia | J83: Ene | K83: Feb | L83: Mar | M83: Abr | N83: May | O83: Jun | P83: Jul | Q83: Ago | R83: Sep | S83: Oct | T83: Nov | U83: Dic | V83: Total
I84: DAC | J84: =-IFERROR(VLOOKUP($I84,$I$62:$U$80,MATCH(J$83,$I$62:$U$62,0),0),0)+IFERROR(VLOOKUP($I84,$I$2:$U$23,MATCH(J$83,$I$2:$U$2,0),0),0) -> -2369650 | K84: =-IFERROR(VLOOKUP($I84,$I$62:$U$80,MATCH(K$83,$I$62:$U$62,0),0),0)+IFERROR(VLOOKUP($I84,$I$2:$U$23,MATCH(K$83,$I$2:$U$2,0),0),0) -> 0 | L84: =-IFERROR(VLOOKUP($I84,$I$62:$U$80,MATCH(L$83,$I$62:$U$62,0),0),0)+IFERROR(VLOOKUP($I84,$I$2:$U$23,MATCH(L$83,$I$2:$U$2,0),0),0) -> 37325134 | M84: =-IFERROR(VLOOKUP($I84,$I$62:$U$80,MATCH(M$83,$I$62:$U$62,0),0),0)+IFERROR(VLOOKUP($I84,$I$2:$U$23,MATCH(M$83,$I$2:$U$2,0),0),0) -> -51813028 | N84: =-IFERROR(VLOOKUP($I84,$I$62:$U$80,MATCH(N$83,$I$62:$U$62,0),0),0)+IFERROR(VLOOKUP($I84,$I$2:$U$23,MATCH(N$83,$I$2:$U$2,0),0),0) -> -5.4624511e+08 | O84: =-IFERROR(VLOOKUP($I84,$I$62:$U$80,MATCH(O$83,$I$62:$U$62,0),0),0)+IFERROR(VLOOKUP($I84,$I$2:$U$23,MATCH(O$83,$I$2:$U$2,0),0),0) -> 1.3781914e+08 | P84: =-IFERROR(VLOOKUP($I84,$I$62:$U$80,MATCH(P$83,$I$62:$U$62,0),0),0)+IFERROR(VLOOKUP($I84,$I$2:$U$23,MATCH(P$83,$I$2:$U$2,0),0),0) -> 0 | Q84: =-IFERROR(VLOOKUP($I84,$I$62:$U$80,MATCH(Q$83,$I$62:$U$62,0),0),0)+IFERROR(VLOOKUP($I84,$I$2:$U$23,MATCH(Q$83,$I$2:$U$2,0),0),0) -> 0 | ... U84: =-IFERROR(VLOOKUP($I84,$I$62:$U$80,MATCH(U$83,$I$62:$U$62,0),0),0)+IFERROR(VLOOKUP($I84,$I$2:$U$23,MATCH(U$83,$I$2:$U$2,0),0),0) -> 0 | V84: =SUM(J84:U84) -> -4.2528352e+08
I86: siglaDivision | J86: DAC | Z86: División | AA86: DAC
I88: EERR s/TI Fact | L88: fecha (mes) | Z88: Ingreso_Salesforce | AA88: Etiquetas de columna
A89: Facturación: Incluye Facturación externa y Traspasos de Servicios Internos | I89: Clasificación | J89: cuenta_contable_full | K89: Referencia Interna | L89: ene | M89: feb | N89: mar | O89: abr | P89: may | Q89: jun | R89: Total general | Z89: Etiquetas de fila | AA89: ene | AB89: feb | AC89: mar | AD89: abr | AE89: may | AF89: jun | AG89: Total general
A90: Traspasos: Corresponde solo a Traspasos de Facturación | I90: Ingresos | J90: 61010302 Asesorías y consultorías exterior | K90: PR.DAC.2026.0055 | M90: 3550450 | R90: 3550450 | Z90: N°PR.DAC.2026.0284 | AE90: 1454693 | AG90: 1454693
A91: Valor en círculo: Representa diferncia entre Backlog y Facturación | I91: Ingresos | J91: 61010323 Análisis de materiales | L91: 4501515 | N91: 78527700 | O91: 69916467 | P91: 8785334 | Q91: 82356400 | R91: 244087416 | Z91: PR.DAC.2019.0644E | AA91: 2879620 | AB91: 0 | AC91: 8625735 | AD91: 2907750 | AE91: 2938148 | AF91: 2958094 | AG91: 20309347
I92: Ingresos | J92: 61010323 Análisis de materiales | K92: N°PR.DAC.2026.0284 | P92: 1451666 | R92: 1451666 | Z92: PR.DAC.2019.432 abril 2026 | AE92: 8024040 | AG92: 8024040
I93: Ingresos | J93: 61010323 Análisis de materiales | K93: PR.DAC.2019.0644E | L93: 5753880 | M93: 2879620 | N93: -2870293 | O93: 11496028 | P93: 54127 | Q93: 2938148 | R93: 20251510 | Z93: PR.DAC.2019.432 enero 2026 | AA93: 0 | AB93: 0 | AG93: 0
I94: Ingresos | J94: 61010323 Análisis de materiales | K94: PR.DAC.2019.432 abril 2026 | P94: 8024040 | R94: 8024040 | Z94: PR.DAC.2019.432 febrero 2026 | AB94: 7958126 | AC94: 0 | AG94: 7958126
I95: Ingresos | J95: 61010323 Análisis de materiales | K95: PR.DAC.2019.432 diciembre 2025 | L95: 7945592 | R95: 7945592 | Z95: PR.DAC.2019.432 marzo 2026 | AC95: 7968344 | AG95: 7968344
I96: Ingresos | J96: 61010323 Análisis de materiales | K96: PR.DAC.2019.432 enero 2026 | M96: 7941214 | R96: 7941214 | Z96: PR.DAC.2019.432 mayo 2026 | AF96: 8122138 | AG96: 8122138
I97: Ingresos | J97: 61010323 Análisis de materiales | K97: PR.DAC.2019.432 febrero 2026 | N97: 7958126 | R97: 7958126 | Z97: PR.DAC.2021.0237D Sept a Abr 2026 | AA97: 1351276 | AB97: 16659278 | AC97: 6898195 | AD97: 10802700 | AG97: 35711449
I98: Ingresos | J98: 61010323 Análisis de materiales | K98: PR.DAC.2019.432 marzo 2026 | O98: 7968344 | R98: 7968344 | Z98: PR.DAC.2021.0390AD | AA98: -4910984 | AG98: -4910984
I99: Ingresos | J99: 61010323 Análisis de materiales | K99: PR.DAC.2019.432 mayo 2026 | Q99: 8122138 | R99: 8122138 | Z99: PR.DAC.2021.0390AF | AA99: -2498748 | AG99: -2498748
I100: Ingresos | J100: 61010323 Análisis de materiales | K100: PR.DAC.2021.0237D Sept a Abr 2026 | M100: 20533796 | N100: 5739776 | O100: 0 | R100: 26273572 | Z100: PR.DAC.2021.0390AI | AA100: -1256714 | AG100: -1256714
I101: Ingresos | J101: 61010323 Análisis de materiales | K101: PR.DAC.2021.0390AC | O101: -1535674 | R101: -1535674 | Z101: PR.DAC.2021.0390AJ | AA101: -4391556 | AG101: -4391556
I102: Ingresos | J102: 61010323 Análisis de materiales | K102: PR.DAC.2021.0390AI | O102: -1257216 | R102: -1257216 | Z102: PR.DAC.2021.0390AK | AA102: -1267697 | AB102: 634298 | AG102: -633399
I103: Ingresos | J103: 61010323 Análisis de materiales | K103: PR.DAC.2021.0390AK | M103: 634298 | O103: -1896776 | R103: -1262478 | Z103: PR.DAC.2021.0390AL | AA103: -951998 | AB103: 634849 | AG103: -317149
I104: Ingresos | J104: 61010323 Análisis de materiales | K104: PR.DAC.2021.0390AL | L104: 635586 | M104: 634849 | R104: 1270435 | Z104: PR.DAC.2021.0390AM | AA104: 4766897 | AB104: -3813042 | AC104: 4766472 | AG104: 5720327
I105: Ingresos | J105: 61010323 Análisis de materiales | K105: PR.DAC.2021.0390AM | L105: 635954 | M105: 953855 | N105: 4766472 | R105: 6356281 | Z105: PR.DAC.2021.0390AM Muestreo | AA105: 953444 | AB105: -953444 | AG105: 0
I106: Ingresos | J106: 61010323 Análisis de materiales | K106: PR.DAC.2021.0390AN | N106: 636196 | O106: 2868605 | P106: 2548416 | Q106: 3055755 | R106: 9108972 | Z106: PR.DAC.2021.0390AN | AC106: 7742625 | AG106: 7742625
I107: Ingresos | J107: 61010323 Análisis de materiales | K107: PR.DAC.2021.0390AO | O107: 3510733 | P107: 1921303 | R107: 5432036 | Z107: PR.DAC.2021.0390AN Muestreo | AC107: 1366346 | AG107: 1366346
I108: Ingresos | J108: 61010323 Análisis de materiales | K108: PR.DAC.2021.0390AP | Q108: 3423997 | R108: 3423997 | Z108: PR.DAC.2021.0390AO | AD108: 4617229 | AG108: 4617229
I109: Ingresos | J109: 61010323 Análisis de materiales | K109: PR.DAC.2021.0390U | L109: 881301 | R109: 881301 | Z109: PR.DAC.2021.0390AP | AE109: 2938897 | AG109: 2938897
I110: Ingresos | J110: 61010323 Análisis de materiales | K110: PR.DAC.2021.0390V | L110: 2089221 | R110: 2089221 | Z110: PR.DAC.2021.0390AP Muestreo | AE110: 485100 | AG110: 485100
I111: Ingresos | J111: 61010323 Análisis de materiales | K111: PR.DAC.2021.0444 3816 Abril | P111: 3548997 | R111: 3548997 | Z111: PR.DAC.2021.0390AQ | AF111: 1941181 | AG111: 1941181
I112: Ingresos | J112: 61010323 Análisis de materiales | K112: PR.DAC.2021.0444 3816 Febrero | N112: 15378904 | R112: 15378904 | Z112: PR.DAC.2021.0390AQ Muestreo | AF112: 342561 | AG112: 342561
I113: Ingresos | J113: 61010323 Análisis de materiales | K113: PR.DAC.2021.0481A | P113: -3445860 | R113: -3445860 | Z113: PR.DAC.2021.0390U | AA113: 0 | AG113: 0
I114: Ingresos | J114: 61010323 Análisis de materiales | K114: PR.DAC.2021.0689AH | L114: 671256 | M114: 5034766 | O114: -2013768 | R114: 3692254 | Z114: PR.DAC.2021.0390V | AA114: -3884262 | AG114: -3884262
I115: Ingresos | J115: 61010323 Análisis de materiales | K115: PR.DAC.2021.0689AI | L115: 4379276 | R115: 4379276 | Z115: PR.DAC.2021.0390W | AA115: -3275803 | AG115: -3275803
I116: Ingresos | J116: 61010323 Análisis de materiales | K116: PR.DAC.2021.0689AJ | L116: 7077553 | M116: 2696024 | R116: 9773577 | Z116: PR.DAC.2021.0390X | AA116: 2505664 | AB116: -4910984 | AG116: -2405320
I117: Ingresos | J117: 61010323 Análisis de materiales | K117: PR.DAC.2021.0689AJ Muestreo | L117: 7419638 | M117: 1349055 | N117: 2360389 | R117: 11129082 | Z117: PR.DAC.2021.0444 3816 | AA117: -10143703 | AG117: -10143703
I118: Ingresos | J118: 61010323 Análisis de materiales | K118: PR.DAC.2021.0689AK | L118: 337916 | M118: 3714937 | R118: 4052853 | Z118: PR.DAC.2021.0444 3816 Abril | AD118: 3630878 | AG118: 3630878
I119: Ingresos | J119: 61010323 Análisis de materiales | K119: PR.DAC.2021.0689AL | M119: 675056 | N119: 4726087 | R119: 5401143 | Z119: PR.DAC.2021.0444 3816 Febrero | AB119: 1670968 | AC119: 13707936 | AG119: 15378904
I120: Ingresos | J120: 61010323 Análisis de materiales | K120: PR.DAC.2021.0689AM | N120: 3046154 | O120: 3724814 | P120: 338655 | R120: 7109623 | Z120: PR.DAC.2021.0689 Especial | AA120: -52713343 | AG120: -52713343
I121: Ingresos | J121: 61010323 Análisis de materiales | K121: PR.DAC.2021.0689AN | O121: 1354618 | P121: 6449295 | R121: 7803913 | Z121: PR.DAC.2021.0689AE | AA121: -1335681 | AG121: -1335681
I122: Ingresos | J122: 61010323 Análisis de materiales | K122: PR.DAC.2021.0689AO | P122: 1707597 | Q122: 343326 | R122: 2050923 | Z122: PR.DAC.2021.0689AF | AA122: -8352285 | AG122: -8352285
I123: Ingresos | J123: 61010323 Análisis de materiales | K123: PR.DAC.2021.0689AP | Q123: 1724518 | R123: 1724518 | Z123: PR.DAC.2021.0689AG | AA123: -4697629 | AG123: -4697629
I124: Ingresos | J124: 61010323 Análisis de materiales | K124: PR.DAC.2022.0035K | L124: 0 | R124: 0 | Z124: PR.DAC.2021.0689AH | AA124: -6043207 | AB124: 5034766 | AG124: -1008441
I125: Ingresos | J125: 61010323 Análisis de materiales | K125: PR.DAC.2022.0035L | N125: 3032766 | R125: 3032766 | Z125: PR.DAC.2021.0689AI | AA125: 1 | AG125: 1
I126: Ingresos | J126: 61010323 Análisis de materiales | K126: PR.DAC.2022.0035M | L126: 675991 | R126: 675991 | Z126: PR.DAC.2021.0689AJ | AA126: -4044103 | AB126: 2696024 | AG126: -1348079
I127: Ingresos | J127: 61010323 Análisis de materiales | K127: PR.DAC.2022.0035N | P127: 1354617 | R127: 1354617 | Z127: PR.DAC.2021.0689AJ Muestreo | AA127: -1348499 | AB127: 1349055 | AC127: 2360389 | AG127: 2360945
I128: Ingresos | J128: 61010323 Análisis de materiales | K128: PR.DAC.2022.0063 AB | L128: 1954674 | R128: 1954674 | Z128: PR.DAC.2021.0689AK | AA128: 3107008 | AB128: 1 | AG128: 3107009
I129: Ingresos | J129: 61010323 Análisis de materiales | K129: PR.DAC.2022.0063 AC | N129: 1958816 | R129: 1958816 | Z129: PR.DAC.2021.0689AK Muestreo | AA129: 607928 | AB129: 0 | AG129: 607928
I130: Ingresos | J130: 61010323 Análisis de materiales | K130: PR.DAC.2022.0063 AD | O130: 1962815 | R130: 1962815 | Z130: PR.DAC.2021.0689AL | AB130: 4928614 | AC130: -337642 | AG130: 4590972
I131: Ingresos | J131: 61010323 Análisis de materiales | K131: PR.DAC.2022.0063 AE | Q131: 2005686 | R131: 2005686 | Z131: PR.DAC.2021.0689AL Muestreo | AB131: 810171 | AG131: 810171
I132: Ingresos | J132: 61010323 Análisis de materiales | K132: PR.DAC.2022.0105 | M132: 4886067 | N132: 358575 | R132: 5244642 | Z132: PR.DAC.2021.0689AM | AC132: 6043180 | AG132: 6043180
I133: Ingresos | J133: 61010323 Análisis de materiales | K133: PR.DAC.2022.0147B | L133: 1480131 | M133: 1469599 | N133: -1464839 | O133: 4410607 | P133: 2940287 | Q133: 1499469 | R133: 10335254 | Z133: PR.DAC.2021.0689AM Muestreo | AC133: 1066443 | AG133: 1066443
I134: Ingresos | J134: 61010323 Análisis de materiales | K134: PR.DAC.2022.0158N | Q134: 1342685 | R134: 1342685 | Z134: PR.DAC.2021.0689AN | AD134: 6625676 | AG134: 6625676
I135: Ingresos | J135: 61010323 Análisis de materiales | K135: PR.DAC.2022.0158O | Q135: 1015964 | R135: 1015964 | Z135: PR.DAC.2021.0689AO | AE135: 3201659 | AG135: 3201659
I136: Ingresos | J136: 61010323 Análisis de materiales | K136: PR.DAC.2023.0015C | L136: 344639 | R136: 344639 | Z136: PR.DAC.2021.0689AP | AF136: 1465840 | AG136: 1465840
I137: Ingresos | J137: 61010323 Análisis de materiales | K137: PR.DAC.2023.0015D | L137: 1741908 | R137: 1741908 | Z137: PR.DAC.2021.0689AP Muestreo | AF137: 258678 | AG137: 258678
I138: Ingresos | J138: 61010323 Análisis de materiales | K138: PR.DAC.2023.0015E | L138: 1395414 | R138: 1395414 | Z138: PR.DAC.2022.0035L | AA138: -3032735 | AC138: 3032766 | AG138: 31
I139: Ingresos | J139: 61010323 Análisis de materiales | K139: PR.DAC.2023.0015F | L139: 2108533 | R139: 2108533 | Z139: PR.DAC.2022.0035M | AA139: -2540201 | AG139: -2540201
I140: Ingresos | J140: 61010323 Análisis de materiales | K140: PR.DAC.2023.0015H | L140: 2469796 | O140: 2469796 | Q140: 352828 | R140: 5292420 | Z140: PR.DAC.2022.0035M Muestreo | AA140: 101394 | AG140: 101394
I141: Ingresos | J141: 61010323 Análisis de materiales | K141: PR.DAC.2023.0015I | Q141: 707636 | R141: 707636 | Z141: PR.DAC.2022.0035N | AC141: 1151425 | AG141: 1151425
I142: Ingresos | J142: 61010323 Análisis de materiales | K142: PR.DAC.2023.0015J | Q142: 353531 | R142: 353531 | Z142: PR.DAC.2022.0035N Muestreo | AC142: 203193 | AG142: 203193
I143: Ingresos | J143: 61010323 Análisis de materiales | K143: PR.DAC.2023.0015K | Q143: 1060289 | R143: 1060289 | Z143: PR.DAC.2022.0035O | AF143: 3536293 | AG143: 3536293
I144: Ingresos | J144: 61010323 Análisis de materiales | K144: PR.DAC.2023.0015L | Q144: 712483 | R144: 712483 | Z144: PR.DAC.2022.0035O Muestreo | AF144: 624052 | AG144: 624052
I145: Ingresos | J145: 61010323 Análisis de materiales | K145: PR.DAC.2023.0189B | O145: 6369917 | R145: 6369917 | Z145: PR.DAC.2022.0063 AB | AA145: 1954674 | AG145: 1954674
I146: Ingresos | J146: 61010323 Análisis de materiales | K146: PR.DAC.2023.0345B | M146: 0 | R146: 0 | Z146: PR.DAC.2022.0063 AC | AC146: 1958816 | AG146: 1958816
I147: Ingresos | J147: 61010323 Análisis de materiales | K147: PR.DAC.2023.0345D | L147: 8737490 | R147: 8737490 | Z147: PR.DAC.2022.0063 AD | AD147: 1962815 | AG147: 1962815
I148: Ingresos | J148: 61010323 Análisis de materiales | K148: PR.DAC.2023.0345E | Q148: 3542377 | R148: 3542377 | Z148: PR.DAC.2022.0063 AE | AF148: 2005686 | AG148: 2005686
I149: Ingresos | J149: 61010323 Análisis de materiales | K149: PR.DAC.2023.0394 | O149: 8450488 | P149: 10968128 | R149: 19418616 | Z149: PR.DAC.2022.0105 | AA149: -4886067 | AB149: 4886067 | AC149: 358575 | AG149: 358575
I150: Ingresos | J150: 61010323 Análisis de materiales | K150: PR.DAC.2023.0450 | P150: 20336680 | R150: 20336680 | Z150: PR.DAC.2022.0147B | AA150: 13267 | AB150: 0 | AC150: 2945768 | AD150: 1483955 | AE150: 1499469 | AF150: 1509648 | AG150: 7452107
I151: Ingresos | J151: 61010323 Análisis de materiales | K151: PR.DAC.2023.0498 abril | Q151: 3152402 | R151: 3152402 | Z151: PR.DAC.2022.0158N | AA151: -1342685 | AG151: -1342685
I152: Ingresos | J152: 61010323 Análisis de materiales | K152: PR.DAC.2023.0498 Adicional Ago a Ene | M152: 16853544 | R152: 16853544 | Z152: PR.DAC.2022.0158O | AA152: -1010912 | AC152: 863569 | AG152: -147343
I153: Ingresos | J153: 61010323 Análisis de materiales | K153: PR.DAC.2023.0498 Febrero | N153: 8718029 | R153: 8718029 | Z153: PR.DAC.2022.0158O Muestreo | AC153: 152395 | AG153: 152395
I154: Ingresos | J154: 61010323 Análisis de materiales | K154: PR.DAC.2023.0498 Marzo | P154: 4123060 | R154: 4123060 | Z154: PR.DAC.2023.0015C | AA154: 0 | AG154: 0
I155: Ingresos | J155: 61010323 Análisis de materiales | K155: PR.DAC.2023.0498 mayo | Q155: 3152402 | R155: 3152402 | Z155: PR.DAC.2023.0015D | AA155: 0 | AG155: 0
I156: Ingresos | J156: 61010323 Análisis de materiales | K156: PR.DAC.2023.0515C | Q156: -10850600 | R156: -10850600 | Z156: PR.DAC.2023.0015E | AA156: 0 | AG156: 0
I157: Ingresos | J157: 61010323 Análisis de materiales | K157: PR.DAC.2023.0534C | P157: -7567837 | R157: -7567837 | Z157: PR.DAC.2023.0015F | AA157: 0 | AG157: 0
I158: Ingresos | J158: 61010323 Análisis de materiales | K158: PR.DAC.2023.0559 | P158: -7195900 | R158: -7195900 | Z158: PR.DAC.2023.0015G | AA158: -655573 | AG158: -655573
I159: Ingresos | J159: 61010323 Análisis de materiales | K159: PR.DAC.2024.0060F | N159: 2116968 | R159: 2116968 | Z159: PR.DAC.2023.0015H | AA159: -352828 | AG159: -352828
I160: Ingresos | J160: 61010323 Análisis de materiales | K160: PR.DAC.2024.0060G | N160: 2122770 | R160: 2122770 | Z160: PR.DAC.2023.0015I | AA160: 2405729 | AB160: -2405729 | AG160: 0
...

Sheet DCO
I1: EERR s/TI Fact | J1: Etiquetas de columna
I2: Etiquetas de fila | J2: ene | K2: feb | L2: mar | M2: abr | N2: may | O2: jun | P2: jul | Q2: ago | R2: sep | S2: oct | T2: nov | U2: dic | V2: Total general
I3: DCO | J3: 206690743 | K3: 512465962 | L3: 555906372 | M3: 323393211 | N3: 574669921 | O3: 202280197 | V3: 2375406406
I4: Total general | J4: 206690743 | K4: 512465962 | L4: 555906372 | M4: 323393211 | N4: 574669921 | O4: 202280197 | V4: 2375406406
I25: Ingreso_Salesforce | J25: Etiquetas de columna
I26: Etiquetas de fila | J26: ene | K26: feb | L26: mar | M26: abr | N26: may | O26: jun | P26: Total general
I27: DAC | J27: -169531556 | K27: 229661282 | L27: 132474079 | M27: 254268998 | N27: 4.6957042e+08 | O27: 3.6332564e+08 | P27: 1.2797689e+09
I28: DCO | J28: 842635563 | K28: 592333115 | L28: 354793861 | M28: 4.2707473e+08 | N28: 892309408 | O28: 486320169 | P28: 3.5954668e+09
I29: DDA | J29: 181228409 | K29: 129936364 | L29: 134027273 | M29: 157001893 | N29: 40429545 | O29: 130045454 | P29: 772668938
I30: DEP | J30: 27617921 | K30: 1.7119322e+08 | L30: 2.5230381e+08 | M30: 1.2067604e+08 | N30: 62156575 | O30: 79488858 | P30: 7.1343642e+08
I31: DES | J31: 289140060 | K31: 2.5750274e+08 | L31: 270815880 | M31: 267801174 | N31: 1.3945091e+08 | O31: 3.2742769e+08 | P31: 1.5521385e+09
I32: DGI | J32: 1271029488 | K32: 1406463891 | L32: 1321970041 | M32: -137844577 | N32: 3434507158 | O32: 1229933471 | P32: 8526059472
I33: DGL | J33: 286168992 | K33: 338984671 | L33: 230154271 | M33: 451087812 | N33: 341520986 | O33: 436919745 | P33: 2084836477
I34: DHC | J34: 73086361 | K34: 73231017 | L34: 80734296 | M34: 85650722 | N34: 83985839 | O34: 146170041 | P34: 542858276
I35: DHI | J35: 218731800 | K35: 172601844 | L35: 161539048 | M35: 196879192 | N35: 201803161 | O35: 125279423 | P35: 1076834468
I36: DIC | J36: 16026670 | K36: 57914174 | L36: 25901536 | M36: 90119211 | N36: 81835932 | O36: 41091978 | P36: 312889501
I37: DIO | J37: 50982594 | K37: 54985753 | L37: 42216285 | M37: 80987512 | N37: 47400975 | O37: 47567549 | P37: 324140668
I38: DPR | J38: 522514884 | K38: 478946114 | L38: 4.0956632e+08 | M38: 5.4676366e+08 | N38: 530145136 | O38: 492863760 | P38: 2980799873
I39: DTC | J39: 1.0186675e+08 | K39: 1.5340891e+08 | L39: 2.1757082e+08 | M39: 1.6916078e+08 | N39: 2.5458868e+08 | O39: 2.1220769e+08 | P39: 1.1088036e+09
I40: SDG | O40: 444000 | P40: 444000
I41: SDO | J41: 3594914 | K41: 198466 | L41: 5612144 | M41: 3876374 | N41: 3868251 | O41: 4465971 | P41: 21616120
I42: Total general | J42: 3.7150929e+09 | K42: 4.1173616e+09 | L42: 3.6396797e+09 | M42: 2.7135035e+09 | N42: 6.583573e+09 | O42: 4.1235514e+09 | P42: 2.4892762e+10
I62: Salesforce | J62: Ene | K62: Feb | L62: Mar | M62: Abr | N62: May | O62: Jun | P62: Jul | Q62: Ago | R62: Sep | S62: Oct | T62: Nov | U62: Dic | V62: Total
I63: DCO | J63: =IFERROR(VLOOKUP($I63,$I$26:$V$42,MATCH(J$62,$I$26:$V$26,0),0),0) -> 842635563 | K63: =IFERROR(VLOOKUP($I63,$I$26:$V$42,MATCH(K$62,$I$26:$V$26,0),0),0) -> 592333115 | L63: =IFERROR(VLOOKUP($I63,$I$26:$V$42,MATCH(L$62,$I$26:$V$26,0),0),0) -> 354793861 | M63: =IFERROR(VLOOKUP($I63,$I$26:$V$42,MATCH(M$62,$I$26:$V$26,0),0),0) -> 4.2707473e+08 | N63: =IFERROR(VLOOKUP($I63,$I$26:$V$42,MATCH(N$62,$I$26:$V$26,0),0),0) -> 892309408 | O63: =IFERROR(VLOOKUP($I63,$I$26:$V$42,MATCH(O$62,$I$26:$V$26,0),0),0) -> 486320169 | P63: =IFERROR(VLOOKUP($I63,$I$26:$V$42,MATCH(P$62,$I$26:$V$26,0),0),0) -> 0 | Q63: =IFERROR(VLOOKUP($I63,$I$26:$V$42,MATCH(Q$62,$I$26:$V$26,0),0),0) -> 0 | ... U63: =IFERROR(VLOOKUP($I63,$I$26:$V$42,MATCH(U$62,$I$26:$V$26,0),0),0) -> 0 | V63: =SUM(J63:U63) -> 3.5954668e+09
I83: Diferencia | J83: Ene | K83: Feb | L83: Mar | M83: Abr | N83: May | O83: Jun | P83: Jul | Q83: Ago | R83: Sep | S83: Oct | T83: Nov | U83: Dic | V83: Total
I84: DCO | J84: =-IFERROR(VLOOKUP($I84,$I$62:$U$80,MATCH(J$83,$I$62:$U$62,0),0),0)+IFERROR(VLOOKUP($I84,$I$2:$U$23,MATCH(J$83,$I$2:$U$2,0),0),0) -> -635944820 | K84: =-IFERROR(VLOOKUP($I84,$I$62:$U$80,MATCH(K$83,$I$62:$U$62,0),0),0)+IFERROR(VLOOKUP($I84,$I$2:$U$23,MATCH(K$83,$I$2:$U$2,0),0),0) -> -79867153 | L84: =-IFERROR(VLOOKUP($I84,$I$62:$U$80,MATCH(L$83,$I$62:$U$62,0),0),0)+IFERROR(VLOOKUP($I84,$I$2:$U$23,MATCH(L$83,$I$2:$U$2,0),0),0) -> 201112511 | M84: =-IFERROR(VLOOKUP($I84,$I$62:$U$80,MATCH(M$83,$I$62:$U$62,0),0),0)+IFERROR(VLOOKUP($I84,$I$2:$U$23,MATCH(M$83,$I$2:$U$2,0),0),0) -> -1.0368152e+08 | N84: =-IFERROR(VLOOKUP($I84,$I$62:$U$80,MATCH(N$83,$I$62:$U$62,0),0),0)+IFERROR(VLOOKUP($I84,$I$2:$U$23,MATCH(N$83,$I$2:$U$2,0),0),0) -> -317639487 | O84: =-IFERROR(VLOOKUP($I84,$I$62:$U$80,MATCH(O$83,$I$62:$U$62,0),0),0)+IFERROR(VLOOKUP($I84,$I$2:$U$23,MATCH(O$83,$I$2:$U$2,0),0),0) -> -284039972 | P84: =-IFERROR(VLOOKUP($I84,$I$62:$U$80,MATCH(P$83,$I$62:$U$62,0),0),0)+IFERROR(VLOOKUP($I84,$I$2:$U$23,MATCH(P$83,$I$2:$U$2,0),0),0) -> 0 | Q84: =-IFERROR(VLOOKUP($I84,$I$62:$U$80,MATCH(Q$83,$I$62:$U$62,0),0),0)+IFERROR(VLOOKUP($I84,$I$2:$U$23,MATCH(Q$83,$I$2:$U$2,0),0),0) -> 0 | ... U84: =-IFERROR(VLOOKUP($I84,$I$62:$U$80,MATCH(U$83,$I$62:$U$62,0),0),0)+IFERROR(VLOOKUP($I84,$I$2:$U$23,MATCH(U$83,$I$2:$U$2,0),0),0) -> 0 | V84: =SUM(J84:U84) -> -1.2200604e+09
I86: siglaDivision | J86: DCO | Z86: División | AA86: DCO
I88: EERR s/TI Fact | L88: fecha (mes) | Z88: Ingreso_Salesforce | AA88: Etiquetas de columna
A89: Facturación: Incluye Facturación externa y Traspasos de Servicios Internos | I89: Clasificación | J89: cuenta_contable_full | K89: Referencia Interna | L89: ene | M89: feb | N89: mar | O89: abr | P89: may | Q89: jun | R89: Total general | Z89: Etiquetas de fila | AA89: ene | AB89: feb | AC89: mar | AD89: abr | AE89: may | AF89: jun | AG89: Total general
A90: Traspasos: Corresponde solo a Traspasos de Facturación | I90: Ingresos | J90: 61010323 Análisis de materiales | L90: 3974932 | M90: 1641121 | O90: 1578203 | Q90: 119602 | R90: 7313858 | Z90: OP-DHC-2022-0093 - VTA (+01) Enero 2026 | AA90: 121616 | AG90: 121616
A91: Valor en círculo: Representa diferncia entre Backlog y Facturación | I91: Ingresos | J91: 61010323 Análisis de materiales | K91: OP-DHC-2022-0093 - VTA (+01) Enero 2026 | L91: 121616 | M91: -121616 | R91: 0 | Z91: OPR.DCO.2024-0948 - Licitación Codelco Andina | AE91: 102940866 | AF91: 37000000 | AG91: 139940866
I92: Ingresos | J92: 61010323 Análisis de materiales | K92: OPR.DCO.2025-0091 Licitación Codelco Chuqui Contramuestras | L92: 9789343 | N92: 897033 | R92: 10686376 | Z92: OPR.DCO.2025-0091 Licitación Codelco Chuqui Contramuestras | AD92: 62063028 | AG92: 62063028
I93: Ingresos | J93: 61010323 Análisis de materiales | K93: PR.DCO.1776.2023.104_Visitas_Permanencias_Aeropuerto | L93: 5742478 | R93: 5742478 | Z93: PR.DCO.1776.2023.104_Visitas_Permanencias_Aeropuerto | AB93: 76214541 | AG93: 76214541
I94: Ingresos | J94: 61010323 Análisis de materiales | K94: PR.DCO.1776.2024.177_INGEVEC-Ppal Cap. Ign. Carrera Pinto, Conchalí Adicional (+Vta Agosto) | L94: 399682 | R94: 399682 | Z94: PR.DCO.1776.2024.131_OHL-Mejoramiento Jenainpol Ñuñoa | AA94: 2785097 | AG94: 2785097
I95: Ingresos | J95: 61010323 Análisis de materiales | K95: PR.DCO.1776.2024.212 Cesfam Padre Hurtado | L95: 905797 | M95: 810004 | O95: 3575327 | P95: 859910 | Q95: 280214 | R95: 6431252 | Z95: PR.DCO.1776.2024.212 Cesfam Padre Hurtado | AA95: 10000000 | AC95: 13501393 | AG95: 23501393
I96: Ingresos | J96: 61010323 Análisis de materiales | K96: PR.DCO.1776.2024.317 Icafal Edificio Santa Rosa H47 | M96: 79195 | R96: 79195 | Z96: PR.DCO.1776.2024.220_BESALCO CONSTRUCCIONES-Placas de Carga | AA96: 6120060 | AG96: 6120060
I97: Ingresos | J97: 61010323 Análisis de materiales | K97: PR.DCO.1776.2024.345_VDZ-San Pablo Barracas | O97: 310765 | P97: -310765 | Q97: 310765 | R97: 310765 | Z97: PR.DCO.1776.2024.316_NOVATEC EDIF.-Barón de Juras Reales | AA97: 907332 | AG97: 907332
I98: Ingresos | J98: 61010323 Análisis de materiales | K98: PR.DCO.1776.2024.351_José M. Carreño_San Francisco | N98: 525236 | O98: 1075726 | P98: 300902 | Q98: 319606 | R98: 2221470 | Z98: PR.DCO.1776.2024.379_PL EDIFICACIONES-Distrito Paulista | AA98: 949102 | AG98: 949102
I99: Ingresos | J99: 61010323 Análisis de materiales | K99: PR.DCO.1776.2024.351_José M. Carreño-T. Tannenbaum | L99: 190694 | P99: 601803 | Q99: 146198 | R99: 938695 | Z99: PR.DCO.1776.2025.028_DPC-Data Center Etapa 2 | AF99: 1500000 | AG99: 1500000
I100: Ingresos | J100: 61010323 Análisis de materiales | K100: PR.DCO.1776.2024.374_INGEC-Rengo Adicional | L100: 15179012 | O100: 3760271 | R100: 18939283 | Z100: PR.DCO.1776.2025.076_Ferroactiva-F-139 Padre Hurtado | AA100: 19493 | AG100: 19493
I101: Ingresos | J101: 61010323 Análisis de materiales | K101: PR.DCO.1776.2025.111 Pocuro Cipreses VII - VIII - IX | L101: 896528 | O101: 2657992 | R101: 3554520 | Z101: PR.DCO.1776.2025.111 Pocuro Cipreses VII - VIII - IX | AA101: 3497526 | AG101: 3497526
I102: Ingresos | J102: 61010323 Análisis de materiales | K102: PR.DCO.1776.2025.132 Agrosonda SE | L102: 4301157 | M102: -1582440 | O102: 7095683 | P102: 682043 | Q102: 345191 | R102: 10841634 | Z102: PR.DCO.1776.2025.134 Icafal Plaza alcanzable | AA102: 6369865 | AG102: 6369865
I103: Ingresos | J103: 61010323 Análisis de materiales | K103: PR.DCO.1776.2025.134 Icafal Plaza alcanzable | L103: 238368 | R103: 238368 | Z103: PR.DCO.1776.2025.149_LEVEL ING.-Mar Del Sur (Mayo 2026) Adicional | AE103: 4000000 | AF103: 4000000 | AG103: 8000000
I104: Ingresos | J104: 61010323 Análisis de materiales | K104: PR.DCO.1776.2025.149_LEVEL ING.-Mar Del Sur | L104: 365497 | O104: 381990 | R104: 747487 | Z104: PR.DCO.1776.2025.174 Edifico Urban Fundamenta | AD104: 180673 | AG104: 180673
I105: Ingresos | J105: 61010323 Análisis de materiales | K105: PR.DCO.1776.2025.170 Los espinos 1 DGA | L105: 1229404 | R105: 1229404 | Z105: PR.DCO.1776.2025.177 Edifico Eco Vicuña | AA105: 2413359 | AG105: 2413359
I106: Ingresos | J106: 61010323 Análisis de materiales | K106: PR.DCO.1776.2025.171 Los espinos 2 DGA | L106: 1420065 | R106: 1420065 | Z106: PR.DCO.1776.2025.192_FUNDAMENTA-Eco Florida | AC106: 1485008 | AG106: 1485008
I107: Ingresos | J107: 61010323 Análisis de materiales | K107: PR.DCO.1776.2025.192_FUNDAMENTA-Eco Florida | O107: 314750 | R107: 314750 | Z107: PR.DCO.1776.2025.257_ALTIUS-The Ethel Balfour Library | AA107: 200000 | AG107: 200000
I108: Ingresos | J108: 61010323 Análisis de materiales | K108: PR.DCO.1776.2025.202_INGEVEC-Franklin | O108: 71715 | Q108: 73099 | R108: 144814 | Z108: PR.DCO.1776.2025.274.v2 Minera Florida Servicio spot | AA108: 5000000 | AC108: 5000000 | AG108: 10000000
I109: Ingresos | J109: 61010323 Análisis de materiales | K109: PR.DCO.1776.2025.205_MYA-LAS HORTENSIAS | O109: 406386 | R109: 406386 | Z109: PR.DCO.1776.2025.280 INGEVEC BAÑOS MODULARES | AA109: 1500000 | AB109: 2039569 | AG109: 3539569
I110: Ingresos | J110: 61010323 Análisis de materiales | K110: PR.DCO.1776.2025.214_SERVILAND-Transformador de Respaldo SE Lampa 220_23 kV | N110: 405864 | R110: 405864 | Z110: PR.DCO.1776.2025.281 Resistencia hormigones - Apoquindo 6880 | AA110: 5000000 | AG110: 5000000
I111: Ingresos | J111: 61010323 Análisis de materiales | K111: PR.DCO.1776.2025.255_MyC-Construcción Obras Civiles Talleres y Cocheras Línea 7 | L111: 0 | R111: 0 | Z111: PR.DCO.1776.2025.320_TECSA-U La Laguna | AA111: 7255480 | AC111: 5854140 | AG111: 13109620
I112: Ingresos | J112: 61010323 Análisis de materiales | K112: PR.DCO.1776.2025.262_MYA-Las Perdices | L112: 969362 | N112: 393927 | O112: 585673 | P112: 914741 | R112: 2863703 | Z112: PR.DCO.1776.2025.335_Embalse Carén_Tecnasic | AA112: 1000000 | AB112: 1000000 | AC112: 2000000 | AD112: 20000000 | AE112: 20000000 | AF112: 20000000 | AG112: 64000000
I113: Ingresos | J113: 61010323 Análisis de materiales | K113: PR.DCO.1776.2025.280 INGEVEC BAÑOS MODULARES | N113: 238744 | O113: 95620 | P113: 385154 | Q113: 194931 | R113: 914449 | Z113: PR.DCO.1776.2025.343_ISLA PICTON-Altos del Valle | AA113: 400000 | AB113: 300000 | AG113: 700000
I114: Ingresos | J114: 61010323 Análisis de materiales | K114: PR.DCO.1776.2025.299_CERRO APOQUINDO 4-PRAT | L114: 654849 | P114: 4018815 | Q114: 961120 | R114: 5634784 | Z114: PR.DCO.1776.2025.344_COPAHUE-Macul Oriente 1 – Etapa 2 | AA114: 8700000 | AB114: 0 | AG114: 8700000
I115: Ingresos | J115: 61010323 Análisis de materiales | K115: PR.DCO.1776.2025.301_CONSTRUCTORA PAZ-Arboleda Etapa 2 | O115: 179287 | R115: 179287 | Z115: PR.DCO.1776.2025.364_Constructora VDZ-San Pablo Barracas | AA115: 1500000 | AB115: 3000000 | AC115: 2031934 | AG115: 6531934
I116: Ingresos | J116: 61010323 Análisis de materiales | K116: PR.DCO.1776.2025.320_TECSA-U La Laguna | L116: 2151392 | O116: 6053150 | P116: 5968290 | Q116: 2838504 | R116: 17011336 | Z116: PR.DCO.1776.2025.372_LUIS OLAVE-CESFAM RURAL DE PAHUILMO Adicional Abril 2026 | AE116: 1115568 | AG116: 1115568
I117: Ingresos | J117: 61010323 Análisis de materiales | K117: PR.DCO.1776.2025.335_Embalse Carén_Tecnasic | L117: 4188169 | M117: 913240 | N117: 1742830 | P117: 3169475 | R117: 10013714 | Z117: PR.DCO.1776.2025.374_INGEVEC-Franklin Sinergia 0788 | AF117: 989687 | AG117: 989687
I118: Ingresos | J118: 61010323 Análisis de materiales | K118: PR.DCO.1776.2025.337 Edificio Vivaceta Ingevec | L118: 143021 | M118: 214413 | R118: 357434 | Z118: PR.DCO.1776.2025.403_INGEVEC-Edificio Coronel Godoy_V2 | AD118: 500000 | AG118: 500000
I119: Ingresos | J119: 61010323 Análisis de materiales | K119: PR.DCO.1776.2025.343_ISLA PICTON-Altos del Valle | L119: 382051 | N119: 412496 | R119: 794547 | Z119: PR.DCO.1776.2025.406_SERVILAND-SE LAS ACACIAS | AB119: 5900000 | AG119: 5900000
I120: Ingresos | J120: 61010323 Análisis de materiales | K120: PR.DCO.1776.2025.344_COPAHUE-Macul Oriente 1 – Etapa 2 | L120: 95347 | M120: 190589 | R120: 285936 | Z120: PR.DCO.1776.2025.409_SAN VICENTE-Cesfam Ossandón | AA120: 900000 | AB120: 700000 | AC120: 737432 | AG120: 2337432
I121: Ingresos | J121: 61010323 Análisis de materiales | K121: PR.DCO.1776.2025.354_PROMET-Planta Chacabuco | L121: 308862 | R121: 308862 | Z121: PR.DCO.1776.2025.411_ALTIUS-Edificio Macul 1C | AD121: 180000 | AE121: 1800000 | AG121: 1980000
I122: Ingresos | J122: 61010323 Análisis de materiales | K122: PR.DCO.1776.2025.372_LUIS OLAVE-CESFAM RURAL DE PAHUILMO | M122: 174655 | N122: 151399 | P122: 869586 | R122: 1195640 | Z122: PR.DCO.1776.2025.422_INGEVEC-Macrolote XII | AE122: 523000 | AG122: 523000
I123: Ingresos | J123: 61010323 Análisis de materiales | K123: PR.DCO.1776.2025.403_INGEVEC-Edificio Coronel Godoy_V2 | O123: 170467 | R123: 170467 | Z123: PR.DCO.1776.2025.427_ALTIUS-Edificio Macul 1C | AA123: 400000 | AG123: 400000
I124: Ingresos | J124: 61010323 Análisis de materiales | K124: PR.DCO.1776.2025.406_SERVILAND-SE LAS ACACIAS | L124: 103293 | R124: 103293 | Z124: PR.DCO.1776.2025.428_DESCO-Marín | AA124: 485009 | AG124: 485009
I125: Ingresos | J125: 61010323 Análisis de materiales | K125: PR.DCO.1776.2025.409_SAN VICENTE-Cesfam Ossandón | P125: 1056923 | R125: 1056923 | Z125: PR.DCO.1776.2025.433_INGEVEC-Nueva Esmeralda | AB125: 350000 | AG125: 350000
I126: Ingresos | J126: 61010323 Análisis de materiales | K126: PR.DCO.1776.2025.424_TECSA-Centro Comercial Parque Quilicura | O126: 1736861 | Q126: 4278819 | R126: 6015680 | Z126: PR.DCO.1776.2025.433_INGEVEC-Nueva Esmeralda_Adicional Mayo 2026 | AE126: 460000 | AF126: 460000 | AG126: 920000
I127: Ingresos | J127: 61010323 Análisis de materiales | K127: PR.DCO.1776.2025.427_ALTIUS-Edificio Macul 1C | M127: 170830 | N127: 743071 | P127: 967900 | Q127: 341130 | R127: 2222931 | Z127: PR.DCO.1776.2025.435_INGEVEC-Edificio Brisas del Maipo | AA127: 450000 | AG127: 450000
I128: Ingresos | J128: 61010323 Análisis de materiales | K128: PR.DCO.1776.2025.428_DESCO-Marín | N128: 441676 | O128: 170830 | P128: 1030590 | Q128: 262662 | R128: 1905758 | Z128: PR.DCO.1776.2025.445_INGEVEC-0775 Las Pioneras de Rodelillo | AA128: 200000 | AB128: 800000 | AC128: 800000 | AD128: 900000 | AE128: 900000 | AF128: 900000 | AG128: 4500000
I129: Ingresos | J129: 61010323 Análisis de materiales | K129: PR.DCO.1776.2025.433_INGEVEC-Nueva Esmeralda | N129: 341231 | Q129: 174626 | R129: 515857 | Z129: PR.DCO.1776.2025.447_TECSA-Centro Comercial Parque Quilicura Hormigones SUELOS | AF129: 6000000 | AG129: 6000000
I130: Ingresos | J130: 61010323 Análisis de materiales | K130: PR.DCO.1776.2025.435_INGEVEC-Edificio Brisas del Maipo | L130: 285037 | R130: 285037 | Z130: PR.DCO.1776.2025.448_SERVILAND-AMPLIACION EN SE RUNGUE (NTR ATMT)_FASE 1 | AB130: 2500000 | AC130: 3000000 | AD130: 3000000 | AE130: 3000000 | AF130: 2165947 | AG130: 13665947
I131: Ingresos | J131: 61010323 Análisis de materiales | K131: PR.DCO.1776.2025.445_INGEVEC-0775 Las Pioneras de Rodelillo | N131: 874643 | O131: 370528 | P131: 365094 | Q131: 609160 | R131: 2219425 | Z131: PR.DCO.1776.2025.449_GALCONT-Pavimentos SEL VM | AA131: 400000 | AG131: 400000
I132: Ingresos | J132: 61010323 Análisis de materiales | K132: PR.DCO.1776.2025.448_SERVILAND-AMPLIACION EN SE RUNGUE (NTR ATMT)_FASE 1 | N132: 990787 | O132: 302797 | P132: 280841 | R132: 1574425 | Z132: PR.DCO.1776.2026.002_ANTUCOYA-Placas de Carga Antucoya | AC132: 11885549 | AG132: 11885549
I133: Ingresos | J133: 61010323 Análisis de materiales | K133: PR.DCO.1776.2025.449_GALCONT-Pavimentos SEL VM | L133: 333971 | R133: 333971 | Z133: PR.DCO.1776.2026.004_COPAHUE-Los Barbechos | AA133: 174887 | AG133: 174887
I134: Ingresos | J134: 61010323 Análisis de materiales | K134: PR.DCO.1776.2026.002_ANTUCOYA-Placas de Carga Antucoya | N134: 11933787 | R134: 11933787 | Z134: PR.DCO.1776.2026.009_COX-BESS Cardonal | AB134: 6000000 | AC134: 8000000 | AD134: 8000000 | AE134: 5139807 | AG134: 27139807
I135: Ingresos | J135: 61010323 Análisis de materiales | K135: PR.DCO.1776.2026.004_COPAHUE-Los Barbechos | P135: 0 | R135: 0 | Z135: PR.DCO.1776.2026.025_Alejandro Alfaro-Condominio Golf Los Lirios | AC135: 1000027 | AG135: 1000027
I136: Ingresos | J136: 61010323 Análisis de materiales | K136: PR.DCO.1776.2026.009_COX-BESS Cardonal | O136: 7294420 | P136: 4959860 | Q136: 3092504 | R136: 15346784 | Z136: PR.DCO.1776.2026.043_FGS-Las Condes 7944 | AD136: 400000 | AG136: 400000
I137: Ingresos | J137: 61010323 Análisis de materiales | K137: PR.DCO.1776.2026.025_Alejandro Alfaro-Condominio Golf Los Lirios | Q137: 1000027 | R137: 1000027 | Z137: PR.DCO.1776.2026.047_SERVILAND-SE Cerro Navia | AB137: 1600000 | AC137: 1600000 | AD137: 1600000 | AE137: 1754887 | AG137: 6554887
I138: Ingresos | J138: 61010323 Análisis de materiales | K138: PR.DCO.1776.2026.043_FGS-Las Condes 7944 | P138: 171100 | R138: 171100 | Z138: PR.DCO.1776.2026.053_INGEVEC-Edificio Diagonal Paraguay | AD138: 170000 | AG138: 170000
I139: Ingresos | J139: 61010323 Análisis de materiales | K139: PR.DCO.1776.2026.047_SERVILAND-SE Cerro Navia | N139: 198953 | O139: 764961 | P139: 840518 | Q139: 292397 | R139: 2096829 | Z139: PR.DCO.1776.2026.056_SAN VICENTE-Cesfam Ossandón | AB139: 208033 | AG139: 208033
I140: Ingresos | J140: 61010323 Análisis de materiales | K140: PR.DCO.1776.2026.056_SAN VICENTE-Cesfam Ossandón | O140: 175079 | R140: 175079 | Z140: PR.DCO.1776.2026.057_ALM-VM1500 TORRE | AB140: 170714 | AG140: 170714
I141: Ingresos | J141: 61010323 Análisis de materiales | K141: PR.DCO.1776.2026.057_ALM-VM1500 TORRE | O141: 171100 | P141: -171100 | R141: 0 | Z141: PR.DCO.1776.2026.069_ANDES SOLAR-PFV Los Pétalos ubicado en Camino Interior 1897, Fundo Santa Adela | AD141: 800000 | AG141: 800000
I142: Ingresos | J142: 61010323 Análisis de materiales | K142: PR.DCO.1776.2026.069_ANDES SOLAR-PFV Los Pétalos ubicado en Camino Interior 1897, Fundo Santa Adela | O142: 746074 | R142: 746074 | Z142: PR.DCO.1776.2026.085_SERVILAND-Subestación Polpaico | AD142: 3000000 | AG142: 3000000
I143: Ingresos | J143: 61010323 Análisis de materiales | K143: PR.DCO.1776.2026.085_SERVILAND-Subestación Polpaico | O143: 262955 | P143: 184553 | Q143: 938107 | R143: 1385615 | Z143: PR.DCO.1776.2026.120 - Proyecto Los Castaños 2796 La Florida | AE143: 500000 | AG143: 500000
I144: Ingresos | J144: 61010323 Análisis de materiales | K144: PR.DCO.1776.2026.120 - Proyecto Los Castaños 2796 La Florida | P144: 418338 | R144: 418338 | Z144: PR.DCO.1776.2026.133_Constructora Paz-Parque Arboleda 2 | AD144: 140000 | AG144: 140000
I145: Ingresos | J145: 61010323 Análisis de materiales | K145: PR.DCO.1776.2026.142 Serviland SE El Manzano | O145: 625515 | P145: 328986 | Q145: 331992 | R145: 1286493 | Z145: PR.DCO.1776.2026.142 Serviland SE El Manzano | AD145: 2500000 | AF145: 577841 | AG145: 3077841
I146: Ingresos | J146: 61010323 Análisis de materiales | K146: PR.DCO.1776.2026.143 Serviland SE Batuco | O146: 278892 | P146: 581743 | R146: 860635 | Z146: PR.DCO.1776.2026.143 Serviland SE Batuco | AD146: 2500000 | AF146: 3077841 | AG146: 5577841
I147: Ingresos | J147: 61010323 Análisis de materiales | K147: PR.DCO.1776.2026.152_UNO DESARROLLOS-Remodelación ACHS Melipilla | O147: 382481 | R147: 382481 | Z147: PR.DCO.1776.2026.152_UNO DESARROLLOS-Remodelación ACHS Melipilla | AD147: 1000000 | AG147: 1000000
I148: Ingresos | J148: 61010323 Análisis de materiales | K148: PR.DCO.1776.2026.169 CONSTRUCTORA IGNACIO HURTADO LTDA. Edificio Uno | N148: 478101 | R148: 478101 | Z148: PR.DCO.1776.2026.169 CONSTRUCTORA IGNACIO HURTADO LTDA. Edificio Uno | AC148: 30 | AG148: 30
I149: Ingresos | J149: 61010323 Análisis de materiales | K149: PR.DCO.1776.2026.196_IK2-CASA HELSINKI | P149: 660667 | R149: 660667 | Z149: PR.DCO.1776.2026.196_IK2-CASA HELSINKI | AE149: 661325 | AG149: 661325
I150: Ingresos | J150: 61010323 Análisis de materiales | K150: PR.DCO.1776.2026.199_BOETSCH-Terrazas del Bicentenario | P150: 385154 | Q150: 97466 | R150: 482620 | Z150: PR.DCO.1776.2026.199_BOETSCH-Terrazas del Bicentenario | AE150: 450000 | AG150: 450000
I151: Ingresos | J151: 61010323 Análisis de materiales | K151: PR.DCO.1776.2026.217_Const. del Choapa-Conservación Río Maipo Confluencia Estero San José y Quebrad | O151: 470132 | Q151: 1277168 | R151: 1747300 | Z151: PR.DCO.1776.2026.217_Const. del Choapa-Conservación Río Maipo Confluencia Estero San José y Quebrada La Solana | AD151: 1747299 | AG151: 1747299
I152: Ingresos | J152: 61010323 Análisis de materiales | K152: PR.DCO.1776.2026.243_VAIPS-Subestación Eléctrica Itahue | O152: 951226 | P152: 501336 | R152: 1452562 | Z152: PR.DCO.1776.2026.240_INGESAT-Sub Estación El Salto Huechuraba | AF152: 1750000 | AG152: 1750000
I153: Ingresos | J153: 61010323 Análisis de materiales | K153: PR.DCO.1776.2026.278_SERVILAND-Modificaciones en Patio 110 Kv SE VITACURA | Q153: 316763 | R153: 316763 | Z153: PR.DCO.1776.2026.243 VAI PS INGENIERIA Y SERVICIOS SPA | AD153: 475219 | AG153: 475219
I154: Ingresos | J154: 61010323 Análisis de materiales | K154: PR.DCO.1776.2026.297_LA NAVE-Universidad Autónoma Sede San Miguel | Q154: 304580 | R154: 304580 | Z154: PR.DCO.1776.2026.243_VAIPS-Subestación Eléctrica Itahue | AD154: 1000000 | AG154: 1000000
I155: Ingresos | J155: 61010323 Análisis de materiales | K155: PR.DCO.1829.2025-0590 - VTA (+01) Abril 2026 | O155: 53858 | R155: 53858 | Z155: PR.DCO.1776.2026.258 Tecton Edificación y OOCC SE Lord Cochrane | AF155: 2000000 | AG155: 2000000
I156: Ingresos | J156: 61010323 Análisis de materiales | K156: PR.DCO.1829.2025-0591 - Constructora Gonzalez García - Reposición Cuarta Comisaría Hualpén | L156: 1441043 | N156: 1710215 | O156: 1368563 | P156: 667765 | R156: 5187586 | Z156: PR.DCO.1776.2026.278_SERVILAND-Modificaciones en Patio 110 Kv SE VITACURA | AE156: 590942 | AG156: 590942
I157: Ingresos | J157: 61010323 Análisis de materiales | K157: PR.DCO.1829.2025-0638 - Edificio Castellon 227 | L157: 535913 | M157: 1052768 | P157: 1449961 | Q157: 466051 | R157: 3504693 | Z157: PR.DCO.1776.2026.297_LA NAVE-Universidad Autónoma Sede San Miguel | AF157: 1000000 | AG157: 1000000
I158: Ingresos | J158: 61010323 Análisis de materiales | K158: PR.DCO.1829.2025-0657 - Fundación y Estructura para Condensador Oriente - Pesquera Orizon Coronel | P158: 147079 | R158: 147079 | Z158: PR.DCO.1829.2025-0590 - VTA (+01) Abril 2026 | AD158: 53858 | AG158: 53858
I159: Ingresos | J159: 61010323 Análisis de materiales | K159: PR.DCO.1829.2025-0660 - VTA (+01) Enero 2026 | L159: 522776 | R159: 522776 | Z159: PR.DCO.1829.2025-0590 - VTA (+01) Junio 2026 | AF159: 55052 | AG159: 55052
I160: Ingresos | J160: 61010323 Análisis de materiales | K160: PR.DCO.1829.2025-0662 - Fundación Estanque Hualqui | L160: 1025368 | R160: 1025368 | Z160: PR.DCO.1829.2025-0591 - Constructora Gonzalez García - Reposición Cuarta Comisaría Hualpén | AA160: 1500000 | AB160: 1500000 | AC160: 1500000 | AD160: 1500000 | AE160: 1500000 | AG160: 7500000
...

Sheet DDA
I1: EERR s/TI Fact | J1: Etiquetas de columna
I2: Etiquetas de fila | J2: ene | K2: feb | L2: mar | M2: abr | N2: may | O2: jun | P2: jul | Q2: ago | R2: sep | S2: oct | T2: nov | U2: dic | V2: Total general
I3: DDA | J3: 253505267 | K3: 260928783 | L3: 243506035 | M3: 317466070 | N3: 267291057 | O3: 268536935 | V3: 1611234147
I4: Total general | J4: 253505267 | K4: 260928783 | L4: 243506035 | M4: 317466070 | N4: 267291057 | O4: 268536935 | V4: 1611234147
I25: Ingreso_Salesforce | J25: Etiquetas de columna
I26: Etiquetas de fila | J26: ene | K26: feb | L26: mar | M26: abr | N26: may | O26: jun | P26: Total general
I27: DAC | J27: -169531556 | K27: 229661282 | L27: 132474079 | M27: 254268998 | N27: 4.6957042e+08 | O27: 3.6332564e+08 | P27: 1.2797689e+09
I28: DCO | J28: 842635563 | K28: 592333115 | L28: 354793861 | M28: 4.2707473e+08 | N28: 892309408 | O28: 486320169 | P28: 3.5954668e+09
I29: DDA | J29: 181228409 | K29: 129936364 | L29: 134027273 | M29: 157001893 | N29: 40429545 | O29: 130045454 | P29: 772668938
I30: DEP | J30: 27617921 | K30: 1.7119322e+08 | L30: 2.5230381e+08 | M30: 1.2067604e+08 | N30: 62156575 | O30: 79488858 | P30: 7.1343642e+08
I31: DES | J31: 289140060 | K31: 2.5750274e+08 | L31: 270815880 | M31: 267801174 | N31: 1.3945091e+08 | O31: 3.2742769e+08 | P31: 1.5521385e+09
I32: DGI | J32: 1271029488 | K32: 1406463891 | L32: 1321970041 | M32: -137844577 | N32: 3434507158 | O32: 1229933471 | P32: 8526059472
I33: DGL | J33: 286168992 | K33: 338984671 | L33: 230154271 | M33: 451087812 | N33: 341520986 | O33: 436919745 | P33: 2084836477
I34: DHC | J34: 73086361 | K34: 73231017 | L34: 80734296 | M34: 85650722 | N34: 83985839 | O34: 146170041 | P34: 542858276
I35: DHI | J35: 218731800 | K35: 172601844 | L35: 161539048 | M35: 196879192 | N35: 201803161 | O35: 125279423 | P35: 1076834468
I36: DIC | J36: 16026670 | K36: 57914174 | L36: 25901536 | M36: 90119211 | N36: 81835932 | O36: 41091978 | P36: 312889501
I37: DIO | J37: 50982594 | K37: 54985753 | L37: 42216285 | M37: 80987512 | N37: 47400975 | O37: 47567549 | P37: 324140668
I38: DPR | J38: 522514884 | K38: 478946114 | L38: 4.0956632e+08 | M38: 5.4676366e+08 | N38: 530145136 | O38: 492863760 | P38: 2980799873
I39: DTC | J39: 1.0186675e+08 | K39: 1.5340891e+08 | L39: 2.1757082e+08 | M39: 1.6916078e+08 | N39: 2.5458868e+08 | O39: 2.1220769e+08 | P39: 1.1088036e+09
I40: SDG | O40: 444000 | P40: 444000
I41: SDO | J41: 3594914 | K41: 198466 | L41: 5612144 | M41: 3876374 | N41: 3868251 | O41: 4465971 | P41: 21616120
I42: Total general | J42: 3.7150929e+09 | K42: 4.1173616e+09 | L42: 3.6396797e+09 | M42: 2.7135035e+09 | N42: 6.583573e+09 | O42: 4.1235514e+09 | P42: 2.4892762e+10
I62: Salesforce | J62: Ene | K62: Feb | L62: Mar | M62: Abr | N62: May | O62: Jun | P62: Jul | Q62: Ago | R62: Sep | S62: Oct | T62: Nov | U62: Dic | V62: Total
I63: DDA | J63: =IFERROR(VLOOKUP($I63,$I$26:$V$42,MATCH(J$62,$I$26:$V$26,0),0),0) -> 181228409 | K63: =IFERROR(VLOOKUP($I63,$I$26:$V$42,MATCH(K$62,$I$26:$V$26,0),0),0) -> 129936364 | L63: =IFERROR(VLOOKUP($I63,$I$26:$V$42,MATCH(L$62,$I$26:$V$26,0),0),0) -> 134027273 | M63: =IFERROR(VLOOKUP($I63,$I$26:$V$42,MATCH(M$62,$I$26:$V$26,0),0),0) -> 157001893 | N63: =IFERROR(VLOOKUP($I63,$I$26:$V$42,MATCH(N$62,$I$26:$V$26,0),0),0) -> 40429545 | O63: =IFERROR(VLOOKUP($I63,$I$26:$V$42,MATCH(O$62,$I$26:$V$26,0),0),0) -> 130045454 | P63: =IFERROR(VLOOKUP($I63,$I$26:$V$42,MATCH(P$62,$I$26:$V$26,0),0),0) -> 0 | Q63: =IFERROR(VLOOKUP($I63,$I$26:$V$42,MATCH(Q$62,$I$26:$V$26,0),0),0) -> 0 | ... U63: =IFERROR(VLOOKUP($I63,$I$26:$V$42,MATCH(U$62,$I$26:$V$26,0),0),0) -> 0 | V63: =SUM(J63:U63) -> 772668938
I83: Diferencia | J83: Ene | K83: Feb | L83: Mar | M83: Abr | N83: May | O83: Jun | P83: Jul | Q83: Ago | R83: Sep | S83: Oct | T83: Nov | U83: Dic | V83: Total
I84: DDA | J84: =-IFERROR(VLOOKUP($I84,$I$62:$U$80,MATCH(J$83,$I$62:$U$62,0),0),0)+IFERROR(VLOOKUP("Total general",$I$2:$U$23,MATCH(J$83,$I$2:$U$2,0),0),0) -> 72276858 | K84: =-IFERROR(VLOOKUP($I84,$I$62:$U$80,MATCH(K$83,$I$62:$U$62,0),0),0)+IFERROR(VLOOKUP("Total general",$I$2:$U$23,MATCH(K$83,$I$2:$U$2,0),0),0) -> 130992419 | L84: =-IFERROR(VLOOKUP($I84,$I$62:$U$80,MATCH(L$83,$I$62:$U$62,0),0),0)+IFERROR(VLOOKUP("Total general",$I$2:$U$23,MATCH(L$83,$I$2:$U$2,0),0),0) -> 109478762 | M84: =-IFERROR(VLOOKUP($I84,$I$62:$U$80,MATCH(M$83,$I$62:$U$62,0),0),0)+IFERROR(VLOOKUP("Total general",$I$2:$U$23,MATCH(M$83,$I$2:$U$2,0),0),0) -> 160464177 | N84: =-IFERROR(VLOOKUP($I84,$I$62:$U$80,MATCH(N$83,$I$62:$U$62,0),0),0)+IFERROR(VLOOKUP("Total general",$I$2:$U$23,MATCH(N$83,$I$2:$U$2,0),0),0) -> 226861512 | O84: =-IFERROR(VLOOKUP($I84,$I$62:$U$80,MATCH(O$83,$I$62:$U$62,0),0),0)+IFERROR(VLOOKUP("Total general",$I$2:$U$23,MATCH(O$83,$I$2:$U$2,0),0),0) -> 138491481 | P84: =-IFERROR(VLOOKUP($I84,$I$62:$U$80,MATCH(P$83,$I$62:$U$62,0),0),0)+IFERROR(VLOOKUP("Total general",$I$2:$U$23,MATCH(P$83,$I$2:$U$2,0),0),0) -> 0 | Q84: =-IFERROR(VLOOKUP($I84,$I$62:$U$80,MATCH(Q$83,$I$62:$U$62,0),0),0)+IFERROR(VLOOKUP("Total general",$I$2:$U$23,MATCH(Q$83,$I$2:$U$2,0),0),0) -> 0 | ... U84: =-IFERROR(VLOOKUP($I84,$I$62:$U$80,MATCH(U$83,$I$62:$U$62,0),0),0)+IFERROR(VLOOKUP("Total general",$I$2:$U$23,MATCH(U$83,$I$2:$U$2,0),0),0) -> 0 | V84: =SUM(J84:U84) -> 838565209
I86: siglaDivision | J86: DDA | Z86: División | AA86: DDA
I88: EERR s/TI Fact | L88: fecha (mes) | Z88: Ingreso_Salesforce | AA88: Etiquetas de columna
A89: Facturación: Incluye Facturación externa y Traspasos de Servicios Internos | I89: Clasificación | J89: cuenta_contable_full | K89: Referencia Interna | L89: ene | M89: feb | N89: mar | O89: abr | P89: may | Q89: jun | R89: Total general | Z89: Etiquetas de fila | AA89: ene | AB89: feb | AC89: mar | AD89: abr | AE89: may | AF89: jun | AG89: Total general
A90: Traspasos: Corresponde solo a Traspasos de Facturación | I90: Ingresos | J90: 61010302 Asesorías y consultorías exterior | K90: PR.DDA.2025-075B Cuenca Magallanes | P90: 0 | R90: 0 | Z90: PR.DDA.2025-075B Cuenca Magallanes | AD90: 26956439 | AG90: 26956439
A91: Valor en círculo: Representa diferncia entre Backlog y Facturación | I91: Ingresos | J91: 61010323 Análisis de materiales | K91: PR.DDA.2025-075B Cuenca Magallanes | P91: 26956439 | R91: 26956439 | Z91: PR.DGI.2023-043 Estudio hidrogeológico Pozos Araucanía DOH | AA91: 0 | AB91: 0 | AC91: 0 | AD91: 0 | AF91: 0 | AG91: 0
I92: Provisión | J92: 61010302 Asesorías y consultorías exterior | K92: PR.DDA.2025-075B Cuenca Magallanes | O92: 26956439 | R92: 26956439 | Z92: PR.DOH.2025-001 Estudio hidrogeológico Pozos Araucanía DOH | AA92: 89615909 | AB92: 89615909 | AC92: 93706818 | AD92: 89615909 | AF92: 89615909 | AG92: 452170454
I93: Provisión | J93: 61010804 Aporte Ministerio | K93: (en blanco) | L93: 253505267 | M93: 260928783 | N93: 243506035 | R93: 757940085 | Z93: Propuesta comercial DOH Araucanía (Cuotas 2025) | AA93: 91612500 | AB93: 40320455 | AC93: 40320455 | AD93: 40429545 | AE93: 40429545 | AF93: 40429545 | AG93: 293542045
I94: Provisión | J94: 61010804 Aporte Ministerio | K94: PR.DGI.2023-043 Estudio hidrogeológico Pozos Araucanía DOH | O94: 290509631 | P94: 267291057 | Q94: 268536935 | R94: 826337623 | Z94: Total general | AA94: 181228409 | AB94: 129936364 | AC94: 134027273 | AD94: 157001893 | AE94: 40429545 | AF94: 130045454 | AG94: 772668938
I95: Reversa | J95: 61010302 Asesorías y consultorías exterior | K95: PR.DDA.2025-075B Cuenca Magallanes | P95: -26956439 | R95: -26956439
I96: Reversa | J96: 61010804 Aporte Ministerio | K96: (en blanco) | N96: -178985088 | P96: -874519487 | R96: -1053504575
I97: Reversa | J97: 61010804 Aporte Ministerio | K97: PR.DGI.2023-043 Estudio hidrogeológico Pozos Araucanía DOH | P97: -97148440 | Q97: -320548099 | R97: -417696539
I98: Traspasos | J98: 61010804 Aporte Ministerio | K98: 478769 | N98: 178985088 | R98: 178985088
I99: Traspasos | J99: 61010804 Aporte Ministerio | K99: 483671 | P99: 110837276 | R99: 110837276
I100: Traspasos | J100: 61010804 Aporte Ministerio | K100: 483672 | P100: 386493310 | R100: 386493310
I101: Traspasos | J101: 61010804 Aporte Ministerio | K101: 483673 | P101: 271551543 | R101: 271551543
I102: Traspasos | J102: 61010804 Aporte Ministerio | K102: 485447 | P102: 202785798 | R102: 202785798
I103: Traspasos | J103: 61010804 Aporte Ministerio | K103: 488662 | Q103: 320548099 | R103: 320548099
I104: Total general | L104: 253505267 | M104: 260928783 | N104: 243506035 | O104: 317466070 | P104: 267291057 | Q104: 268536935 | R104: 1611234147

Sheet DEP
I1: EERR s/TI Fact | J1: Etiquetas de columna
I2: Etiquetas de fila | J2: ene | K2: feb | L2: mar | M2: abr | N2: may | O2: jun | P2: jul | Q2: ago | R2: sep | S2: oct | T2: nov | U2: dic | V2: Total general
I3: DEP | J3: 100713842 | K3: 103734301 | L3: 148678005 | M3: 137835819 | N3: 135342044 | O3: 151372459 | V3: 777676470
I4: Total general | J4: 100713842 | K4: 103734301 | L4: 148678005 | M4: 137835819 | N4: 135342044 | O4: 151372459 | V4: 777676470
I25: Ingreso_Salesforce | J25: Etiquetas de columna
I26: Etiquetas de fila | J26: ene | K26: feb | L26: mar | M26: abr | N26: may | O26: jun | P26: Total general
I27: DAC | J27: -169531556 | K27: 229661282 | L27: 132474079 | M27: 254268998 | N27: 4.6957042e+08 | O27: 3.6332564e+08 | P27: 1.2797689e+09
I28: DCO | J28: 842635563 | K28: 592333115 | L28: 354793861 | M28: 4.2707473e+08 | N28: 892309408 | O28: 486320169 | P28: 3.5954668e+09
I29: DDA | J29: 181228409 | K29: 129936364 | L29: 134027273 | M29: 157001893 | N29: 40429545 | O29: 130045454 | P29: 772668938
I30: DEP | J30: 27617921 | K30: 1.7119322e+08 | L30: 2.5230381e+08 | M30: 1.2067604e+08 | N30: 62156575 | O30: 79488858 | P30: 7.1343642e+08
I31: DES | J31: 289140060 | K31: 2.5750274e+08 | L31: 270815880 | M31: 267801174 | N31: 1.3945091e+08 | O31: 3.2742769e+08 | P31: 1.5521385e+09
I32: DGI | J32: 1271029488 | K32: 1406463891 | L32: 1321970041 | M32: -137844577 | N32: 3434507158 | O32: 1229933471 | P32: 8526059472
I33: DGL | J33: 286168992 | K33: 338984671 | L33: 230154271 | M33: 451087812 | N33: 341520986 | O33: 436919745 | P33: 2084836477
I34: DHC | J34: 73086361 | K34: 73231017 | L34: 80734296 | M34: 85650722 | N34: 83985839 | O34: 146170041 | P34: 542858276
I35: DHI | J35: 218731800 | K35: 172601844 | L35: 161539048 | M35: 196879192 | N35: 201803161 | O35: 125279423 | P35: 1076834468
I36: DIC | J36: 16026670 | K36: 57914174 | L36: 25901536 | M36: 90119211 | N36: 81835932 | O36: 41091978 | P36: 312889501
I37: DIO | J37: 50982594 | K37: 54985753 | L37: 42216285 | M37: 80987512 | N37: 47400975 | O37: 47567549 | P37: 324140668
I38: DPR | J38: 522514884 | K38: 478946114 | L38: 4.0956632e+08 | M38: 5.4676366e+08 | N38: 530145136 | O38: 492863760 | P38: 2980799873
I39: DTC | J39: 1.0186675e+08 | K39: 1.5340891e+08 | L39: 2.1757082e+08 | M39: 1.6916078e+08 | N39: 2.5458868e+08 | O39: 2.1220769e+08 | P39: 1.1088036e+09
I40: SDG | O40: 444000 | P40: 444000
I41: SDO | J41: 3594914 | K41: 198466 | L41: 5612144 | M41: 3876374 | N41: 3868251 | O41: 4465971 | P41: 21616120
I42: Total general | J42: 3.7150929e+09 | K42: 4.1173616e+09 | L42: 3.6396797e+09 | M42: 2.7135035e+09 | N42: 6.583573e+09 | O42: 4.1235514e+09 | P42: 2.4892762e+10
I62: Salesforce | J62: Ene | K62: Feb | L62: Mar | M62: Abr | N62: May | O62: Jun | P62: Jul | Q62: Ago | R62: Sep | S62: Oct | T62: Nov | U62: Dic | V62: Total
I63: DEP | J63: =IFERROR(VLOOKUP($I63,$I$26:$V$42,MATCH(J$62,$I$26:$V$26,0),0),0) -> 27617921 | K63: =IFERROR(VLOOKUP($I63,$I$26:$V$42,MATCH(K$62,$I$26:$V$26,0),0),0) -> 1.7119322e+08 | L63: =IFERROR(VLOOKUP($I63,$I$26:$V$42,MATCH(L$62,$I$26:$V$26,0),0),0) -> 2.5230381e+08 | M63: =IFERROR(VLOOKUP($I63,$I$26:$V$42,MATCH(M$62,$I$26:$V$26,0),0),0) -> 1.2067604e+08 | N63: =IFERROR(VLOOKUP($I63,$I$26:$V$42,MATCH(N$62,$I$26:$V$26,0),0),0) -> 62156575 | O63: =IFERROR(VLOOKUP($I63,$I$26:$V$42,MATCH(O$62,$I$26:$V$26,0),0),0) -> 79488858 | P63: =IFERROR(VLOOKUP($I63,$I$26:$V$42,MATCH(P$62,$I$26:$V$26,0),0),0) -> 0 | Q63: =IFERROR(VLOOKUP($I63,$I$26:$V$42,MATCH(Q$62,$I$26:$V$26,0),0),0) -> 0 | ... U63: =IFERROR(VLOOKUP($I63,$I$26:$V$42,MATCH(U$62,$I$26:$V$26,0),0),0) -> 0 | V63: =SUM(J63:U63) -> 7.1343642e+08
I83: Diferencia | J83: Ene | K83: Feb | L83: Mar | M83: Abr | N83: May | O83: Jun | P83: Jul | Q83: Ago | R83: Sep | S83: Oct | T83: Nov | U83: Dic | V83: Total
I84: DEP | J84: =-IFERROR(VLOOKUP($I84,$I$62:$U$80,MATCH(J$83,$I$62:$U$62,0),0),0)+IFERROR(VLOOKUP($I84,$I$2:$U$23,MATCH(J$83,$I$2:$U$2,0),0),0) -> 73095921 | K84: =-IFERROR(VLOOKUP($I84,$I$62:$U$80,MATCH(K$83,$I$62:$U$62,0),0),0)+IFERROR(VLOOKUP($I84,$I$2:$U$23,MATCH(K$83,$I$2:$U$2,0),0),0) -> -67458916 | L84: =-IFERROR(VLOOKUP($I84,$I$62:$U$80,MATCH(L$83,$I$62:$U$62,0),0),0)+IFERROR(VLOOKUP($I84,$I$2:$U$23,MATCH(L$83,$I$2:$U$2,0),0),0) -> -1.0362581e+08 | M84: =-IFERROR(VLOOKUP($I84,$I$62:$U$80,MATCH(M$83,$I$62:$U$62,0),0),0)+IFERROR(VLOOKUP($I84,$I$2:$U$23,MATCH(M$83,$I$2:$U$2,0),0),0) -> 17159780 | N84: =-IFERROR(VLOOKUP($I84,$I$62:$U$80,MATCH(N$83,$I$62:$U$62,0),0),0)+IFERROR(VLOOKUP($I84,$I$2:$U$23,MATCH(N$83,$I$2:$U$2,0),0),0) -> 73185469 | O84: =-IFERROR(VLOOKUP($I84,$I$62:$U$80,MATCH(O$83,$I$62:$U$62,0),0),0)+IFERROR(VLOOKUP($I84,$I$2:$U$23,MATCH(O$83,$I$2:$U$2,0),0),0) -> 71883601 | P84: =-IFERROR(VLOOKUP($I84,$I$62:$U$80,MATCH(P$83,$I$62:$U$62,0),0),0)+IFERROR(VLOOKUP($I84,$I$2:$U$23,MATCH(P$83,$I$2:$U$2,0),0),0) -> 0 | Q84: =-IFERROR(VLOOKUP($I84,$I$62:$U$80,MATCH(Q$83,$I$62:$U$62,0),0),0)+IFERROR(VLOOKUP($I84,$I$2:$U$23,MATCH(Q$83,$I$2:$U$2,0),0),0) -> 0 | ... U84: =-IFERROR(VLOOKUP($I84,$I$62:$U$80,MATCH(U$83,$I$62:$U$62,0),0),0)+IFERROR(VLOOKUP($I84,$I$2:$U$23,MATCH(U$83,$I$2:$U$2,0),0),0) -> 0 | V84: =SUM(J84:U84) -> 64240048
I86: siglaDivision | J86: DEP | Z86: División | AA86: DEP
I88: EERR s/TI Fact | L88: fecha (mes) | Z88: Ingreso_Salesforce | AA88: Etiquetas de columna
A89: Facturación: Incluye Facturación externa y Traspasos de Servicios Internos | I89: Clasificación | J89: cuenta_contable_full | K89: Referencia Interna | L89: ene | M89: feb | N89: mar | O89: abr | P89: may | Q89: jun | R89: Total general | Z89: Etiquetas de fila | AA89: ene | AB89: feb | AC89: mar | AD89: abr | AE89: may | AF89: jun | AG89: Total general
A90: Traspasos: Corresponde solo a Traspasos de Facturación | I90: Ingresos | J90: 61010302 Asesorías y consultorías exterior | K90: PR.DEP.2025.0309 Diagnóstico estructural APS Hospital San José de Maipo | Q90: 28885247 | R90: 28885247 | Z90: PR.DEP.2023 | AA90: 1753929 | AB90: 1753929 | AC90: 1753929 | AD90: 1753929 | AE90: 1753929 | AF90: 1753929 | AG90: 10523574
A91: Valor en círculo: Representa diferncia entre Backlog y Facturación | I91: Ingresos | J91: 61010323 Análisis de materiales | Q91: 1571490 | R91: 1571490 | Z91: PR.DEP.2025.0005 Diagnóstico estructural Amunátegui No139 | AA91: 13622549 | AG91: 13622549
I92: Ingresos | J92: 61010323 Análisis de materiales | K92: PR.DEP.2024.0065 | L92: 117630460 | R92: 117630460 | Z92: PR.DEP.2025.0215 DIAGNÓSTICO DEL ESTADO DE CONSERVACIÓN MONUMENTO HISTÓRICO HOSPITAL EL SALVADOR - PROVIDENCIA | AB92: 77248242 | AC92: 77248242 | AG92: 154496484
I93: Ingresos | J93: 61010323 Análisis de materiales | K93: PR.DEP.2024.0176 | M93: -1120098 | R93: -1120098 | Z93: PR.DEP.2025.0251 Evaluación estructural edificio Instituto Traumatológico | AB93: 55205685 | AG93: 55205685
I94: Ingresos | J94: 61010323 Análisis de materiales | K94: PR.DEP.2025.0005 Diagnóstico estructural Amunátegui No139 | M94: 27434017 | N94: -13712118 | O94: 18449169 | P94: 0 | R94: 32171068 | Z94: PR.DEP.2025.0297A Ensayos carga transversal a baranda | AB94: 1588345.2 | AG94: 1588345.2
I95: Ingresos | J95: 61010323 Análisis de materiales | K95: PR.DEP.2025.0019 | L95: 40742214 | M95: 7601388 | N95: 3600149 | O95: 14944909 | P95: 3600149 | R95: 70488809 | Z95: PR.DEP.2025.0299 Ensayos carga transversal a baranda | AB95: 1886823 | AC95: 1886823 | AG95: 3773646
I96: Ingresos | J96: 61010323 Análisis de materiales | K96: PR.DEP.2025.0075 Ensayos de tracción a conectores mecánicos | L96: 0 | R96: 0 | Z96: PR.DEP.2025.0303 Evaluación estructural Losas Edificio Sede Universitaria para la provincia de Chiloé | AC96: 30129128 | AG96: 30129128
I97: Ingresos | J97: 61010323 Análisis de materiales | K97: PR.DEP.2025.0147 Diagnóstico estructural y monitoreo permanente de Apilador móvil No1 – Planta de P | L97: 19054 | N97: 31275750 | R97: 31294804 | Z97: PR.DEP.2025.0306 Ensayos de Compresión a Alzaprimas | AA97: 596898 | AG97: 596898
I98: Ingresos | J98: 61010323 Análisis de materiales | K98: PR.DEP.2025.0205 Extensión monitoreo continuo mediante instrumentación remota | L98: 143608 | R98: 143608 | Z98: PR.DEP.2025.0309 Diagnóstico estructural APS Hospital San José de Maipo | AC98: 28741603 | AE98: 28741603 | AG98: 57483206
I99: Ingresos | J99: 61010323 Análisis de materiales | K99: PR.DEP.2025.0228 Ensayos de impacto a vidrios | M99: 0 | R99: 0 | Z99: PR.DEP.2025.0316 EFE servicio de evaluación estructural de las estaciones de Curicó, San Javier, Linares, Parral y San C | AC99: 57985827 | AD99: 57985827 | AG99: 1.1597165e+08
I100: Ingresos | J100: 61010323 Análisis de materiales | K100: PR.DEP.2025.0241A Ensayo de tracción a probetas de hormigón | L100: 0 | M100: -888427 | R100: -888427 | Z100: PR.DEP.2025.0318A Ensayos carga transversal a baranda | AA100: 3173326 | AG100: 3173326
I101: Ingresos | J101: 61010323 Análisis de materiales | K101: PR.DEP.2025.0251 Evaluación estructural edificio Instituto Traumatológico | O101: 55379991 | R101: 55379991 | Z101: PR.DEP.2025.0320 EVALUACIÓN DE DAÑOS ESTRUCTURALES POR INCENDIO EN BODEGA – IQUIQUE, REGIÓN DE TARAPACÁ | AB101: 10723406 | AC101: 10723406 | AG101: 21446812
I102: Ingresos | J102: 61010323 Análisis de materiales | K102: PR.DEP.2025.0274 Cálculo Estructural de altillo en Edificio Ciencias Físicas - FCFM Universidad de | N102: 11449699 | R102: 11449699 | Z102: PR.DEP.2025.0321 Ensayos a sistema de fortificación de túnel | AE102: 3031874.2 | AG102: 3031874.2
I103: Ingresos | J103: 61010323 Análisis de materiales | K103: PR.DEP.2025.0278 Ensayos de impacto a vidrios | L103: -5848393 | N103: 5848393 | R103: 0 | Z103: PR.DEP.2025.0324 Ensayos mecánicos a paneles | AB103: 1429049 | AC103: 1429049 | AG103: 2858098
I104: Ingresos | J104: 61010323 Análisis de materiales | K104: PR.DEP.2025.0282 Ensayos de tracción confinada a anclajes químicos | L104: 2766488 | R104: 2766488 | Z104: PR.DEP.2025.0345 Revisión Memoria de Cálculo de proyecto de Racks - Cliente Evolog SpA. | AA104: 2781399 | AB104: 2781399 | AG104: 5562798
I105: Ingresos | J105: 61010323 Análisis de materiales | K105: PR.DEP.2025.0287 Ensayos de compresión a muestra de hormigón drenante | L105: 0 | R105: 0 | Z105: PR.DEP.2025.0349 Ensayos de tracción a barras autoperforantes | AA105: 3575170.8 | AG105: 3575170.8
I106: Ingresos | J106: 61010323 Análisis de materiales | K106: PR.DEP.2025.0296 Diseño | Q106: 6703455 | R106: 6703455 | Z106: PR.DEP.2026.0001 Evaluación de daños estructurales por incendio en centro de distribución World Logistic Park II San Ber | AB106: 12698557 | AC106: 12698557 | AG106: 25397114
I107: Ingresos | J107: 61010323 Análisis de materiales | K107: PR.DEP.2025.0297A Ensayos carga transversal a baranda | M107: 1588904 | R107: 1588904 | Z107: PR.DEP.2026.0003 Ensayos carga transversal a baranda | AA107: 1589987.2 | AG107: 1589987.2
I108: Ingresos | J108: 61010323 Análisis de materiales | K108: PR.DEP.2025.0299 Ensayos carga transversal a baranda | N108: 3386546 | R108: 3386546 | Z108: PR.DEP.2026.0006 Evaluación de daños estructurales por incendio en bodega Camilo Henríquez 3022 - Concepción | AC108: 13893534 | AG108: 13893534
I109: Ingresos | J109: 61010323 Análisis de materiales | K109: PR.DEP.2025.0303 Evaluación estructural Losas Edificio Sede Universitaria para la provincia de Chil | Q109: 15393530 | R109: 15393530 | Z109: PR.DEP.2026.0012 Ensayo Modulo Elasticidad de muestra hormigón | AA109: 524661.98 | AG109: 524661.98
I110: Ingresos | J110: 61010323 Análisis de materiales | K110: PR.DEP.2025.0305A Ensayos para determinación del módulo de elasticidad a muestra de hormigón | P110: -1588829 | R110: -1588829 | Z110: PR.DEP.2026.0013 Ensayos carga transversal a baranda | AC110: 3677390.8 | AG110: 3677390.8
I111: Ingresos | J111: 61010323 Análisis de materiales | K111: PR.DEP.2025.0306 Ensayos de Compresión a Alzaprimas | L111: 595862 | M111: 595862 | R111: 1191724 | Z111: PR.DEP.2026.0015 Ensayos a sistemas de fortificación de túnel | AB111: 2382825.6 | AG111: 2382825.6
I112: Ingresos | J112: 61010323 Análisis de materiales | K112: PR.DEP.2025.0309 Diagnóstico estructural APS Hospital San José de Maipo | O112: 28885247 | R112: 28885247 | Z112: PR.DEP.2026.0026 Ensayos carga transversal a panel | AF112: 5706856.4 | AG112: 5706856.4
I113: Ingresos | J113: 61010323 Análisis de materiales | K113: PR.DEP.2025.0318A Ensayos carga transversal a baranda | L113: 3173326 | R113: 3173326 | Z113: PR.DEP.2026.0027 Ensayos mecánicos a paneles | AB113: 1906957.4 | AG113: 1906957.4
I114: Ingresos | J114: 61010323 Análisis de materiales | K114: PR.DEP.2025.0320 EVALUACIÓN DE DAÑOS ESTRUCTURALES POR INCENDIO EN BODEGA – IQUIQUE, REGIÓN DE TARA | M114: 10740408 | N114: 10757264 | R114: 21497672 | Z114: PR.DEP.2026.0037 Ensayos carga transversal a baranda | AB114: 1587999 | AG114: 1587999
I115: Ingresos | J115: 61010323 Análisis de materiales | K115: PR.DEP.2025.0324 Ensayos mecánicos a paneles | M115: 1429049 | N115: 1429049 | R115: 2858098 | Z115: PR.DEP.2026.0040 Elaboración de especificaciones técnicas y seguimiento para reparación de pedestal PD1-2 - Turbogenera | AD115: 34130749 | AF115: 15730749 | AG115: 49861498
I116: Ingresos | J116: 61010323 Análisis de materiales | K116: PR.DEP.2025.0325 Ensayos mecánicos a paneles | L116: 0 | R116: 0 | Z116: PR.DEP.2026.0046 Ensayos de tracción a conectores mecánicos | AC116: 1195251.6 | AG116: 1195251.6
I117: Ingresos | J117: 61010323 Análisis de materiales | K117: PR.DEP.2025.0345 Revisión Memoria de Cálculo de proyecto de Racks - Cliente Evolog SpA. | M117: 5563159 | R117: 5563159 | Z117: PR.DEP.2026.0048 Ensayos de tracción in situ a barras | AC117: 2788920.4 | AG117: 2788920.4
I118: Ingresos | J118: 61010323 Análisis de materiales | K118: PR.DEP.2025.0349 Ensayos de tracción a barras autoperforantes | L118: 1788505 | R118: 1788505 | Z118: PR.DEP.2026.0051 Ensayos para determinación del módulo de elasticidad a muestra de hormigón | AC118: 1194570.3 | AG118: 1194570.3
I119: Ingresos | J119: 61010323 Análisis de materiales | K119: PR.DEP.2026.0001 Evaluación de daños estructurales por incendio en centro de distribución World Log | N119: 25397114 | R119: 25397114 | Z119: PR.DEP.2026.0053 Ensayos de tracción a barras autoperforantes | AC119: 2389480.8 | AG119: 2389480.8
I120: Ingresos | J120: 61010323 Análisis de materiales | K120: PR.DEP.2026.0003 Ensayos carga transversal a baranda | M120: 0 | R120: 0 | Z120: PR.DEP.2026.0054A Ensayos de tracción a barras autoperforantes | AD120: 3595282.2 | AG120: 3595282.2
I121: Ingresos | J121: 61010323 Análisis de materiales | K121: PR.DEP.2026.0006 Evaluación de daños estructurales por incendio en bodega Camilo Henríquez 3022 - C | O121: 13893534 | R121: 13893534 | Z121: PR.DEP.2026.0063 Ensayos de tracción y de contenido de zinc a alambre de malla de fortificación de túnel | AE121: 1212244.5 | AG121: 1212244.5
I122: Ingresos | J122: 61010323 Análisis de materiales | K122: PR.DEP.2026.0013 Ensayos carga transversal a baranda | O122: 2191000 | R122: 2191000 | Z122: PR.DEP.2026.0075A Ensayos de Flexión y Compresión a modulo plástico | AD122: 3207487.2 | AG122: 3207487.2
I123: Ingresos | J123: 61010323 Análisis de materiales | K123: PR.DEP.2026.0015 Ensayos a sistemas de fortificación de túnel | M123: 2386740 | R123: 2386740 | Z123: PR.DEP.2026.0076 Revisión proyecto de cálculo estructural de 3 tipologías de viviendas El Olivar, Quilpué – Valparaíso | AF123: 27490787 | AG123: 27490787
I124: Ingresos | J124: 61010323 Análisis de materiales | K124: PR.DEP.2026.0027 Ensayos mecánicos a paneles | O124: 1907501 | R124: 1907501 | Z124: PR.DEP.2026.0078 Ensayos carga transversal a baranda | AD124: 2201493.2 | AG124: 2201493.2
I125: Ingresos | J125: 61010323 Análisis de materiales | K125: PR.DEP.2026.0037 Ensayos carga transversal a baranda | M125: 1589811 | R125: 1589811 | Z125: PR.DEP.2026.0079 Revisión del diseño sísmico según NCh2369:2025 para 8 configuraciones de gabinetes | AD125: 8803053 | AE125: 8803053 | AG125: 17606106
I126: Ingresos | J126: 61010323 Análisis de materiales | K126: PR.DEP.2026.0046 Ensayos de tracción a conectores mecánicos | O126: 1195252 | R126: 1195252 | Z126: PR.DEP.2026.0086 Ensayos carga transversal a celosía | AD126: 2000030.5 | AG126: 2000030.5
I127: Ingresos | J127: 61010323 Análisis de materiales | K127: PR.DEP.2026.0048 Ensayos de tracción in situ a barras | N127: 2788920 | R127: 2788920 | Z127: PR.DEP.2026.0089 Ensayos de tracción a barras autoperforantes | AE127: 1691495 | AG127: 1691495
I128: Ingresos | J128: 61010323 Análisis de materiales | K128: PR.DEP.2026.0051 Ensayos para determinación del módulo de elasticidad a muestra de hormigón | N128: 1194570 | R128: 1194570 | Z128: PR.DEP.2026.0091 Ensayos carga transversal a baranda | AE128: 2020407.5 | AG128: 2020407.5
I129: Ingresos | J129: 61010323 Análisis de materiales | K129: PR.DEP.2026.0053 Ensayos de tracción a barras autoperforantes | N129: 2389822 | R129: 2389822 | Z129: PR.DEP.2026.0107 Ensayos de tracción a barras autoperforantes | AD129: 3601249.2 | AG129: 3601249.2
I130: Ingresos | J130: 61010323 Análisis de materiales | K130: PR.DEP.2026.0054A Ensayos de tracción a barras autoperforantes | O130: 3595880 | R130: 3595880 | Z130: PR.DEP.2026.0108 Ensayos de tracción a barras autoperforantes | AD130: 1800624.6 | AG130: 1800624.6
I131: Ingresos | J131: 61010323 Análisis de materiales | K131: PR.DEP.2026.0075A Ensayos de Flexión y Compresión a modulo plástico | O131: 1899002 | P131: 0 | R131: 1899002 | Z131: PR.DEP.2026.0110 Ensayos de carga transversal a prototipo de ventana | AE131: 2418435.6 | AG131: 2418435.6
I132: Ingresos | J132: 61010323 Análisis de materiales | K132: PR.DEP.2026.0076 Revisión proyecto de cálculo estructural de 3 tipologías de viviendas El Olivar, Q | Q132: 41714281 | R132: 41714281 | Z132: PR.DEP.2026.0111 Ensayos carga transversal a baranda | AF132: 1630638.8 | AG132: 1630638.8
I133: Ingresos | J133: 61010323 Análisis de materiales | K133: PR.DEP.2026.0078 Ensayos carga transversal a baranda | O133: 2205147 | R133: 2205147 | Z133: PR.DEP.2026.0112 Ensayos carga transversal a baranda | AE133: 1608004.8 | AG133: 1608004.8
I134: Ingresos | J134: 61010323 Análisis de materiales | K134: PR.DEP.2026.0079 Revisión del diseño sísmico según NCh2369:2025 para 8 configuraciones de gabinetes | O134: 8820590 | Q134: 8975685 | R134: 17796275 | Z134: PR.DEP.2026.0113 Ensayos carga transversal a barandas | AE134: 3221895.2 | AG134: 3221895.2
I135: Ingresos | J135: 61010323 Análisis de materiales | K135: PR.DEP.2026.0086 Ensayos carga transversal a celosía | P135: 2011339 | R135: 2011339 | Z135: PR.DEP.2026.0114 Medición de pilares mediante escáner láser en Centro de Distribución World Logistic Park II – San Berna | AF135: 4556250 | AG135: 4556250
I136: Ingresos | J136: 61010323 Análisis de materiales | K136: PR.DEP.2026.0089 Ensayos de tracción a barras autoperforantes | P136: 1697850 | R136: 1697850 | Z136: PR.DEP.2026.0116 Ensayo de la conexión, flexión y compresión excéntrica de columna CLT | AE136: 7653633 | AG136: 7653633
I137: Ingresos | J137: 61010323 Análisis de materiales | K137: PR.DEP.2026.0091 Ensayos carga transversal a baranda | P137: 1010204 | R137: 1010204 | Z137: PR.DEP.2026.0124 Ensayos carga transversal a baranda | AF137: 1630530.4 | AG137: 1630530.4
I138: Ingresos | J138: 61010323 Análisis de materiales | K138: PR.DEP.2026.0107 Ensayos de tracción a barras autoperforantes | P138: 4219613 | R138: 4219613 | Z138: PR.DEP.2026.0130 Ensayos de tracción de pernos autoperforantes | AF138: 1825959 | AG138: 1825959
I139: Ingresos | J139: 61010323 Análisis de materiales | K139: PR.DEP.2026.0108 Ensayos de tracción a barras autoperforantes | O139: 1802119 | R139: 1802119 | Z139: PR.DEP.2026.0131 Ensayos mecánicos a paneles | AF139: 8560853.7 | AG139: 8560853.7
I140: Ingresos | J140: 61010323 Análisis de materiales | K140: PR.DEP.2026.0110 Ensayos de carga transversal a prototipo de ventana | P140: 1208714 | R140: 1208714 | Z140: PR.DEP.2026.0134 Ensayos carga transversal a barandas | AF140: 3261495 | AG140: 3261495
I141: Ingresos | J141: 61010323 Análisis de materiales | K141: PR.DEP.2026.0114 Medición de pilares mediante escáner láser en Centro de Distribución World Logisti | P141: 4545917 | Q141: 4545917 | R141: 9091834 | Z141: PR.DEP.2026.0138 Ensayos a sistema de fortificación de túnel | AF141: 4891591 | AG141: 4891591
I142: Ingresos | J142: 61010323 Análisis de materiales | K142: PR.DEP.2026.0116 Ensayo de la conexión, flexión y compresión excéntrica de columna CLT | P142: 7653633 | R142: 7653633 | Z142: PR.DEP.2026.0154 Ensayos de tracción a conectores mecánicos | AF142: 2449218.6 | AG142: 2449218.6
I143: Ingresos | J143: 61010323 Análisis de materiales | K143: PR.DEP.2026.0131 Ensayos mecánicos a paneles | Q143: 4269455 | R143: 4269455 | Z143: PR.DEP.2026-0074 Ensayos carga transversal a baranda | AD143: 1596314 | AG143: 1596314
I144: Ingresos | J144: 61010323 Análisis de materiales | K144: PR.DEP.2026.0138 Ensayos a sistema de fortificación de túnel | Q144: 2440680 | R144: 2440680 | Z144: PR-DEP.2026.0038 MEDICIÓN DE VIBRACIONES Y VERTICALIDAD DE MURO COLINDANTE DURANTE CONSTRUCCIÓN PROYECTO ECUADOR – CORON | AC144: 4568100.2 | AG144: 4568100.2
I145: Ingresos | J145: 61010323 Análisis de materiales | K145: PR.DEP.2026-0074 Ensayos carga transversal a baranda | O145: 1600024 | R145: 1600024 | Z145: Total general | AA145: 27617921 | AB145: 1.7119322e+08 | AC145: 2.5230381e+08 | AD145: 1.2067604e+08 | AE145: 62156575 | AF145: 79488858 | AG145: 7.1343642e+08
I146: Ingresos | J146: 61010323 Análisis de materiales | K146: PR-DEP.2026.0038 MEDICIÓN DE VIBRACIONES Y VERTICALIDAD DE MURO COLINDANTE DURANTE CONSTRUCCIÓN PRO | N146: 4568752 | R146: 4568752
I147: Ingresos | J147: 62030986 Ventas internas electronicas | K147: PR.DEP.2025.0144 Proyecto de intervención estructural de edificio Bachillerato etapa 3 | L147: 27021058 | R147: 27021058
I148: Ingresos | J148: 62030986 Ventas internas electronicas | K148: PR.DEP.2026.0102 MEDICIÓN DE VIBRACIONES LOSA CASINO EDIFICIO FILOSOFÍA Campus Juan Gómez Millas – | Q148: 5676030 | R148: 5676030
I149: Ingresos | J149: 62030986 Ventas internas electronicas | K149: PR.DGI.2025-066 Edificio Bachillerato Campus JGM | N149: 14195206 | R149: 14195206
I150: Provisión | J150: 61010302 Asesorías y consultorías exterior | K150: PR.DEP.2025.0019 | Q150: 44114909 | R150: 44114909
I151: Provisión | J151: 61010302 Asesorías y consultorías exterior | K151: PR.DEP.2025.0144 Proyecto de intervención estructural de edificio Bachillerato etapa 3 | Q151: 27757811 | R151: 27757811
I152: Provisión | J152: 61010302 Asesorías y consultorías exterior | K152: PR.DEP.2025.0296 Diseño | Q152: 6703455 | R152: 6703455
I153: Provisión | J153: 61010302 Asesorías y consultorías exterior | K153: PR.DEP.2025.0303 Evaluación estructural Losas Edificio Sede Universitaria para la provincia de Chil | Q153: 15511718 | R153: 15511718
I154: Provisión | J154: 61010302 Asesorías y consultorías exterior | K154: PR.DEP.2026.0040 Elaboración de especificaciones técnicas y seguimiento para reparación de pedesta | Q154: 16000000 | R154: 16000000
I155: Provisión | J155: 61010323 Análisis de materiales | K155: PR.DEP.2025.0005 Diagnóstico estructural Amunátegui No139 | L155: 13700364 | M155: 18301081 | N155: 18327191 | R155: 50328636
I156: Provisión | J156: 61010323 Análisis de materiales | K156: PR.DEP.2025.0019 | L156: 7601388 | M156: 3600149 | N156: 14944909 | O156: 3600149 | P156: 3000000 | Q156: 3600149 | R156: 36346744
I157: Provisión | J157: 61010323 Análisis de materiales | K157: PR.DEP.2025.0147 Diagnóstico estructural y monitoreo permanente de Apilador móvil No1 – Planta de P | M157: 18738716 | R157: 18738716
I158: Provisión | J158: 61010323 Análisis de materiales | K158: PR.DEP.2025.0215 DIAGNÓSTICO DEL ESTADO DE CONSERVACIÓN MONUMENTO HISTÓRICO HOSPITAL EL SALVADOR - | O158: 106920333 | P158: 103194155 | Q158: 103725040 | R158: 313839528
I159: Provisión | J159: 61010323 Análisis de materiales | K159: PR.DEP.2025.0237 - Revisión del diseño de losa de subterráneo Hospital Melipilla | L159: 15487368 | M159: 15487368 | N159: 15487368 | Q159: 15922043 | R159: 62384147
I160: Provisión | J160: 61010323 Análisis de materiales | K160: PR.DEP.2025.0251 Evaluación estructural edificio Instituto Traumatológico | M160: 27602842 | N160: 55379990 | R160: 82982832
...

Sheet DES
I1: EERR s/TI Fact | J1: Etiquetas de columna
I2: Etiquetas de fila | J2: ene | K2: feb | L2: mar | M2: abr | N2: may | O2: jun | P2: jul | Q2: ago | R2: sep | S2: oct | T2: nov | U2: dic | V2: Total general
I3: DES | J3: 289140060 | K3: 257502742 | L3: 270815880 | M3: 267801174 | N3: 139450905 | O3: 319390498 | V3: 1544101259
I4: Total general | J4: 289140060 | K4: 257502742 | L4: 270815880 | M4: 267801174 | N4: 139450905 | O4: 319390498 | V4: 1544101259
I25: Ingreso_Salesforce | J25: Etiquetas de columna
I26: Etiquetas de fila | J26: ene | K26: feb | L26: mar | M26: abr | N26: may | O26: jun | P26: Total general
I27: DAC | J27: -169531556 | K27: 229661282 | L27: 132474079 | M27: 254268998 | N27: 4.6957042e+08 | O27: 3.6332564e+08 | P27: 1.2797689e+09
I28: DCO | J28: 842635563 | K28: 592333115 | L28: 354793861 | M28: 4.2707473e+08 | N28: 892309408 | O28: 486320169 | P28: 3.5954668e+09
I29: DDA | J29: 181228409 | K29: 129936364 | L29: 134027273 | M29: 157001893 | N29: 40429545 | O29: 130045454 | P29: 772668938
I30: DEP | J30: 27617921 | K30: 1.7119322e+08 | L30: 2.5230381e+08 | M30: 1.2067604e+08 | N30: 62156575 | O30: 79488858 | P30: 7.1343642e+08
I31: DES | J31: 289140060 | K31: 2.5750274e+08 | L31: 270815880 | M31: 267801174 | N31: 1.3945091e+08 | O31: 3.2742769e+08 | P31: 1.5521385e+09
I32: DGI | J32: 1271029488 | K32: 1406463891 | L32: 1321970041 | M32: -137844577 | N32: 3434507158 | O32: 1229933471 | P32: 8526059472
I33: DGL | J33: 286168992 | K33: 338984671 | L33: 230154271 | M33: 451087812 | N33: 341520986 | O33: 436919745 | P33: 2084836477
I34: DHC | J34: 73086361 | K34: 73231017 | L34: 80734296 | M34: 85650722 | N34: 83985839 | O34: 146170041 | P34: 542858276
I35: DHI | J35: 218731800 | K35: 172601844 | L35: 161539048 | M35: 196879192 | N35: 201803161 | O35: 125279423 | P35: 1076834468
I36: DIC | J36: 16026670 | K36: 57914174 | L36: 25901536 | M36: 90119211 | N36: 81835932 | O36: 41091978 | P36: 312889501
I37: DIO | J37: 50982594 | K37: 54985753 | L37: 42216285 | M37: 80987512 | N37: 47400975 | O37: 47567549 | P37: 324140668
I38: DPR | J38: 522514884 | K38: 478946114 | L38: 4.0956632e+08 | M38: 5.4676366e+08 | N38: 530145136 | O38: 492863760 | P38: 2980799873
I39: DTC | J39: 1.0186675e+08 | K39: 1.5340891e+08 | L39: 2.1757082e+08 | M39: 1.6916078e+08 | N39: 2.5458868e+08 | O39: 2.1220769e+08 | P39: 1.1088036e+09
I40: SDG | O40: 444000 | P40: 444000
I41: SDO | J41: 3594914 | K41: 198466 | L41: 5612144 | M41: 3876374 | N41: 3868251 | O41: 4465971 | P41: 21616120
I42: Total general | J42: 3.7150929e+09 | K42: 4.1173616e+09 | L42: 3.6396797e+09 | M42: 2.7135035e+09 | N42: 6.583573e+09 | O42: 4.1235514e+09 | P42: 2.4892762e+10
I62: Salesforce | J62: Ene | K62: Feb | L62: Mar | M62: Abr | N62: May | O62: Jun | P62: Jul | Q62: Ago | R62: Sep | S62: Oct | T62: Nov | U62: Dic | V62: Total
I63: DES | J63: =IFERROR(VLOOKUP($I63,$I$26:$V$42,MATCH(J$62,$I$26:$V$26,0),0),0) -> 289140060 | K63: =IFERROR(VLOOKUP($I63,$I$26:$V$42,MATCH(K$62,$I$26:$V$26,0),0),0) -> 2.5750274e+08 | L63: =IFERROR(VLOOKUP($I63,$I$26:$V$42,MATCH(L$62,$I$26:$V$26,0),0),0) -> 270815880 | M63: =IFERROR(VLOOKUP($I63,$I$26:$V$42,MATCH(M$62,$I$26:$V$26,0),0),0) -> 267801174 | N63: =IFERROR(VLOOKUP($I63,$I$26:$V$42,MATCH(N$62,$I$26:$V$26,0),0),0) -> 1.3945091e+08 | O63: =IFERROR(VLOOKUP($I63,$I$26:$V$42,MATCH(O$62,$I$26:$V$26,0),0),0) -> 3.2742769e+08 | P63: =IFERROR(VLOOKUP($I63,$I$26:$V$42,MATCH(P$62,$I$26:$V$26,0),0),0) -> 0 | Q63: =IFERROR(VLOOKUP($I63,$I$26:$V$42,MATCH(Q$62,$I$26:$V$26,0),0),0) -> 0 | ... U63: =IFERROR(VLOOKUP($I63,$I$26:$V$42,MATCH(U$62,$I$26:$V$26,0),0),0) -> 0 | V63: =SUM(J63:U63) -> 1.5521385e+09
I83: Diferencia | J83: Ene | K83: Feb | L83: Mar | M83: Abr | N83: May | O83: Jun | P83: Jul | Q83: Ago | R83: Sep | S83: Oct | T83: Nov | U83: Dic | V83: Total
I84: DES | J84: =-IFERROR(VLOOKUP($I84,$I$62:$U$80,MATCH(J$83,$I$62:$U$62,0),0),0)+IFERROR(VLOOKUP($I84,$I$2:$U$23,MATCH(J$83,$I$2:$U$2,0),0),0) -> 0 | K84: =-IFERROR(VLOOKUP($I84,$I$62:$U$80,MATCH(K$83,$I$62:$U$62,0),0),0)+IFERROR(VLOOKUP($I84,$I$2:$U$23,MATCH(K$83,$I$2:$U$2,0),0),0) -> 0 | L84: =-IFERROR(VLOOKUP($I84,$I$62:$U$80,MATCH(L$83,$I$62:$U$62,0),0),0)+IFERROR(VLOOKUP($I84,$I$2:$U$23,MATCH(L$83,$I$2:$U$2,0),0),0) -> 0 | M84: =-IFERROR(VLOOKUP($I84,$I$62:$U$80,MATCH(M$83,$I$62:$U$62,0),0),0)+IFERROR(VLOOKUP($I84,$I$2:$U$23,MATCH(M$83,$I$2:$U$2,0),0),0) -> 0 | N84: =-IFERROR(VLOOKUP($I84,$I$62:$U$80,MATCH(N$83,$I$62:$U$62,0),0),0)+IFERROR(VLOOKUP($I84,$I$2:$U$23,MATCH(N$83,$I$2:$U$2,0),0),0) -> -0.39999998 | O84: =-IFERROR(VLOOKUP($I84,$I$62:$U$80,MATCH(O$83,$I$62:$U$62,0),0),0)+IFERROR(VLOOKUP($I84,$I$2:$U$23,MATCH(O$83,$I$2:$U$2,0),0),0) -> -8037196.8 | P84: =-IFERROR(VLOOKUP($I84,$I$62:$U$80,MATCH(P$83,$I$62:$U$62,0),0),0)+IFERROR(VLOOKUP($I84,$I$2:$U$23,MATCH(P$83,$I$2:$U$2,0),0),0) -> 0 | Q84: =-IFERROR(VLOOKUP($I84,$I$62:$U$80,MATCH(Q$83,$I$62:$U$62,0),0),0)+IFERROR(VLOOKUP($I84,$I$2:$U$23,MATCH(Q$83,$I$2:$U$2,0),0),0) -> 0 | ... U84: =-IFERROR(VLOOKUP($I84,$I$62:$U$80,MATCH(U$83,$I$62:$U$62,0),0),0)+IFERROR(VLOOKUP($I84,$I$2:$U$23,MATCH(U$83,$I$2:$U$2,0),0),0) -> 0 | V84: =SUM(J84:U84) -> -8037197.2
I86: siglaDivision | J86: DES | Z86: División | AA86: DES
I88: EERR s/TI Fact | L88: fecha (mes) | Z88: Ingreso_Salesforce | AA88: Etiquetas de columna
A89: Facturación: Incluye Facturación externa y Traspasos de Servicios Internos | I89: Clasificación | J89: cuenta_contable_full | K89: Referencia Interna | L89: ene | M89: feb | N89: mar | O89: abr | P89: may | Q89: jun | R89: Total general | Z89: Etiquetas de fila | AA89: ene | AB89: feb | AC89: mar | AD89: abr | AE89: may | AF89: jun | AG89: Total general
A90: Traspasos: Corresponde solo a Traspasos de Facturación | I90: Ingresos | J90: 61010302 Asesorías y consultorías exterior | K90: PR.DES.2024-88 | P90: 74433497 | Q90: 84300076 | R90: 158733573 | Z90: Antofagasta (DEPTOS) PR.DES.2022-29 | AA90: 0 | AB90: 0 | AC90: 0 | AD90: 0 | AG90: 0
A91: Valor en círculo: Representa diferncia entre Backlog y Facturación | I91: Ingresos | J91: 61010302 Asesorías y consultorías exterior | K91: PR.DES.2025-195 | Q91: 68541504 | R91: 68541504 | Z91: Antofagasta (Hotel) PR.DES.2022-29 | AA91: 0 | AC91: 0 | AG91: 0
I92: Ingresos | J92: 61010302 Asesorías y consultorías exterior | K92: PR.DES.2025-48 (+) | L92: -298139711 | R92: -298139711 | Z92: Bellavista PR.DES.2022-29 | AA92: 0 | AB92: 0 | AC92: 0 | AD92: 0 | AE92: 0 | AF92: 0 | AG92: 0
I93: Ingresos | J93: 61010323 Análisis de materiales | L93: 18 | R93: 18 | Z93: Briones Luco PR.DES.2022-29 | AA93: 0 | AB93: 0 | AC93: 0 | AD93: 0 | AF93: 0 | AG93: 0
I94: Ingresos | J94: 61010323 Análisis de materiales | K94: Centro Gabriela Mistral Etapa 2 | N94: 12600000 | R94: 12600000 | Z94: Carlos Valdovinos PR.DES.2022-29 | AA94: 0 | AB94: 0 | AC94: 0 | AD94: 0 | AE94: 0 | AF94: 0 | AG94: 0
I95: Ingresos | J95: 61010323 Análisis de materiales | K95: PR,DES.2026-51 | O95: 1397238 | R95: 1397238 | Z95: Eglo PR.DES.2022-29 | AA95: 0 | AB95: 0 | AC95: 0 | AE95: 0 | AF95: 0 | AG95: 0
I96: Ingresos | J96: 61010323 Análisis de materiales | K96: PR.DES.2021-190 | M96: 1588653 | R96: 1588653 | Z96: Esmax La Florida PR.DES.2022-29 | AC96: 27436537 | AG96: 27436537
I97: Ingresos | J97: 61010323 Análisis de materiales | K97: PR.DES.2022-231 | L97: 1588653 | Q97: 816406 | R97: 2405059 | Z97: Esmax La Florida PR.DES.2022-29 (-) | AC97: -27436537 | AG97: -27436537
I98: Ingresos | J98: 61010323 Análisis de materiales | K98: PR.DES.2023-167 | L98: 397163 | M98: 397906 | Q98: 816406 | R98: 1611475 | Z98: Grajales PR.DES.2022-29 | AA98: 0 | AB98: 0 | AC98: 0 | AD98: 0 | AG98: 0
I99: Ingresos | J99: 61010323 Análisis de materiales | K99: PR.DES.2023-184 | N99: 295207 | R99: 295207 | Z99: Jose Ureta PR.DES.2022-29 | AA99: 0 | AB99: 0 | AC99: 0 | AD99: 0 | AE99: 0 | AF99: 0 | AG99: 0
I100: Ingresos | J100: 61010323 Análisis de materiales | K100: PR.DES.2023-202 | L100: 1164348 | M100: 1889627 | Q100: 1889627 | R100: 4943602 | Z100: Ñuble PR.DES.2022-29 | AA100: 0 | AB100: 0 | AC100: 0 | AD100: 0 | AE100: 0 | AF100: 0 | AG100: 0
I101: Ingresos | J101: 61010323 Análisis de materiales | K101: PR.DES.2023-228 | L101: 292706 | N101: 292706 | R101: 585412 | Z101: Pedro de Valdivia PR.DES.2022-29 | AA101: 0 | AB101: 0 | AC101: 0 | AE101: 0 | AF101: 0 | AG101: 0
I102: Ingresos | J102: 61010323 Análisis de materiales | K102: PR.DES.2023-36 (+) | N102: 15903498 | P102: 0 | R102: 15903498 | Z102: PR,DES.2026-51 | AD102: 1436206 | AG102: 1436206
I103: Ingresos | J103: 61010323 Análisis de materiales | K103: PR.DES.2023-85 | L103: 1191490 | R103: 1191490 | Z103: PR.DES.2018-VIS | AA103: 43259095 | AB103: 11205034 | AC103: 34425800 | AD103: 46572710 | AE103: -110402142 | AG103: 25060497
I104: Ingresos | J104: 61010323 Análisis de materiales | K104: PR.DES.2024-101 | L104: 429340 | O104: 4254560 | P104: 855260 | R104: 5539160 | Z104: PR.DES.2019-216 | AA104: 0 | AB104: 0 | AC104: 0 | AD104: 0 | AE104: 0 | AG104: 0
I105: Ingresos | J105: 61010323 Análisis de materiales | K105: PR.DES.2024-101 (+) | L105: 429340 | R105: 429340 | Z105: PR.DES.2021-190 | AE105: 1218303 | AG105: 1218303
I106: Ingresos | J106: 61010323 Análisis de materiales | K106: PR.DES.2024-141 | P106: 564028 | R106: 564028 | Z106: PR.DES.2021-196 | AF106: 3864393 | AG106: 3864393
I107: Ingresos | J107: 61010323 Análisis de materiales | K107: PR.DES.2024-149 | L107: 1191490 | N107: 398417 | P107: 406301 | R107: 1996208 | Z107: PR.DES.2021-251 | AF107: 1408459 | AG107: 1408459
I108: Ingresos | J108: 61010323 Análisis de materiales | K108: PR.DES.2024-150 | L108: 794326 | R108: 794326 | Z108: PR.DES.2021-265 | AC108: 1560215 | AG108: 1560215
I109: Ingresos | J109: 61010323 Análisis de materiales | K109: PR.DES.2024-155 | L109: 1804890 | N109: 902445 | O109: 902445 | P109: 601630 | Q109: 1203260 | R109: 5414670 | Z109: PR.DES.2021-266 | AF109: 1105118 | AG109: 1105118
I110: Ingresos | J110: 61010323 Análisis de materiales | K110: PR.DES.2024-156 | L110: 1222060 | M110: 488824 | N110: 733236 | O110: 244412 | P110: 488824 | R110: 3177356 | Z110: PR.DES.2021-90 | AA110: 446724 | AG110: 446724
I111: Ingresos | J111: 61010323 Análisis de materiales | K111: PR.DES.2024-158 | N111: 1593669 | R111: 1593669 | Z111: PR.DES.2022-231 | AA111: 1588652.8 | AG111: 1588652.8
I112: Ingresos | J112: 61010323 Análisis de materiales | K112: PR.DES.2024-174 | L112: 750459 | M112: 250153 | N112: 500306 | P112: 1593000 | Q112: 1843153 | R112: 4937071 | Z112: PR.DES.2022-45 | AF112: 1406285 | AG112: 1406285
I113: Ingresos | J113: 61010323 Análisis de materiales | K113: PR.DES.2024-195 | L113: 2762427 | N113: 1841619 | P113: 613872 | R113: 5217918 | Z113: PR.DES.2023-167 | AA113: 397163 | AB113: 399706.3 | AG113: 796869.3
I114: Ingresos | J114: 61010323 Análisis de materiales | K114: PR.DES.2024-201 | L114: 2148554 | N114: 920809 | O114: 920809 | P114: 1227745 | Q114: 1995087 | R114: 7213004 | Z114: PR.DES.2023-184 | AC114: 295207 | AG114: 295207
I115: Ingresos | J115: 61010323 Análisis de materiales | K115: PR.DES.2024-51 | L115: 298982 | O115: 2242363 | Q115: 1943381 | R115: 4484726 | Z115: PR.DES.2023-202 | AA115: 1163348 | AB115: 1889627 | AG115: 3052975
I116: Ingresos | J116: 61010323 Análisis de materiales | K116: PR.DES.2024-71 | L116: 1191490 | M116: 399706 | P116: 812202 | R116: 2403398 | Z116: PR.DES.2023-216 | AA116: 33670818 | AB116: 16835409 | AC116: 19252362 | AD116: 55340133 | AE116: 57757085 | AF116: 43338630 | AG116: 226194437
I117: Ingresos | J117: 61010323 Análisis de materiales | K117: PR.DES.2024-82 | L117: 5792771 | R117: 5792771 | Z117: PR.DES.2023-228 | AA117: 292706 | AC117: 292706 | AG117: 585412
I118: Ingresos | J118: 61010323 Análisis de materiales | K118: PR.DES.2024-83 | L118: 4484688 | M118: 298982 | N118: 1195928 | O118: 597964 | Q118: 298982 | R118: 6876544 | Z118: PR.DES.2023-58 | AA118: 711670 | AG118: 711670
I119: Ingresos | J119: 61010323 Análisis de materiales | K119: PR.DES.2024-88 | M119: 158680257 | N119: 74075431 | P119: 82915214 | R119: 315670902 | Z119: PR.DES.2023-85 | AA119: 1191489.6 | AG119: 1191489.6
I120: Ingresos | J120: 61010323 Análisis de materiales | K120: PR.DES.2024-94 | L120: 1810044 | M120: 603348 | N120: 1206696 | O120: 905022 | P120: 905022 | Q120: 2263140 | R120: 7693272 | Z120: PR.DES.2024-101 | AA120: 858680 | AG120: 858680
I121: Ingresos | J121: 61010323 Análisis de materiales | K121: PR.DES.2024-95 | L121: 1222060 | M121: 733236 | N121: 2444121 | O121: 1955297 | Q121: 244412 | R121: 6599126 | Z121: PR.DES.2024-101 (+) | AA121: 1 | AG121: 1
I122: Ingresos | J122: 61010323 Análisis de materiales | K122: PR.DES.2024-96 | L122: 2444121 | M122: 244412 | Q122: 1955297 | R122: 4643830 | Z122: PR.DES.2024-107 | AE122: 905022 | AG122: 905022
I123: Ingresos | J123: 61010323 Análisis de materiales | K123: PR.DES.2024-97 | L123: 1692089 | M123: 2820150 | N123: 1692090 | O123: 1128061 | P123: 1692092 | Q123: 1692092 | R123: 10716574 | Z123: PR.DES.2024-121 | AD123: 563593.25 | AG123: 563593.25
I124: Ingresos | J124: 61010323 Análisis de materiales | K124: PR.DES.2025-100 | M124: 65761692 | R124: 65761692 | Z124: PR.DES.2024-129 | AD124: 300563.68 | AF124: 300563.68 | AG124: 601127.36
I125: Ingresos | J125: 61010323 Análisis de materiales | K125: PR.DES.2025-11 ASESORIA A LA INSPECCION TECNICA DE OBRAS (ATO) Y EQUIPO ESPECIALIDADES HABILITACION | M125: 8280000 | N125: 8280000 | O125: 8280000 | P125: 0 | R125: 24840000 | Z125: PR.DES.2024-141 | AA125: 0 | AE125: 564028 | AG125: 564028
I126: Ingresos | J126: 61010323 Análisis de materiales | K126: PR.DES.2025-110 | L126: 627688 | M126: 3373822 | N126: 627688 | O126: 627688 | P126: 627688 | R126: 5884574 | Z126: PR.DES.2024-149 | AA126: 1191490 | AC126: 398417 | AE126: 406101.1 | AF126: 2071241 | AG126: 4067249.1
I127: Ingresos | J127: 61010323 Análisis de materiales | K127: PR.DES.2025-111 | L127: 5099960 | M127: 2667673 | N127: 2039984 | O127: 2039984 | P127: 2039984 | R127: 13887585 | Z127: PR.DES.2024-150 | AA127: 794326 | AF127: 1804106 | AG127: 2598432
I128: Ingresos | J128: 61010323 Análisis de materiales | K128: PR.DES.2025-114 | L128: 1254215 | M128: 3370702 | N128: 940662 | O128: 940661 | P128: 627107 | Q128: 627107 | R128: 7760454 | Z128: PR.DES.2024-154 | AA128: 0 | AB128: 0 | AC128: 9785961 | AG128: 9785961
I129: Ingresos | J129: 61010323 Análisis de materiales | K129: PR.DES.2025-12 | P129: 20481811 | R129: 20481811 | Z129: PR.DES.2024-155 | AA129: 1804890 | AB129: 0 | AC129: 902445 | AD129: 902445 | AE129: 601630 | AF129: 0 | AG129: 4211410
I130: Ingresos | J130: 61010323 Análisis de materiales | K130: PR.DES.2025-122 | P130: 406101 | R130: 406101 | Z130: PR.DES.2024-156 | AA130: 1222060 | AB130: 488824 | AC130: 733236 | AD130: 244412 | AE130: 488824 | AF130: 0 | AG130: 3177356
I131: Ingresos | J131: 61010323 Análisis de materiales | K131: PR.DES.2025-127 | L131: 1254216 | M131: 5526394 | N131: 940662 | O131: 627108 | P131: 1254216 | Q131: 940662 | R131: 10543258 | Z131: PR.DES.2024-174 | AA131: 750459 | AB131: 250153 | AC131: 500306 | AE131: 1593000 | AG131: 3093918
I132: Ingresos | J132: 61010323 Análisis de materiales | K132: PR.DES.2025-128 | L132: 2351653 | M132: 7054959 | N132: 3527478 | P132: 3527478 | Q132: 1763739 | R132: 18225307 | Z132: PR.DES.2024-186 | AB132: 3984386 | AG132: 3984386
I133: Ingresos | J133: 61010323 Análisis de materiales | K133: PR.DES.2025-136 | M133: 2775052 | N133: 2775052 | R133: 5550104 | Z133: PR.DES.2024-190 | AF133: 569259.25 | AG133: 569259.25
I134: Ingresos | J134: 61010323 Análisis de materiales | K134: PR.DES.2025-14 | O134: 1459484 | P134: 1709639 | Q134: 750462 | R134: 3919585 | Z134: PR.DES.2024-195 | AA134: 2762427 | AB134: 0 | AC134: 1841619 | AD134: 0 | AE134: 613872 | AF134: 0 | AG134: 5217918
I135: Ingresos | J135: 61010323 Análisis de materiales | K135: PR.DES.2025-145 AITE PROYECTO “REPOSICIÓN CESFAM RURAL CURACO DE VÉLEZ | N135: 8387647 | R135: 8387647 | Z135: PR.DES.2024-199 | AA135: 18983557 | AG135: 18983557
I136: Ingresos | J136: 61010323 Análisis de materiales | K136: PR.DES.2025-15 | L136: 2148557 | N136: 920810 | O136: 920810 | P136: 613873 | Q136: 1227748 | R136: 5831798 | Z136: PR.DES.2024-199 (-) | AA136: -18983557 | AG136: -18983557
I137: Ingresos | J137: 61010323 Análisis de materiales | K137: PR.DES.2025-157 | N137: 3984172 | R137: 3984172 | Z137: PR.DES.2024-201 | AA137: 2148554 | AB137: 0 | AC137: 920808 | AD137: 920808 | AE137: 1227744 | AF137: 0 | AG137: 5217914
I138: Ingresos | J138: 61010323 Análisis de materiales | K138: PR.DES.2025-158 | M138: 1986714 | N138: 1986714 | R138: 3973428 | Z138: PR.DES.2024-228 | AB138: 3494476 | AG138: 3494476
I139: Ingresos | J139: 61010323 Análisis de materiales | K139: PR.DES.2025-159 | M139: 2781400 | N139: 2781400 | R139: 5562800 | Z139: PR.DES.2024-240 | AF139: 576324.75 | AG139: 576324.75
I140: Ingresos | J140: 61010323 Análisis de materiales | K140: PR.DES.2025-164 | N140: 20000000 | O140: -20000000 | R140: 0 | Z140: PR.DES.2024-32 | AC140: 1095723 | AG140: 1095723
I141: Ingresos | J141: 61010323 Análisis de materiales | K141: PR.DES.2025-179 | L141: 1506456 | R141: 1506456 | Z141: PR.DES.2024-51 | AA141: 1254215 | AB141: 0 | AD141: 2242363 | AG141: 3496578
I142: Ingresos | J142: 61010323 Análisis de materiales | K142: PR.DES.2025-181 | M142: 2576833 | N142: 2576833 | R142: 5153666 | Z142: PR.DES.2024-54 | AA142: 13904703 | AG142: 13904703
I143: Ingresos | J143: 61010323 Análisis de materiales | K143: PR.DES.2025-182 | M143: 1982179 | N143: 1982179 | R143: 3964358 | Z143: PR.DES.2024-71 | AB143: 399706.3 | AE143: 812202.2 | AG143: 1211908.5
I144: Ingresos | J144: 61010323 Análisis de materiales | K144: PR.DES.2025-183 | M144: 2061466 | N144: 2061466 | R144: 4122932 | Z144: PR.DES.2024-82 | AA144: 5792771 | AB144: 0 | AC144: 0 | AD144: 0 | AG144: 5792771
I145: Ingresos | J145: 61010323 Análisis de materiales | K145: PR.DES.2025-184 | M145: 2775051 | N145: 2775051 | P145: 634297 | Q145: 634297 | R145: 6818696 | Z145: PR.DES.2024-83 | AA145: 4484688 | AB145: 298982 | AC145: 1195928 | AD145: 597964 | AE145: 0 | AG145: 6577562
I146: Ingresos | J146: 61010323 Análisis de materiales | K146: PR.DES.2025-186 | M146: 2576833 | N146: 2576833 | R146: 5153666 | Z146: PR.DES.2024-88 | AA146: 68696786 | AB146: 76006175 | AC146: 64881707 | AD146: 72243703 | AE146: 77980646 | AF146: 76006175 | AG146: 435815192
I147: Ingresos | J147: 61010323 Análisis de materiales | K147: PR.DES.2025-195 | N147: 127886650 | O147: 67243660 | P147: 67713670 | R147: 262843980 | Z147: PR.DES.2024-9 | AF147: 713904 | AG147: 713904
I148: Ingresos | J148: 61010323 Análisis de materiales | K148: PR.DES.2025-201 | M148: 2775052 | N148: 3409350 | O148: 634298 | P148: 634298 | Q148: 951447 | R148: 8404445 | Z148: PR.DES.2024-94 | AA148: 1810044 | AB148: 603348 | AC148: 1206696 | AD148: 905022 | AE148: 905022 | AF148: 0 | AG148: 5430132
I149: Ingresos | J149: 61010323 Análisis de materiales | K149: PR.DES.2025-202 | L149: 1271415 | R149: 1271415 | Z149: PR.DES.2024-95 | AA149: 1222060 | AB149: 733236 | AC149: 2444121 | AD149: 1955297 | AE149: 0 | AF149: 0 | AG149: 6354714
I150: Ingresos | J150: 61010323 Análisis de materiales | K150: PR.DES.2025-203 | L150: 1271415 | R150: 1271415 | Z150: PR.DES.2024-96 | AA150: 2444121 | AB150: 244412 | AC150: 0 | AF150: 2041267 | AG150: 4729800
I151: Ingresos | J151: 61010323 Análisis de materiales | K151: PR.DES.2025-25 (+) | M151: -5388206 | N151: 5388206 | R151: 0 | Z151: PR.DES.2024-97 | AA151: 3384180 | AB151: 1128060 | AC151: 1692090 | AD151: 1128060 | AE151: 1692090 | AF151: 0 | AG151: 9024480
I152: Ingresos | J152: 61010323 Análisis de materiales | K152: PR.DES.2025-26 (+) | M152: 8509908 | R152: 8509908 | Z152: PR.DES.2025-103 | AD152: 13725180 | AG152: 13725180
I153: Ingresos | J153: 61010323 Análisis de materiales | K153: PR.DES.2025-34 | L153: 1534685 | M153: 2685694 | N153: 613874 | O153: 920811 | P153: 1227746 | Q153: 920810 | R153: 7903620 | Z153: PR.DES.2025-108 | AF153: 4736909 | AG153: 4736909
I154: Ingresos | J154: 61010323 Análisis de materiales | K154: PR.DES.2025-48 (+) | L154: 15550724 | Q154: 15550724 | R154: 31101448 | Z154: PR.DES.2025-11 ASESORIA A LA INSPECCION TECNICA DE OBRAS (ATO) Y EQUIPO ESPECIALIDADES HABILITACION CENTRO CULTURAL, COM | AA154: 7804277 | AB154: 8280000 | AC154: 8280000 | AD154: 0 | AF154: 9861536 | AG154: 34225813
I155: Ingresos | J155: 61010323 Análisis de materiales | K155: PR.DES.2025-50 | L155: 1254216 | M155: 3100683 | N155: 940662 | O155: 1254216 | P155: 1254216 | Q155: 940662 | R155: 8744655 | Z155: PR.DES.2025-110 | AA155: 627768 | AB155: 3373822 | AC155: 627688 | AD155: 627688 | AE155: 627688 | AF155: 0 | AG155: 5884654
I156: Ingresos | J156: 61010323 Análisis de materiales | K156: PR.DES.2025-51 | L156: 1254214 | M156: 627108 | N156: 4232975 | R156: 6114297 | Z156: PR.DES.2025-111 | AA156: 5099960 | AB156: 2667673 | AC156: 2039984 | AD156: 2039984 | AE156: 2039984 | AF156: 0 | AG156: 13887585
I157: Ingresos | J157: 61010323 Análisis de materiales | K157: PR.DES.2025-54 | L157: 43832095 | R157: 43832095 | Z157: PR.DES.2025-114 | AA157: 1254215 | AB157: 3370702 | AC157: 940662 | AD157: 940662 | AE157: 627108 | AF157: 0 | AG157: 7133349
I158: Ingresos | J158: 61010323 Análisis de materiales | K158: PR.DES.2025-55 | M158: 979855 | R158: 979855 | Z158: PR.DES.2025-12 | AA158: 0 | AF158: 25784070 | AG158: 25784070
I159: Ingresos | J159: 61010323 Análisis de materiales | K159: PR.DES.2025-56 | L159: 1254196 | M159: 3370683 | N159: 1254376 | O159: 940632 | P159: 1567970 | R159: 8387857 | Z159: PR.DES.2025-122 | AE159: 406101.1 | AF159: 3303587 | AG159: 3709688.1
I160: Ingresos | J160: 61010323 Análisis de materiales | K160: PR.DES.2025-75 | L160: 3177306 | R160: 3177306 | Z160: PR.DES.2025-123 | AF160: 3532499 | AG160: 3532499
...

Sheet DGI
I1: EERR s/TI Fact | J1: Etiquetas de columna
I2: Etiquetas de fila | J2: ene | K2: feb | L2: mar | M2: abr | N2: may | O2: jun | P2: jul | Q2: ago | R2: sep | S2: oct | T2: nov | U2: dic | V2: Total general
I3: DGI | J3: 1271029488 | K3: 1406463891 | L3: 1338014616 | M3: -14883670 | N3: 2187487154 | O3: 1585394898 | V3: 7773506377
I4: Total general | J4: 1271029488 | K4: 1406463891 | L4: 1338014616 | M4: -14883670 | N4: 2187487154 | O4: 1585394898 | V4: 7773506377
I25: Ingreso_Salesforce | J25: Etiquetas de columna
I26: Etiquetas de fila | J26: ene | K26: feb | L26: mar | M26: abr | N26: may | O26: jun | P26: Total general
I27: DAC | J27: -169531556 | K27: 229661282 | L27: 132474079 | M27: 254268998 | N27: 4.6957042e+08 | O27: 3.6332564e+08 | P27: 1.2797689e+09
I28: DCO | J28: 842635563 | K28: 592333115 | L28: 354793861 | M28: 4.2707473e+08 | N28: 892309408 | O28: 486320169 | P28: 3.5954668e+09
I29: DDA | J29: 181228409 | K29: 129936364 | L29: 134027273 | M29: 157001893 | N29: 40429545 | O29: 130045454 | P29: 772668938
I30: DEP | J30: 27617921 | K30: 1.7119322e+08 | L30: 2.5230381e+08 | M30: 1.2067604e+08 | N30: 62156575 | O30: 79488858 | P30: 7.1343642e+08
I31: DES | J31: 289140060 | K31: 2.5750274e+08 | L31: 270815880 | M31: 267801174 | N31: 1.3945091e+08 | O31: 3.2742769e+08 | P31: 1.5521385e+09
I32: DGI | J32: 1271029488 | K32: 1406463891 | L32: 1321970041 | M32: -137844577 | N32: 3434507158 | O32: 1229933471 | P32: 8526059472
I33: DGL | J33: 286168992 | K33: 338984671 | L33: 230154271 | M33: 451087812 | N33: 341520986 | O33: 436919745 | P33: 2084836477
I34: DHC | J34: 73086361 | K34: 73231017 | L34: 80734296 | M34: 85650722 | N34: 83985839 | O34: 146170041 | P34: 542858276
I35: DHI | J35: 218731800 | K35: 172601844 | L35: 161539048 | M35: 196879192 | N35: 201803161 | O35: 125279423 | P35: 1076834468
I36: DIC | J36: 16026670 | K36: 57914174 | L36: 25901536 | M36: 90119211 | N36: 81835932 | O36: 41091978 | P36: 312889501
I37: DIO | J37: 50982594 | K37: 54985753 | L37: 42216285 | M37: 80987512 | N37: 47400975 | O37: 47567549 | P37: 324140668
I38: DPR | J38: 522514884 | K38: 478946114 | L38: 4.0956632e+08 | M38: 5.4676366e+08 | N38: 530145136 | O38: 492863760 | P38: 2980799873
I39: DTC | J39: 1.0186675e+08 | K39: 1.5340891e+08 | L39: 2.1757082e+08 | M39: 1.6916078e+08 | N39: 2.5458868e+08 | O39: 2.1220769e+08 | P39: 1.1088036e+09
I40: SDG | O40: 444000 | P40: 444000
I41: SDO | J41: 3594914 | K41: 198466 | L41: 5612144 | M41: 3876374 | N41: 3868251 | O41: 4465971 | P41: 21616120
I42: Total general | J42: 3.7150929e+09 | K42: 4.1173616e+09 | L42: 3.6396797e+09 | M42: 2.7135035e+09 | N42: 6.583573e+09 | O42: 4.1235514e+09 | P42: 2.4892762e+10
I62: Salesforce | J62: Ene | K62: Feb | L62: Mar | M62: Abr | N62: May | O62: Jun | P62: Jul | Q62: Ago | R62: Sep | S62: Oct | T62: Nov | U62: Dic | V62: Total
I63: DGI | J63: =IFERROR(VLOOKUP($I63,$I$26:$V$42,MATCH(J$62,$I$26:$V$26,0),0),0) -> 1271029488 | K63: =IFERROR(VLOOKUP($I63,$I$26:$V$42,MATCH(K$62,$I$26:$V$26,0),0),0) -> 1406463891 | L63: =IFERROR(VLOOKUP($I63,$I$26:$V$42,MATCH(L$62,$I$26:$V$26,0),0),0) -> 1321970041 | M63: =IFERROR(VLOOKUP($I63,$I$26:$V$42,MATCH(M$62,$I$26:$V$26,0),0),0) -> -137844577 | N63: =IFERROR(VLOOKUP($I63,$I$26:$V$42,MATCH(N$62,$I$26:$V$26,0),0),0) -> 3434507158 | O63: =IFERROR(VLOOKUP($I63,$I$26:$V$42,MATCH(O$62,$I$26:$V$26,0),0),0) -> 1229933471 | P63: =IFERROR(VLOOKUP($I63,$I$26:$V$42,MATCH(P$62,$I$26:$V$26,0),0),0) -> 0 | Q63: =IFERROR(VLOOKUP($I63,$I$26:$V$42,MATCH(Q$62,$I$26:$V$26,0),0),0) -> 0 | ... U63: =IFERROR(VLOOKUP($I63,$I$26:$V$42,MATCH(U$62,$I$26:$V$26,0),0),0) -> 0 | V63: =SUM(J63:U63) -> 8526059472
I83: Diferencia | J83: Ene | K83: Feb | L83: Mar | M83: Abr | N83: May | O83: Jun | P83: Jul | Q83: Ago | R83: Sep | S83: Oct | T83: Nov | U83: Dic | V83: Total
